Workbook
Name SAL_PAGO_ESTADO: SALON!$T$14:$V$14
Name FIT_INS_CUOTA: FITNESS!$B$12:$D$12
Name FIT_INS_MODALIDAD: FITNESS!$P$10:$R$10
Name SAL_PAGO_DNI: SALON!$T$10:$V$10
Name FIT_INS_TURNO: FITNESS!$P$12:$R$12
Name AUL_INS_MODALIDAD: AULA!$P$10:$R$10
Name AUL_INS_HORARIO: AULA!$P$12:$R$12
Name FIT_PAGO_APELLIDO: FITNESS!$T$12:$V$12
Name SAL_INS_TEL: SALON!$J$10:$L$10
Name SAL_INS_INSTRUCTOR: SALON!$K$12:$O$12
Name SAL_INS_NOMBRE: SALON!$B$10:$D$10
Name AUL_INS_APELLIDO: AULA!$E$10:$G$10
Name AUL_PAGO_INSTRUCTOR: AULA!$W$12:$Z$12
Name AUL_PAGO_MONTO: AULA!$AA$12:$AD$12
Name SAL_PAGO_INSTRUCTOR: SALON!$W$12:$Z$12
Name AUL_PAGO_ACTIVIDAD: AULA!$T$12:$V$12
Name FIT_INS_TEL: FITNESS!$J$10:$L$10
Name FIT_INS_OBS: FITNESS!$B$14:$R$14
Name AUL_INS_INSTRUCTOR: AULA!$K$12:$O$12
Name AUL_INS_NOMBRE: AULA!$B$10:$D$10
Name FIT_PAGO_DNI: FITNESS!$T$10:$V$10
Name SAL_INS_DNI: SALON!$H$10:$I$10
Name FIT_INS_APELLIDO: FITNESS!$E$10:$G$10
Name SAL_PAGO_MP: SALON!$W$14:$Z$14
Name FIT_PAGO_MONTO: FITNESS!$W$12:$Z$12
Name SAL_INS_APELLIDO: SALON!$E$10:$G$10
Name FIT_PAGO_ESTADO: FITNESS!$T$14:$V$14
Name FIT_PAGO_NOMBRE: FITNESS!$W$10:$Z$10
Name FIT_INS_DESCUENTO: FITNESS!$E$12:$G$12
Name AUL_INS_CUOTA: AULA!$B$12:$D$12
Name FIT_INS_PROMO: FITNESS!$H$12:$J$12
Name FIT_INS_ENTRENADOR: FITNESS!$K$12:$O$12
Name AUL_PAGO_APELLIDO: AULA!$AA$10:$AD$10
Name AUL_PAGO_DNI: AULA!$T$10:$V$10
Name FIT_INS_DNI: FITNESS!$H$10:$I$10
Name SAL_INS_CUOTA: SALON!$B$12:$D$12
Name AUL_INS_DNI: AULA!$H$10:$I$10
Name SAL_INS_HORARIO: SALON!$P$12:$R$12
Name SAL_PAGO_ACTIVIDAD: SALON!$T$12:$V$12
Name AUL_PAGO_MP: AULA!$W$14:$Z$14
Name SAL_INS_MODALIDAD: SALON!$P$10:$R$10
Name SAL_INS_ACTIVIDAD: SALON!$M$10:$O$10
Name SAL_PAGO_APELLIDO: SALON!$AA$10:$AD$10
Name FIT_INS_ACTIVIDAD: FITNESS!$M$10:$O$10
Name AUL_PAGO_NOMBRE: AULA!$W$10:$Z$10
Name SAL_PAGO_NOMBRE: SALON!$W$10:$Z$10
Name AUL_INS_TEL: AULA!$J$10:$L$10
Name AUL_PAGO_ESTADO: AULA!$T$14:$V$14
Name FIT_INS_NOMBRE: FITNESS!$B$10:$D$10
Name AUL_INS_ACTIVIDAD: AULA!$M$10:$O$10
Name SAL_PAGO_MONTO: SALON!$AA$12:$AD$12
Name FIT_PAGO_MP: FITNESS!$W$14:$Z$14

Sheet DASHBOARD
C2: LOCAL 1 | J2: CANCHA FÚTBOL 5 | AE2: ESPACIO FITNESS | AQ2: SALÓN SUPERIOR | AY2: =TODAY() -> 46227 | BE2: CAPITAL | BJ2: +/- 30 DÍAS
AY3: =NOW() -> 46227.681 | BB3: =MONTH(TODAY()) -> 7 | BE3: ='ADMINISTRACIÓN'!AD12 -> 2498829 | BJ3: =IFERROR(SUMIFS('ADMINISTRACIÓN'!$U$13:$U$2003,'ADMINISTRACIÓN'!$E$13:$E$2003,"INGRESOS",'ADMINISTRACIÓN'!$C$13:$C$2003,">="&($AY$2-30),'ADMINISTRACIÓN'!$C$13:$C$2003,"<="&$AY$2)-SUMIFS('ADMINISTRACIÓN'!$U$13:$U$2003,'ADMINISTRACIÓN'!$E$13:$E$2003,"EGRESOS",'ADMINISTRACIÓN'!$C$13:$C$2003,">="&($AY$2-30),'ADMINISTRACIÓN'!$C$13:$C$2003,"<="&$AY$2),0) -> -546616
AY4: ------------------------------------------------------------------------------------
AY5: INGRESOS | BB5: JULIO | BG5: GASTOS | BK5: +/-
AY6: =IF(OR($BB$5="ENERO",$BB$5="MARZO",$BB$5="MAYO",$BB$5="JULIO",$BB$5="SEPTIEMBRE",$BB$5="NOVIEMBRE"),VLOOKUP($BB$5,'ADMINISTRACIÓN'!$B$3:$E$8,3,FALSE),VLOOKUP($BB$5,'ADMINISTRACIÓN'!$F3:$I8,3,FALSE)) -> 4967369 | BE6: =IF(OR($BB$5="ENERO",$BB$5="MARZO",$BB$5="MAYO",$BB$5="JULIO",$BB$5="SEPTIEMBRE",$BB$5="NOVIEMBRE"),VLOOKUP($BB$5,'ADMINISTRACIÓN'!$K$3:$N$8,3,FALSE),VLOOKUP($BB$5,'ADMINISTRACIÓN'!$O3:$R8,3,FALSE)) -> -5593840 | BK6: =AY6+BE6 -> -626471
AY8: $ LOCAL 1 | BD8: 0 | BL8: ESTADO
AY9: $ LOCAL 2 | BD9: 0 | BL9: ESTADO
C10: LOCAL 2 | AY10: $ CANCHA 1 | BD10: 0 | BL10: ESTADO
AY11: $ FITNESS | BD11: 0 | BL11: ESTADO
AY12: $ CANTINA | BD12: 0 | BL12: ESTADO
AY13: $ SALÓN | BD13: 0 | BL13: ESTADO
AY14: $ AULA | BD14: 0 | BL14: ESTADO
AY15: $ OTROS | BD15: 0 | BL15: ESTADO
AY16: $ TESORERÍA | BD16: 0 | BL16: ESTADO
F18: ADMINISTRACIÓN | U18: CANTINA | AA18: BAÑOS | AQ18: AULA SUPERIOR | AY18: ALQUILER | BC18: {=LET( mesTxt, LOWER(TRIM($BB$5)), meses, {"enero";"febrero";"marzo";"abril";"mayo";"junio";"julio";"agosto";"septiembre";"octubre";"noviembre";"diciembre"}, mesNum, IFERROR(MATCH(mesTxt, meses, 0), 0), anio, YEAR($AY$2), inicio, DATE(anio, mesNum, 1), finExcl, EDATE(inicio, 1), gasto, UPPER(TRIM(AY18)), existe, IF( mesNum=0, FALSE, COUNTIFS( 'ADMINISTRACIÓN'!$C$13:$C$2003, ">="&inicio, 'ADMINISTRACIÓN'!$C$13:$C$2003, "<"&finExcl, 'ADMINISTRACIÓN'!$H$13:$H$2003, gasto )>0 ), IF( mesNum=0, "MES INVÁLIDO", IF(existe, "PAGADO", IF(mesNum=$BB$3, "PENDIENTE", "IMPAGO")) ) )} -> PAGADO | BG18: LUZ | BK18: {=LET( mesTxt, LOWER(TRIM($BB$5)), meses, {"enero";"febrero";"marzo";"abril";"mayo";"junio";"julio";"agosto";"septiembre";"octubre";"noviembre";"diciembre"}, mesNum, IFERROR(MATCH(mesTxt, meses, 0), 0), anio, YEAR($AY$2), inicio, DATE(anio, mesNum, 1), finExcl, EDATE(inicio, 1), gasto, UPPER(TRIM(BG18)), existe, IF( mesNum=0, FALSE, COUNTIFS( 'ADMINISTRACIÓN'!$C$13:$C$2003, ">="&inicio, 'ADMINISTRACIÓN'!$C$13:$C$2003, "<"&finExcl, 'ADMINISTRACIÓN'!$H$13:$H$2003, gasto )>0 ), IF( mesNum=0, "MES INVÁLIDO", IF(existe, "PAGADO", IF(mesNum=$BB$3, "PENDIENTE", "IMPAGO")) ) )} -> PAGADO
AY19: AGUA | BC19: {=LET( mesTxt, LOWER(TRIM($BB$5)), meses, {"enero";"febrero";"marzo";"abril";"mayo";"junio";"julio";"agosto";"septiembre";"octubre";"noviembre";"diciembre"}, mesNum, IFERROR(MATCH(mesTxt, meses, 0), 0), anio, YEAR($AY$2), inicio, DATE(anio, mesNum, 1), finExcl, EDATE(inicio, 1), gasto, UPPER(TRIM(AY19)), existe, IF( mesNum=0, FALSE, COUNTIFS( 'ADMINISTRACIÓN'!$C$13:$C$2003, ">="&inicio, 'ADMINISTRACIÓN'!$C$13:$C$2003, "<"&finExcl, 'ADMINISTRACIÓN'!$H$13:$H$2003, gasto )>0 ), IF( mesNum=0, "MES INVÁLIDO", IF(existe, "PAGADO", IF(mesNum=$BB$3, "PENDIENTE", "IMPAGO")) ) )} -> PAGADO | BG19: INTERNET | BK19: {=LET( mesTxt, LOWER(TRIM($BB$5)), meses, {"enero";"febrero";"marzo";"abril";"mayo";"junio";"julio";"agosto";"septiembre";"octubre";"noviembre";"diciembre"}, mesNum, IFERROR(MATCH(mesTxt, meses, 0), 0), anio, YEAR($AY$2), inicio, DATE(anio, mesNum, 1), finExcl, EDATE(inicio, 1), gasto, UPPER(TRIM(BG19)), existe, IF( mesNum=0, FALSE, COUNTIFS( 'ADMINISTRACIÓN'!$C$13:$C$2003, ">="&inicio, 'ADMINISTRACIÓN'!$C$13:$C$2003, "<"&finExcl, 'ADMINISTRACIÓN'!$H$13:$H$2003, gasto )>0 ), IF( mesNum=0, "MES INVÁLIDO", IF(existe, "PAGADO", IF(mesNum=$BB$3, "PENDIENTE", "IMPAGO")) ) )} -> PAGADO
AY20: IMPUESTOS | BC20: {=LET( mesTxt, LOWER(TRIM($BB$5)), meses, {"enero";"febrero";"marzo";"abril";"mayo";"junio";"julio";"agosto";"septiembre";"octubre";"noviembre";"diciembre"}, mesNum, IFERROR(MATCH(mesTxt, meses, 0), 0), anio, YEAR($AY$2), inicio, DATE(anio, mesNum, 1), finExcl, EDATE(inicio, 1), gasto, UPPER(TRIM(AY20)), existe, IF( mesNum=0, FALSE, COUNTIFS( 'ADMINISTRACIÓN'!$C$13:$C$2003, ">="&inicio, 'ADMINISTRACIÓN'!$C$13:$C$2003, "<"&finExcl, 'ADMINISTRACIÓN'!$H$13:$H$2003, gasto )>0 ), IF( mesNum=0, "MES INVÁLIDO", IF(existe, "PAGADO", IF(mesNum=$BB$3, "PENDIENTE", "IMPAGO")) ) )} -> PAGADO | BG20: SALARIOS | BK20: {=LET( mesTxt, LOWER(TRIM($BB$5)), meses, {"enero";"febrero";"marzo";"abril";"mayo";"junio";"julio";"agosto";"septiembre";"octubre";"noviembre";"diciembre"}, mesNum, IFERROR(MATCH(mesTxt, meses, 0), 0), anio, YEAR($AY$2), inicio, DATE(anio, mesNum, 1), finExcl, EDATE(inicio, 1), gasto, UPPER(TRIM(BG20)), existe, IF( mesNum=0, FALSE, COUNTIFS( 'ADMINISTRACIÓN'!$C$13:$C$2003, ">="&inicio, 'ADMINISTRACIÓN'!$C$13:$C$2003, "<"&finExcl, 'ADMINISTRACIÓN'!$H$13:$H$2003, gasto )>0 ), IF( mesNum=0, "MES INVÁLIDO", IF(existe, "PAGADO", IF(mesNum=$BB$3, "PENDIENTE", "IMPAGO")) ) )} -> PENDIENTE
AY22: SECTOR +++ | BD22: SECTOR ---

Sheet ADMINISTRACIÓN
B2: INGRESOS | K2: GASTOS | T2: UTILIDAD | AD2: AGREGAR MOVIMIENTO
B3: Enero | D3: =SUMIFS($U$13:$U$2004,$C$13:$C$2004,">="&DATE(2026,1,1),$C$13:$C$2004,"<"&DATE(2026,2,1),$E$13:$E$2004,"INGRESOS",$Z$13:$Z$2004,"COMPLETADO") -> 0 | F3: Febrero | H3: =SUMIFS($U$13:$U$2004,$C$13:$C$2004,">="&DATE(2026,2,1),$C$13:$C$2004,"<"&DATE(2026,3,1),$E$13:$E$2004,"INGRESOS",$Z$13:$Z$2004,"COMPLETADO") -> 0 | K3: Enero | M3: =-(SUMIFS($U$13:$U$2004,$C$13:$C$2004,">="&DATE(2026,1,1),$C$13:$C$2004,"<"&DATE(2026,2,1),$E$13:$E$2004,"EGRESOS",$Z$13:$Z$2004,"COMPLETADO") -SUMIFS($U$13:$U$2004,$C$13:$C$2004,">="&DATE(2026,1,1),$C$13:$C$2004,"<"&DATE(2026,2,1),$E$13:$E$2004,"EGRESOS",$H$13:$H$2004,"DÓLARES",$Z$13:$Z$2004,"COMPLETADO")) -> 0 | O3: Febrero | Q3: =-(SUMIFS($U$13:$U$2004,$C$13:$C$2004,">="&DATE(2026,2,1),$C$13:$C$2004,"<"&DATE(2026,3,1),$E$13:$E$2004,"EGRESOS",$Z$13:$Z$2004,"COMPLETADO") -SUMIFS($U$13:$U$2004,$C$13:$C$2004,">="&DATE(2026,2,1),$C$13:$C$2004,"<"&DATE(2026,3,1),$E$13:$E$2004,"EGRESOS",$H$13:$H$2004,"DÓLARES",$Z$13:$Z$2004,"COMPLETADO")) -> -100000 | T3: Enero | V3: =D3+M3 -> 0 | X3: Febrero | Z3: =H3+Q3 -> -100000 | AD3: Tipo | AF3: Categ. | AI3: Sector
B4: Marzo | D4: =SUMIFS($U$13:$U$2004,$C$13:$C$2004,">="&DATE(2026,3,1),$C$13:$C$2004,"<"&DATE(2026,4,1),$E$13:$E$2004,"INGRESOS",$Z$13:$Z$2004,"COMPLETADO") -> 1083501 | F4: Abril | H4: =SUMIFS($U$13:$U$2004,$C$13:$C$2004,">="&DATE(2026,4,1),$C$13:$C$2004,"<"&DATE(2026,5,1),$E$13:$E$2004,"INGRESOS",$Z$13:$Z$2004,"COMPLETADO") -> 4289262 | K4: Marzo | M4: =-(SUMIFS($U$13:$U$2004,$C$13:$C$2004,">="&DATE(2026,3,1),$C$13:$C$2004,"<"&DATE(2026,4,1),$E$13:$E$2004,"EGRESOS",$Z$13:$Z$2004,"COMPLETADO") -SUMIFS($U$13:$U$2004,$C$13:$C$2004,">="&DATE(2026,3,1),$C$13:$C$2004,"<"&DATE(2026,4,1),$E$13:$E$2004,"EGRESOS",$H$13:$H$2004,"DÓLARES",$Z$13:$Z$2004,"COMPLETADO")) -> -11319563 | O4: Abril | Q4: =-(SUMIFS($U$13:$U$2004,$C$13:$C$2004,">="&DATE(2026,4,1),$C$13:$C$2004,"<"&DATE(2026,5,1),$E$13:$E$2004,"EGRESOS",$Z$13:$Z$2004,"COMPLETADO") -SUMIFS($U$13:$U$2004,$C$13:$C$2004,">="&DATE(2026,4,1),$C$13:$C$2004,"<"&DATE(2026,5,1),$E$13:$E$2004,"EGRESOS",$H$13:$H$2004,"DÓLARES",$Z$13:$Z$2004,"COMPLETADO")) -> -5157136 | T4: Marzo | V4: =D4+M4 -> -10236062 | X4: Abril | Z4: =H4+Q4 -> -867874
B5: Mayo | D5: =SUMIFS($U$13:$U$2004,$C$13:$C$2004,">="&DATE(2026,5,1),$C$13:$C$2004,"<"&DATE(2026,6,1),$E$13:$E$2004,"INGRESOS",$Z$13:$Z$2004,"COMPLETADO") -> 4296109 | F5: Junio | H5: =SUMIFS($U$13:$U$2004,$C$13:$C$2004,">="&DATE(2026,6,1),$C$13:$C$2004,"<"&DATE(2026,7,1),$E$13:$E$2004,"INGRESOS",$Z$13:$Z$2004,"COMPLETADO") -> 5622517 | K5: Mayo | M5: =-(SUMIFS($U$13:$U$2004,$C$13:$C$2004,">="&DATE(2026,5,1),$C$13:$C$2004,"<"&DATE(2026,6,1),$E$13:$E$2004,"EGRESOS",$Z$13:$Z$2004,"COMPLETADO") -SUMIFS($U$13:$U$2004,$C$13:$C$2004,">="&DATE(2026,5,1),$C$13:$C$2004,"<"&DATE(2026,6,1),$E$13:$E$2004,"EGRESOS",$H$13:$H$2004,"DÓLARES",$Z$13:$Z$2004,"COMPLETADO")) -> -4714283 | O5: Junio | Q5: =-(SUMIFS($U$13:$U$2004,$C$13:$C$2004,">="&DATE(2026,6,1),$C$13:$C$2004,"<"&DATE(2026,7,1),$E$13:$E$2004,"EGRESOS",$Z$13:$Z$2004,"COMPLETADO") -SUMIFS($U$13:$U$2004,$C$13:$C$2004,">="&DATE(2026,6,1),$C$13:$C$2004,"<"&DATE(2026,7,1),$E$13:$E$2004,"EGRESOS",$H$13:$H$2004,"DÓLARES",$Z$13:$Z$2004,"COMPLETADO")) -> -5626507 | T5: Mayo | V5: =D5+M5 -> -418174 | X5: Junio | Z5: =H5+Q5 -> -3990 | AD5: Concepto | AH5: Monto $
B6: Julio | D6: =SUMIFS($U$13:$U$2004,$C$13:$C$2004,">="&DATE(2026,7,1),$C$13:$C$2004,"<"&DATE(2026,8,1),$E$13:$E$2004,"INGRESOS",$Z$13:$Z$2004,"COMPLETADO") -> 4967369 | F6: Agosto | H6: =SUMIFS($U$13:$U$2004,$C$13:$C$2004,">="&DATE(2026,8,1),$C$13:$C$2004,"<"&DATE(2026,9,1),$E$13:$E$2004,"INGRESOS",$Z$13:$Z$2004,"COMPLETADO") -> 0 | K6: Julio | M6: =-(SUMIFS($U$13:$U$2004,$C$13:$C$2004,">="&DATE(2026,7,1),$C$13:$C$2004,"<"&DATE(2026,8,1),$E$13:$E$2004,"EGRESOS",$Z$13:$Z$2004,"COMPLETADO") -SUMIFS($U$13:$U$2004,$C$13:$C$2004,">="&DATE(2026,7,1),$C$13:$C$2004,"<"&DATE(2026,8,1),$E$13:$E$2004,"EGRESOS",$H$13:$H$2004,"DÓLARES",$Z$13:$Z$2004,"COMPLETADO")) -> -5593840 | O6: Agosto | Q6: =-(SUMIFS($U$13:$U$2004,$C$13:$C$2004,">="&DATE(2026,8,1),$C$13:$C$2004,"<"&DATE(2026,9,1),$E$13:$E$2004,"EGRESOS",$Z$13:$Z$2004,"COMPLETADO") -SUMIFS($U$13:$U$2004,$C$13:$C$2004,">="&DATE(2026,8,1),$C$13:$C$2004,"<"&DATE(2026,9,1),$E$13:$E$2004,"EGRESOS",$H$13:$H$2004,"DÓLARES",$Z$13:$Z$2004,"COMPLETADO")) -> 0 | T6: Julio | V6: =D6+M6 -> -626471 | X6: Agosto | Z6: =H6+Q6 -> 0
B7: Septiembre | D7: =SUMIFS($U$13:$U$2004,$C$13:$C$2004,">="&DATE(2026,9,1),$C$13:$C$2004,"<"&DATE(2026,10,1),$E$13:$E$2004,"INGRESOS",$Z$13:$Z$2004,"COMPLETADO") -> 0 | F7: Octubre | H7: =SUMIFS($U$13:$U$2004,$C$13:$C$2004,">="&DATE(2026,10,1),$C$13:$C$2004,"<"&DATE(2026,11,1),$E$13:$E$2004,"INGRESOS",$Z$13:$Z$2004,"COMPLETADO") -> 0 | K7: Septiembre | M7: =-(SUMIFS($U$13:$U$2004,$C$13:$C$2004,">="&DATE(2026,9,1),$C$13:$C$2004,"<"&DATE(2026,10,1),$E$13:$E$2004,"EGRESOS",$Z$13:$Z$2004,"COMPLETADO") -SUMIFS($U$13:$U$2004,$C$13:$C$2004,">="&DATE(2026,9,1),$C$13:$C$2004,"<"&DATE(2026,10,1),$E$13:$E$2004,"EGRESOS",$H$13:$H$2004,"DÓLARES",$Z$13:$Z$2004,"COMPLETADO")) -> 0 | O7: Octubre | Q7: =-(SUMIFS($U$13:$U$2004,$C$13:$C$2004,">="&DATE(2026,10,1),$C$13:$C$2004,"<"&DATE(2026,11,1),$E$13:$E$2004,"EGRESOS",$Z$13:$Z$2004,"COMPLETADO") -SUMIFS($U$13:$U$2004,$C$13:$C$2004,">="&DATE(2026,4,1),$C$13:$C$2004,"<"&DATE(2026,5,1),$E$13:$E$2004,"EGRESOS",$H$13:$H$2004,"DÓLARES",$Z$13:$Z$2004,"COMPLETADO")) -> 0 | T7: Septiembre | V7: =D7+M7 -> 0 | X7: Octubre | Z7: =H7+Q7 -> 0 | AD7: Contra-parte (D.N.I.)
B8: Noviembre | D8: =SUMIFS($U$13:$U$2004,$C$13:$C$2004,">="&DATE(2026,11,1),$C$13:$C$2004,"<"&DATE(2026,12,1),$E$13:$E$2004,"INGRESOS",$Z$13:$Z$2004,"COMPLETADO") -> 0 | F8: Diciembre | H8: =SUMIFS($U$13:$U$2004,$C$13:$C$2004,">="&DATE(2026,12,1),$C$13:$C$2004,"<"&DATE(2027,1,1),$E$13:$E$2004,"INGRESOS",$Z$13:$Z$2004,"COMPLETADO") -> 0 | K8: Noviembre | M8: =-(SUMIFS($U$13:$U$2004,$C$13:$C$2004,">="&DATE(2026,11,1),$C$13:$C$2004,"<"&DATE(2026,12,1),$E$13:$E$2004,"EGRESOS",$Z$13:$Z$2004,"COMPLETADO") -SUMIFS($U$13:$U$2004,$C$13:$C$2004,">="&DATE(2026,4,1),$C$13:$C$2004,"<"&DATE(2026,5,1),$E$13:$E$2004,"EGRESOS",$H$13:$H$2004,"DÓLARES",$Z$13:$Z$2004,"COMPLETADO")) -> 0 | O8: Diciembre | Q8: =-(SUMIFS($U$13:$U$2004,$C$13:$C$2004,">="&DATE(2026,12,1),$C$13:$C$2004,"<"&DATE(2027,1,1),$E$13:$E$2004,"EGRESOS",$Z$13:$Z$2004,"COMPLETADO") -SUMIFS($U$13:$U$2004,$C$13:$C$2004,">="&DATE(2026,4,1),$C$13:$C$2004,"<"&DATE(2026,5,1),$E$13:$E$2004,"EGRESOS",$H$13:$H$2004,"DÓLARES",$Z$13:$Z$2004,"COMPLETADO")) -> 0 | T8: Noviembre | V8: =D8+M8 -> 0 | X8: Diciembre | Z8: =H8+Q8 -> 0 | AD8: Impuesto | AF8: 0 | AG8: M.P.
B9: TOTAL | F9: =SUM(D3:E8,H3:I8) -> 20258758 | K9: TOTAL | O9: =SUM(M3:N8,Q3:R8) -> -32511329 | T9: TOTAL | X9: =SUM(V3:W8,Z3:AA8) -> -12252571 | AD9: AGREGAR
B11: MOVIMIENTOS | AD11: CAJA Y BANCOS
B12: Id. | C12: Fecha | E12: Tipo | H12: Categoría | K12: Concepto | P12: Contra-parte | S12: Sector | U12: Monto | X12: Impuestos | Z12: Estado | AB12: M.P. | AD12: =SUMIFS($U$13:$U$2004,$E$13:$E$2004,"CAPITAL",$Z$13:$Z$2004,"COMPLETADO")-SUMIFS($U$13:$U$2004,$E$13:$E$2004,"CAPITAL",$H$13:$H$2004,"DÓLARES",$Z$13:$Z$2004,"COMPLETADO")+X9+(AG14*AF14) -> 2498829 | AG12: =SUMIFS($U$13:$U$2004,$E$13:$E$2004,"INGRESOS",$AB$13:$AB$2004,"Efectivo",$Z$13:$Z$2004,"COMPLETADO")+SUMIFS($U$13:$U$2004,$E$13:$E$2004,"CAPITAL",$AB$13:$AB$2004,"Efectivo",$Z$13:$Z$2004,"COMPLETADO")-SUMIFS($U$13:$U$2004,$E$13:$E$2004,"EGRESOS",$AB$13:$AB$2004,"Efectivo",$Z$13:$Z$2004,"COMPLETADO") -> 1812430 | AI12: Efectivo | AK12: PROYECTADO
B13: I-1038 | C13: 46227.655 | E13: INGRESOS | H13: CUOTA | K13: Pago de cuota [F-0027] de Patricia Feldick por actividad de Funcional | P13: 20.118.913 | S13: FITNESS | U13: 0 | X13: 0 | Z13: COMPLETADO | AB13: Efectivo | AG13: =SUMIFS($U$13:$U$2004,$E$13:$E$2004,"INGRESOS",$AB$13:$AB$2004,"Transferencia",$Z$13:$Z$2004,"COMPLETADO")+SUMIFS($U$13:$U$2004,$E$13:$E$2004,"CAPITAL",$AB$13:$AB$2004,"Transferencia",$Z$13:$Z$2004,"COMPLETADO")-SUMIFS($U$13:$U$2004,$E$13:$E$2004,"EGRESOS",$AB$13:$AB$2004,"Transferencia",$Z$13:$Z$2004,"COMPLETADO") -> 535399 | AI13: Cuenta Corriente | AK13: =$AD$12+SUMIFS($U$13:$U$2004,$E$13:$E$2004,"INGRESOS",$Z$13:$Z$2004,"PENDIENTE")-SUMIFS($U$13:$U$2004,$E$13:$E$2004,"EGRESOS",$Z$13:$Z$2004,"PENDIENTE")+($AF$14*(SUMIFS($U$13:$U$2004,$H$13:$H$2004,"DÓLARES",$Z$13:$Z$2004,"PENDIENTE")))-'LOCAL 1'!X3-FITNESS!X3-SALON!AB19-AULA!AB19 -> 1711829
B14: E-1037 | C14: 46226.954 | E14: EGRESOS | H14: IMPUESTOS | K14: Retención IIBB SIRCUPA | P14: 67.238.712 | S14: TESORERÍA | U14: 3000 | X14: 0 | Z14: COMPLETADO | AB14: Transferencia | AD14: Tipo de cambio → | AF14: 1510 | AG14: =SUMIFS($U$13:$U$2004,$E$13:$E$2004,"INGRESOS",$H$13:$H$2004,"DÓLARES",$Z$13:$Z$2004,"COMPLETADO")+SUMIFS($U$13:$U$2004,$E$13:$E$2004,"CAPITAL",$H$13:$H$2004,"DÓLARES",$Z$13:$Z$2004,"COMPLETADO")-SUMIFS($U$13:$U$2004,$E$13:$E$2004,"EGRESOS",$H$13:$H$2004,"DÓLARES",$Z$13:$Z$2004,"COMPLETADO") -> 100 | AI14: Dólares
B15: I-1036 | C15: 46226.844 | E15: INGRESOS | H15: VENTAS | K15: Seña Tattoo - Minitattoo Silvina | P15: 35.872.158 | S15: LOCAL 1 | U15: 20000 | X15: 0 | Z15: COMPLETADO | AB15: Transferencia
B16: I-1035 | C16: 46226.842 | E16: INGRESOS | H16: VENTAS | K16: Seña Tattoo - Mundialista Pamela | P16: 35.872.158 | S16: LOCAL 1 | U16: 40000 | X16: 0 | Z16: COMPLETADO | AB16: Transferencia | AD16: INFO SECTORES
B17: E-1034 | C17: 46226.7 | E17: EGRESOS | H17: EXTRACCIONES | K17: Conciliación de caja y banco - contra I-1033 | P17: 35.004.264 | S17: TESORERÍA | U17: 20000 | X17: 0 | Z17: COMPLETADO | AB17: Transferencia | AD17: SECTOR | AF17: INGRESOS | AH17: EGRESOS | AJ17: VOL. | AK17: UTILIDAD
B18: I-1033 | C18: 46226.698 | E18: INGRESOS | H18: DEPÓSITOS | K18: Conciliación de caja y banco - contra E-1034 | P18: 35.004.264 | S18: TESORERÍA | U18: 20000 | X18: 0 | Z18: COMPLETADO | AB18: Efectivo | AD18: LOCAL 1 | AF18: =SUMIFS($U$13:$U$2004,$S$13:$S$2004,AD18,$E$13:$E$2004,$AF$17,$Z13:$Z2004,"COMPLETADO") -> 6734800 | AH18: =SUMIFS($U$13:$U$2004,$S$13:$S$2004,AD18,$E$13:$E$2004,$AH$17,$Z13:$Z2004,"COMPLETADO")*-1 -> -3657365 | AJ18: =COUNTIF($S$13:$S$2004,AD18) -> 163 | AK18: =AF18+AH18 -> 3077435
B19: E-1032 | C19: 46226.591 | E19: EGRESOS | H19: COMISIÓN | K19: Pago de SALDO A LIQUIDAR - 23/7/2026 | P19: 35.872.158 | S19: LOCAL 1 | U19: 45000 | X19: 0 | Z19: COMPLETADO | AB19: Transferencia | AD19: LOCAL 2 | AF19: =SUMIFS($U$13:$U$2004,$S$13:$S$2004,AD19,$E$13:$E$2004,$AF$17,$Z13:$Z2004,"COMPLETADO") -> 0 | AH19: =SUMIFS($U$13:$U$2004,$S$13:$S$2004,AD19,$E$13:$E$2004,$AH$17,$Z13:$Z2004,"COMPLETADO")*-1 -> -88825 | AJ19: =COUNTIF($S$13:$S$2004,AD19) -> 3 | AK19: =AF19+AH19 -> -88825
B20: I-1031 | C20: 46226.59 | E20: INGRESOS | H20: VENTAS | K20: Seña Tattoo - minitattoos en la mano Virginia | P20: 35.872.158 | S20: LOCAL 1 | U20: 30000 | X20: 0 | Z20: COMPLETADO | AB20: Transferencia | AD20: CANCHA 1 | AF20: =SUMIFS($U$13:$U$2004,$S$13:$S$2004,AD20,$E$13:$E$2004,$AF$17,$Z13:$Z2004,"COMPLETADO") -> 0 | AH20: =SUMIFS($U$13:$U$2004,$S$13:$S$2004,AD20,$E$13:$E$2004,$AH$17,$Z13:$Z2004,"COMPLETADO")*-1 -> -100000 | AJ20: =COUNTIF($S$13:$S$2004,AD20) -> 1 | AK20: =AF20+AH20 -> -100000
B21: E-1030 | C21: 46226.588 | E21: EGRESOS | H21: LIMPIEZA | K21: Papel Higiénico + naftalina + lavandina + trapos | P21: 24.600.903 | S21: OTROS | U21: 34800 | X21: 0 | Z21: COMPLETADO | AB21: Transferencia | AD21: FITNESS | AF21: =SUMIFS($U$13:$U$2004,$S$13:$S$2004,AD21,$E$13:$E$2004,$AF$17,$Z13:$Z2004,"COMPLETADO") -> 8025500 | AH21: =SUMIFS($U$13:$U$2004,$S$13:$S$2004,AD21,$E$13:$E$2004,$AH$17,$Z13:$Z2004,"COMPLETADO")*-1 -> -4147367 | AJ21: =COUNTIF($S$13:$S$2004,AD21) -> 315 | AK21: =AF21+AH21 -> 3878133
B22: E-1029 | C22: 46226.536 | E22: EGRESOS | H22: AGUA | K22: SAMSA - Período 6/26 - 38mts cúbicos | P22: 69.809.590 | S22: OTROS | U22: 177442 | X22: 0 | Z22: COMPLETADO | AB22: Transferencia | AD22: CANTINA | AF22: =SUMIFS($U$13:$U$2004,$S$13:$S$2004,AD22,$E$13:$E$2004,$AF$17,$Z13:$Z2004,"COMPLETADO") -> 763017 | AH22: =SUMIFS($U$13:$U$2004,$S$13:$S$2004,AD22,$E$13:$E$2004,$AH$17,$Z13:$Z2004,"COMPLETADO")*-1 -> -1660925 | AJ22: =COUNTIF($S$13:$S$2004,AD22) -> 63 | AK22: =AF22+AH22 -> -897908
B23: I-1028 | C23: 46225.829 | E23: INGRESOS | H23: CUOTA | K23: Pago de cuota [F-0018] de Silvina Molina por actividad de Funcional | P23: 33.720.939 | S23: FITNESS | U23: 30000 | X23: 0 | Z23: COMPLETADO | AB23: Transferencia | AD23: SALON | AF23: =SUMIFS($U$13:$U$2004,$S$13:$S$2004,AD23,$E$13:$E$2004,$AF$17,$Z13:$Z2004,"COMPLETADO") -> 2527500 | AH23: =SUMIFS($U$13:$U$2004,$S$13:$S$2004,AD23,$E$13:$E$2004,$AH$17,$Z13:$Z2004,"COMPLETADO")*-1 -> -1227050 | AJ23: =COUNTIF($S$13:$S$2004,AD23) -> 131 | AK23: =AF23+AH23 -> 1300450
B24: E-1027 | C24: 46225.741 | E24: EGRESOS | H24: IMPUESTOS | K24: Retención IIBB SIRCUPA | P24: 67.238.712 | S24: TESORERÍA | U24: 4850 | X24: 0 | Z24: COMPLETADO | AB24: Transferencia | AD24: AULA | AF24: =SUMIFS($U$13:$U$2004,$S$13:$S$2004,AD24,$E$13:$E$2004,$AF$17,$Z13:$Z2004,"COMPLETADO") -> 835000 | AH24: =SUMIFS($U$13:$U$2004,$S$13:$S$2004,AD24,$E$13:$E$2004,$AH$17,$Z13:$Z2004,"COMPLETADO")*-1 -> -497000 | AJ24: =COUNTIF($S$13:$S$2004,AD24) -> 52 | AK24: =AF24+AH24 -> 338000
B25: I-1026 | C25: 46225.71 | E25: INGRESOS | H25: CUOTA | K25: Pago de cuota [C-0139] de Cristian Gimenez por actividad de Complemento | P25: 33.486.350 | S25: FITNESS | U25: 30000 | X25: 0 | Z25: COMPLETADO | AB25: Transferencia | AD25: TESORERÍA | AF25: =SUMIFS($U$13:$U$2004,$S$13:$S$2004,AD25,$E$13:$E$2004,$AF$17)+SUMIFS($U$13:$U$2004,$S$13:$S$2004,AD25,$E$13:$E$2004,"CAPITAL",$U$13:$U$2004,">0",$Z13:$Z2004,"COMPLETADO") -> 16124841 | AH25: =(SUMIFS($U$13:$U$2004,$S$13:$S$2004,AD25,$E$13:$E$2004,$AH$17)*-1)+SUMIFS($U$13:$U$2004,$S$13:$S$2004,AD25,$E$13:$E$2004,"CAPITAL",$U$13:$U$2004,"<0",$Z13:$Z2004,"COMPLETADO") -> -16416451 | AJ25: =COUNTIF($S$13:$S$2004,AD25) -> 222 | AK25: =AF25+AH25 -> -291610
B26: I-1025 | C26: 46225.708 | E26: INGRESOS | H26: CUOTA | K26: Pago de cuota [C-0138] de Daniela Soto por actividad de Complemento | P26: 32.608.369 | S26: FITNESS | U26: 30000 | X26: 0 | Z26: COMPLETADO | AB26: Transferencia | AD26: OTROS | AF26: =SUMIFS($U$13:$U$2004,$S$13:$S$2004,AD26,$E$13:$E$2004,$AF$17,$Z13:$Z2004,"COMPLETADO") -> 0 | AH26: =SUMIFS($U$13:$U$2004,$S$13:$S$2004,AD26,$E$13:$E$2004,$AH$17,$Z13:$Z2004,"COMPLETADO")*-1 -> -4883846 | AJ26: =COUNTIF($S$13:$S$2004,AD26) -> 88 | AK26: =AF26+AH26 -> -4883846
B27: E-1024 | C27: 46225.704 | E27: EGRESOS | H27: COMISIÓN | K27: Pago de SALDO A LIQUIDAR - 22/7/2026 | P27: 35.872.158 | S27: LOCAL 1 | U27: 150000 | X27: 0 | Z27: COMPLETADO | AB27: Efectivo
B28: I-1023 | C28: 46225.702 | E28: INGRESOS | H28: VENTAS | K28: Tattoo - Manga floral Isabel | P28: 35.872.158 | S28: LOCAL 1 | U28: 300000 | X28: 0 | Z28: COMPLETADO | AB28: Efectivo | AD28: INFO CATEGORÍAS
B29: E-1022 | C29: 46225.699 | E29: EGRESOS | H29: COMISIÓN | K29: Pago de SALDO A LIQUIDAR - 22/7/2026 | P29: 35.872.158 | S29: LOCAL 1 | U29: 25000 | X29: 0 | Z29: COMPLETADO | AB29: Transferencia | AD29: CATEG. | AF29: INGRESOS | AH29: EGRESOS | AJ29: VOL. | AK29: UTILIDAD
B30: I-1021 | C30: 46225.697 | E30: INGRESOS | H30: VENTAS | K30: Seña Tattoo - Proyecto cobertura cicatrices Paula | P30: 35.872.158 | S30: LOCAL 1 | U30: 50000 | X30: 0 | Z30: COMPLETADO | AB30: Transferencia | AD30: INSCRIPCIÓN | AF30: =SUMIFS($U$13:$U$2004,$H$13:$H$2004,AD30,$E$13:$E$2004,$AF$29) -> 0 | AH30: =SUMIFS($U$13:$U$2004,$H$13:$H$2004,AD30,$E$13:$E$2004,$AH$29,$Z13:$Z2004,"COMPLETADO")*-1 -> 0 | AJ30: =COUNTIF($H$13:$H$2004,AD30) -> 0 | AK30: =AF30+AH30 -> 0
B31: I-1020 | C31: 46224.925 | E31: INGRESOS | H31: CUOTA | K31: Pago de cuota [K-0075] de Ginna Caruso por clases de Kickboxing al profesor Natalia Ortiz | P31: 37.704.699 | S31: SALON | U31: 20000 | X31: 0 | Z31: COMPLETADO | AB31: Efectivo | AD31: CUOTA | AF31: =SUMIFS($U$13:$U$2004,$H$13:$H$2004,AD31,$E$13:$E$2004,$AF$29) -> 10629500 | AH31: =SUMIFS($U$13:$U$2004,$H$13:$H$2004,AD31,$E$13:$E$2004,$AH$29,$Z13:$Z2004,"COMPLETADO")*-1 -> -75000 | AJ31: =COUNTIF($H$13:$H$2004,AD31) -> 424 | AK31: =AF31+AH31 -> 10554500
B32: I-1019 | C32: 46224.899 | E32: INGRESOS | H32: CUOTA | K32: Pago de cuota [F-0042] de Carolina Paredes por actividad de Funcional | P32: 28.162.967 | S32: FITNESS | U32: 6000 | X32: 0 | Z32: COMPLETADO | AB32: Transferencia | AD32: TURNOS | AF32: =SUMIFS($U$13:$U$2004,$H$13:$H$2004,AD32,$E$13:$E$2004,$AF$29) -> 0 | AH32: =SUMIFS($U$13:$U$2004,$H$13:$H$2004,AD32,$E$13:$E$2004,$AH$29,$Z13:$Z2004,"COMPLETADO")*-1 -> 0 | AJ32: =COUNTIF($H$13:$H$2004,AD32) -> 0 | AK32: =AF32+AH32 -> 0
B33: E-1018 | C33: 46224.652 | E33: EGRESOS | H33: PUBLICIDAD | K33: Panfletos x300 + planillas de inscripción | P33: 00.000.000 | S33: OTROS | U33: 14000 | X33: 0 | Z33: COMPLETADO | AB33: Transferencia | AD33: COMISIÓN | AF33: =SUMIFS($U$13:$U$2004,$H$13:$H$2004,AD33,$E$13:$E$2004,$AF$29) -> 859000 | AH33: =SUMIFS($U$13:$U$2004,$H$13:$H$2004,AD33,$E$13:$E$2004,$AH$29,$Z13:$Z2004,"COMPLETADO")*-1 -> -6714900 | AJ33: =COUNTIF($H$13:$H$2004,AD33) -> 109 | AK33: =AF33+AH33 -> -5855900
B34: E-1017 | C34: 46224.631 | E34: EGRESOS | H34: PÉRDIDA | K34: Conciliación de caja y banco - Faltante | P34: 35.004.264 | S34: TESORERÍA | U34: 10000 | X34: 0 | Z34: COMPLETADO | AB34: Efectivo | AD34: ALQUILER | AF34: =SUMIFS($U$13:$U$2004,$H$13:$H$2004,AD34,$E$13:$E$2004,$AF$29) -> 115000 | AH34: =SUMIFS($U$13:$U$2004,$H$13:$H$2004,AD34,$E$13:$E$2004,$AH$29,$Z13:$Z2004,"COMPLETADO")*-1 -> -11260000 | AJ34: =COUNTIF($H$13:$H$2004,AD34) -> 11 | AK34: =AF34+AH34 -> -11145000
B35: E-1016 | C35: 46224.503 | E35: EGRESOS | H35: EXTRACCIONES | K35: Conciliación de caja y banco - contra I-1016 | P35: 35.004.264 | S35: TESORERÍA | U35: 40000 | X35: 0 | Z35: COMPLETADO | AB35: Transferencia | AD35: EVENTOS | AF35: =SUMIFS($U$13:$U$2004,$H$13:$H$2004,AD35,$E$13:$E$2004,$AF$29) -> 205000 | AH35: =SUMIFS($U$13:$U$2004,$H$13:$H$2004,AD35,$E$13:$E$2004,$AH$29,$Z13:$Z2004,"COMPLETADO")*-1 -> -59637 | AJ35: =COUNTIF($H$13:$H$2004,AD35) -> 6 | AK35: =AF35+AH35 -> 145363
B36: I-1015 | C36: 46224.494 | E36: INGRESOS | H36: DEPÓSITOS | K36: Conciliación de caja y banco - contra E-1017 | P36: 35.004.264 | S36: TESORERÍA | U36: 40000 | X36: 0 | Z36: COMPLETADO | AB36: Efectivo | AD36: VENTAS | AF36: =SUMIFS($U$13:$U$2004,$H$13:$H$2004,AD36,$E$13:$E$2004,$AF$29) -> 6115800 | AH36: =SUMIFS($U$13:$U$2004,$H$13:$H$2004,AD36,$E$13:$E$2004,$AH$29,$Z13:$Z2004,"COMPLETADO")*-1 -> 0 | AJ36: =COUNTIF($H$13:$H$2004,AD36) -> 76 | AK36: =AF36+AH36 -> 6115800
B37: I-1014 | C37: 46223.732 | E37: INGRESOS | H37: CUOTA | K37: Pago de cuota [C-0136] de Walter Segovia por actividad de Complemento | P37: 20.060.193 | S37: FITNESS | U37: 30000 | X37: 0 | Z37: COMPLETADO | AB37: Transferencia | AD37: CLASES | AF37: =SUMIFS($U$13:$U$2004,$H$13:$H$2004,AD37,$E$13:$E$2004,$AF$29) -> 0 | AH37: =SUMIFS($U$13:$U$2004,$H$13:$H$2004,AD37,$E$13:$E$2004,$AH$29,$Z13:$Z2004,"COMPLETADO")*-1 -> 0 | AJ37: =COUNTIF($H$13:$H$2004,AD37) -> 0 | AK37: =AF37+AH37 -> 0
B38: I-1013 | C38: 46223.7 | E38: INGRESOS | H38: CUOTA | K38: Pago de cuota [K-0064] de Javier Agustin Caceres Velazquez por clases de Karate al profesor Sergio Tabossi | P38: 54.376.352 | S38: SALON | U38: 20000 | X38: 0 | Z38: COMPLETADO | AB38: Efectivo | AD38: CURSOS | AF38: =SUMIFS($U$13:$U$2004,$H$13:$H$2004,AD38,$E$13:$E$2004,$AF$29) -> 0 | AH38: =SUMIFS($U$13:$U$2004,$H$13:$H$2004,AD38,$E$13:$E$2004,$AH$29,$Z13:$Z2004,"COMPLETADO")*-1 -> 0 | AJ38: =COUNTIF($H$13:$H$2004,AD38) -> 0 | AK38: =AF38+AH38 -> 0
B39: E-1012 | C39: 46223.681 | E39: EGRESOS | H39: VIÁTICOS | K39: Almuerzo | P39: 35.004.264 | S39: TESORERÍA | U39: 6200 | X39: 0 | Z39: COMPLETADO | AB39: Efectivo | AD39: PUBLICIDAD | AF39: =SUMIFS($U$13:$U$2004,$H$13:$H$2004,AD39,$E$13:$E$2004,$AF$29) -> 0 | AH39: =SUMIFS($U$13:$U$2004,$H$13:$H$2004,AD39,$E$13:$E$2004,$AH$29,$Z13:$Z2004,"COMPLETADO")*-1 -> -260000 | AJ39: =COUNTIF($H$13:$H$2004,AD39) -> 10 | AK39: =AF39+AH39 -> -260000
B40: I-1011 | C40: 46223.649 | E40: INGRESOS | H40: CUOTA | K40: Pago de cuota [C-0133] de Magdalena Itati Ramos por actividad de Complemento | P40: 37.044.300 | S40: FITNESS | U40: 30000 | X40: 0 | Z40: COMPLETADO | AB40: Transferencia | AD40: SALARIOS | AF40: =SUMIFS($U$13:$U$2004,$H$13:$H$2004,AD40,$E$13:$E$2004,$AF$29) -> 0 | AH40: =SUMIFS($U$13:$U$2004,$H$13:$H$2004,AD40,$E$13:$E$2004,$AH$29,$Z13:$Z2004,"COMPLETADO")*-1 -> -60000 | AJ40: =COUNTIF($H$13:$H$2004,AD40) -> 1 | AK40: =AF40+AH40 -> -60000
B41: E-1010 | C41: 46223.526 | E41: EGRESOS | H41: PUBLICIDAD | K41: Video para promoción de colecta | P41: 00.000.000 | S41: OTROS | U41: 20000 | X41: 0 | Z41: COMPLETADO | AB41: Transferencia | AD41: MANTENIM. | AF41: =SUMIFS($U$13:$U$2004,$H$13:$H$2004,AD41,$E$13:$E$2004,$AF$29) -> 125000 | AH41: =SUMIFS($U$13:$U$2004,$H$13:$H$2004,AD41,$E$13:$E$2004,$AH$29,$Z13:$Z2004,"COMPLETADO")*-1 -> -355450 | AJ41: =COUNTIF($H$13:$H$2004,AD41) -> 13 | AK41: =AF41+AH41 -> -230450
B42: I-1009 | C42: 46222.841 | E42: INGRESOS | H42: KIOSCO | K42: SALDO A LIQUIDAR - Cantina Kiosco - 13/7/2026 al 19/7/2026 | P42: 29.596.385 | S42: CANTINA | U42: 5150 | X42: 0 | Z42: COMPLETADO | AB42: Transferencia | AD42: LUZ | AF42: =SUMIFS($U$13:$U$2004,$H$13:$H$2004,AD42,$E$13:$E$2004,$AF$29) -> 0 | AH42: =SUMIFS($U$13:$U$2004,$H$13:$H$2004,AD42,$E$13:$E$2004,$AH$29,$Z13:$Z2004,"COMPLETADO")*-1 -> -686455 | AJ42: =COUNTIF($H$13:$H$2004,AD42) -> 2 | AK42: =AF42+AH42 -> -686455
B43: I-1008 | C43: 46222.839 | E43: INGRESOS | H43: BEBIDAS | K43: SALDO A LIQUIDAR - Cantina Bebidas - 16/7/2026 al 19/7/2026 | P43: 29.596.385 | S43: CANTINA | U43: 15000 | X43: 0 | Z43: COMPLETADO | AB43: Transferencia | AD43: AGUA | AF43: =SUMIFS($U$13:$U$2004,$H$13:$H$2004,AD43,$E$13:$E$2004,$AF$29) -> 0 | AH43: =SUMIFS($U$13:$U$2004,$H$13:$H$2004,AD43,$E$13:$E$2004,$AH$29,$Z13:$Z2004,"COMPLETADO")*-1 -> -698749 | AJ43: =COUNTIF($H$13:$H$2004,AD43) -> 7 | AK43: =AF43+AH43 -> -698749
B44: E-1007 | C44: 46222.541 | E44: EGRESOS | H44: LIBRERÍA | K44: Afiches y cinta para decoración Final Mundial | P44: 00.000.000 | S44: OTROS | U44: 13500 | X44: 0 | Z44: COMPLETADO | AB44: Transferencia | AD44: INTERNET | AF44: =SUMIFS($U$13:$U$2004,$H$13:$H$2004,AD44,$E$13:$E$2004,$AF$29) -> 0 | AH44: =SUMIFS($U$13:$U$2004,$H$13:$H$2004,AD44,$E$13:$E$2004,$AH$29,$Z13:$Z2004,"COMPLETADO")*-1 -> -31000 | AJ44: =COUNTIF($H$13:$H$2004,AD44) -> 2 | AK44: =AF44+AH44 -> -31000
B45: E-1006 | C45: 46222.538 | E45: EGRESOS | H45: IMPUESTOS | K45: Retención IIBB SIRCUPA | P45: 67.238.712 | S45: TESORERÍA | U45: 3200 | X45: 0 | Z45: COMPLETADO | AB45: Transferencia | AD45: IMPUESTOS | AF45: =SUMIFS($U$13:$U$2004,$H$13:$H$2004,AD45,$E$13:$E$2004,$AF$29) -> 0 | AH45: =SUMIFS($U$13:$U$2004,$H$13:$H$2004,AD45,$E$13:$E$2004,$AH$29,$Z13:$Z2004,"COMPLETADO")*-1 -> -1161150 | AJ45: =COUNTIF($H$13:$H$2004,AD45) -> 27 | AK45: =AF45+AH45 -> -1161150
B46: E-1005 | C46: 46222.458 | E46: EGRESOS | H46: VIÁTICOS | K46: Chorizos día Final del Mundial | P46: 35.004.264 | S46: TESORERÍA | U46: 27400 | X46: 0 | Z46: COMPLETADO | AB46: Efectivo | AD46: DEPÓSITOS | AF46: =SUMIFS($U$13:$U$2004,$H$13:$H$2004,AD46,$E$13:$E$2004,$AF$29)+SUMIFS($U$13:$U$2004,$H$13:$H$2004,AD46,$E$13:$E$2004,"CAPITAL") -> 16203400 | AH46: =SUMIFS($U$13:$U$2004,$H$13:$H$2004,AD46,$E$13:$E$2004,$AH$29,$Z13:$Z2004,"COMPLETADO")*-1 -> 0 | AJ46: =COUNTIF($H$13:$H$2004,AD46) -> 55 | AK46: =AF46+AH46 -> 16203400
B47: E-1004 | C47: 46222.455 | E47: EGRESOS | H47: COMISIÓN | K47: Pago de SALDO A LIQUIDAR - 19/7/2026 | P47: 35.872.158 | S47: LOCAL 1 | U47: 25000 | X47: 0 | Z47: COMPLETADO | AB47: Efectivo | AD47: EXTRACCIONES | AF47: =SUMIFS($U$13:$U$2004,$H$13:$H$2004,AD47,$E$13:$E$2004,$AF$29) -> 0 | AH47: =(SUMIFS($U$13:$U$2004,$H$13:$H$2004,AD47,$E$13:$E$2004,$AH$29)+SUMIFS($U$13:$U$2004,$H$13:$H$2004,AD47,$E$13:$E$2004,"CAPITAL",$Z13:$Z2004,"COMPLETADO"))*-1 -> -1626000 | AJ47: =COUNTIF($H$13:$H$2004,AD47) -> 42 | AK47: =AF47+AH47 -> -1626000
B48: I-1003 | C48: 46222.452 | E48: INGRESOS | H48: VENTAS | K48: Tattoo - Manga floral Isabel | P48: 35.872.158 | S48: LOCAL 1 | U48: 50000 | X48: 0 | Z48: COMPLETADO | AB48: Efectivo | AD48: DÓLARES | AF48: =SUMIFS($U$13:$U$2004,$H$13:$H$2004,AD48,$E$13:$E$2004,$AF$29) -> 100 | AH48: =SUMIFS($U$13:$U$2004,$H$13:$H$2004,AD48,$E$13:$E$2004,$AH$29,$Z13:$Z2004,"COMPLETADO")*-1 -> -5500 | AJ48: =COUNTIF($H$13:$H$2004,AD48) -> 8 | AK48: =AF48+AH48 -> -5400
B49: E-1002 | C49: 46221.006 | E49: EGRESOS | H49: COMISIÓN | K49: Pago de SALDO A LIQUIDAR - 18/7/2026 | P49: 35.872.158 | S49: LOCAL 1 | U49: 25000 | X49: 0 | Z49: COMPLETADO | AB49: Transferencia | AD49: REPARACIONES | AF49: =SUMIFS($U$13:$U$2004,$H$13:$H$2004,AD49,$E$13:$E$2004,$AF$29) -> 264000 | AH49: =SUMIFS($U$13:$U$2004,$H$13:$H$2004,AD49,$E$13:$E$2004,$AH$29,$Z13:$Z2004,"COMPLETADO")*-1 -> -7080273 | AJ49: =COUNTIF($H$13:$H$2004,AD49) -> 95 | AK49: =AF49+AH49 -> -6816273
B50: I-1001 | C50: 46221.005 | E50: INGRESOS | H50: CUOTA | K50: Pago de cuota [A-0007] de Emily Nielsen por clases de Arte - niños al profesor Vanesa Rodriguez | P50: 55.400.083 | S50: AULA | U50: 5000 | X50: 0 | Z50: COMPLETADO | AB50: Transferencia | AD50: VIÁTICOS | AF50: =SUMIFS($U$13:$U$2004,$H$13:$H$2004,AD50,$E$13:$E$2004,$AF$29) -> 0 | AH50: =SUMIFS($U$13:$U$2004,$H$13:$H$2004,AD50,$E$13:$E$2004,$AH$29,$Z13:$Z2004,"COMPLETADO")*-1 -> -318915 | AJ50: =COUNTIF($H$13:$H$2004,AD50) -> 42 | AK50: =AF50+AH50 -> -318915
B51: E-1000 | C51: 46221.004 | E51: EGRESOS | H51: COMISIÓN | K51: Pago de SALDO A LIQUIDAR - 18/7/2026 | P51: 35.872.158 | S51: LOCAL 1 | U51: 75000 | X51: 0 | Z51: COMPLETADO | AB51: Efectivo | AD51: OTROS | AF51: =SUMIFS($U$13:$U$2004,$H$13:$H$2004,AD51,$E$13:$E$2004,$AF$29) -> 0 | AH51: =SUMIFS($U$13:$U$2004,$H$13:$H$2004,AD51,$E$13:$E$2004,$AH$29,$Z13:$Z2004,"COMPLETADO")*-1 -> -104800 | AJ51: =COUNTIF($H$13:$H$2004,AD51) -> 4 | AK51: =AF51+AH51 -> -104800
B52: I-0999 | C52: 46221.003 | E52: INGRESOS | H52: CUOTA | K52: Pago de cuota [A-0008] de Enzo Nielsen por clases de Arte - niños al profesor Vanesa Rodriguez | P52: 57.962.209 | S52: AULA | U52: 5000 | X52: 0 | Z52: COMPLETADO | AB52: Transferencia
B53: I-0998 | C53: 46221.003 | E53: INGRESOS | H53: VENTAS | K53: Seña Tattoo - Lineas finas manga Micaela | P53: 35.872.158 | S53: LOCAL 1 | U53: 50000 | X53: 0 | Z53: COMPLETADO | AB53: Transferencia | AD53: INGRESOS x SECTOR
B54: I-0997 | C54: 46221.001 | E54: INGRESOS | H54: CUOTA | K54: Pago de cuota [A-0007] de Emily Nielsen por clases de Arte - niños al profesor Vanesa Rodriguez | P54: 55.400.083 | S54: AULA | U54: 20000 | X54: 0 | Z54: COMPLETADO | AB54: Efectivo
B55: I-0996 | C55: 46221.001 | E55: INGRESOS | H55: VENTAS | K55: Tattoo - Manga floral Isabel | P55: 35.872.158 | S55: LOCAL 1 | U55: 150000 | X55: 0 | Z55: COMPLETADO | AB55: Efectivo
B56: I-0995 | C56: 46220.999 | E56: INGRESOS | H56: CUOTA | K56: Pago de cuota [A-0008] de Enzo Nielsen por clases de Arte - niños al profesor Vanesa Rodriguez | P56: 57.962.209 | S56: AULA | U56: 20000 | X56: 0 | Z56: COMPLETADO | AB56: Efectivo
B57: E-0994 | C57: 46220.082 | E57: EGRESOS | H57: IMPUESTOS | K57: Retención IIBB SIRCUPA | P57: 67.238.712 | S57: TESORERÍA | U57: 4400 | X57: 0 | Z57: COMPLETADO | AB57: Transferencia
B58: I-0993 | C58: 46219.798 | E58: INGRESOS | H58: CUOTA | K58: Pago de cuota [C-0095] de Sergio Rolon por actividad de Complemento | P58: 48.546.483 | S58: FITNESS | U58: 15000 | X58: 0 | Z58: COMPLETADO | AB58: Transferencia
B59: I-0992 | C59: 46219.797 | E59: INGRESOS | H59: CUOTA | K59: Pago de cuota [C-0095] de Sergio Rolon por actividad de Complemento | P59: 48.546.483 | S59: FITNESS | U59: 10000 | X59: 0 | Z59: COMPLETADO | AB59: Efectivo
B60: I-0991 | C60: 46219.785 | E60: INGRESOS | H60: CUOTA | K60: Pago de cuota [T-0047] de Isaias Silva por clases de Taekwon-do al profesor Luzmila Cinquetti | P60: 58.036.520 | S60: SALON | U60: 20000 | X60: 0 | Z60: COMPLETADO | AB60: Transferencia
B61: I-0990 | C61: 46219.671 | E61: INGRESOS | H61: CUOTA | K61: Pago de cuota [X-0045] de Claudia Gaona por actividad de Combo F+C | P61: 22.090.381 | S61: FITNESS | U61: 50000 | X61: 0 | Z61: COMPLETADO | AB61: Transferencia
B62: I-0989 | C62: 46219.661 | E62: INGRESOS | H62: CUOTA | K62: Pago de cuota [A-0025] de Joaquin Rodriguez por clases de Arte - niños al profesor Vanesa Rodriguez | P62: 05.555.555 | S62: AULA | U62: 25000 | X62: 0 | Z62: COMPLETADO | AB62: Efectivo
B63: I-0988 | C63: 46219.66 | E63: INGRESOS | H63: CUOTA | K63: Pago de cuota [A-0024] de Olivia Acosta por clases de Arte - niños al profesor Vanesa Rodriguez | P63: 54.944.974 | S63: AULA | U63: 25000 | X63: 0 | Z63: COMPLETADO | AB63: Efectivo
B64: I-0987 | C64: 46219.659 | E64: INGRESOS | H64: CUOTA | K64: Pago de cuota [C-0135] de Victoria Weiss por actividad de Complemento | P64: 50.731.392 | S64: FITNESS | U64: 25000 | X64: 0 | Z64: COMPLETADO | AB64: Efectivo
B65: I-0986 | C65: 46219.657 | E65: INGRESOS | H65: CUOTA | K65: Pago de cuota [C-0134] de Vanesa Campuzano por actividad de Complemento | P65: 28.818.123 | S65: FITNESS | U65: 25000 | X65: 0 | Z65: COMPLETADO | AB65: Efectivo
B66: I-0985 | C66: 46219.627 | E66: INGRESOS | H66: CUOTA | K66: Pago de cuota [F-0127] de Sebastian Borjas por actividad de Funcional | P66: 52.173.302 | S66: FITNESS | U66: 30000 | X66: 0 | Z66: COMPLETADO | AB66: Efectivo
B67: I-0984 | C67: 46219.624 | E67: INGRESOS | H67: CUOTA | K67: Pago de cuota [F-0123] de Margarita Ayala por actividad de Funcional | P67: 31.914.258 | S67: FITNESS | U67: 35000 | X67: 0 | Z67: COMPLETADO | AB67: Efectivo | AD67: GASTOS x SECTOR
B68: E-0983 | C68: 46218.829 | E68: EGRESOS | H68: VIÁTICOS | K68: Yerba | P68: 35.004.264 | S68: TESORERÍA | U68: 3500 | X68: 0 | Z68: COMPLETADO | AB68: Efectivo
B69: E-0982 | C69: 46218.827 | E69: EGRESOS | H69: IMPUESTOS | K69: Retención IIBB SIRCUPA | P69: 67.238.712 | S69: TESORERÍA | U69: 1400 | X69: 0 | Z69: COMPLETADO | AB69: Transferencia
B70: E-0981 | C70: 46218.825 | E70: EGRESOS | H70: COMISIÓN | K70: Pago de SALDO A LIQUIDAR - 15/7/2026 | P70: 35.872.158 | S70: LOCAL 1 | U70: 35000 | X70: 0 | Z70: COMPLETADO | AB70: Transferencia
B71: E-0980 | C71: 46218.823 | E71: EGRESOS | H71: COMISIÓN | K71: Pago de SALDO A LIQUIDAR - 15/7/2026 | P71: 35.872.158 | S71: LOCAL 1 | U71: 70000 | X71: 0 | Z71: COMPLETADO | AB71: Efectivo
B72: I-0979 | C72: 46218.822 | E72: INGRESOS | H72: VENTAS | K72: Tattoo - Proyecto Candela Dragones y 2 minitattoos | P72: 35.872.158 | S72: LOCAL 1 | U72: 70000 | X72: 0 | Z72: COMPLETADO | AB72: Transferencia
B73: I-0978 | C73: 46218.82 | E73: INGRESOS | H73: VENTAS | K73: Tattoo - Proyecto Candela Dragones y 2 minitattoos | P73: 35.872.158 | S73: LOCAL 1 | U73: 140000 | X73: 0 | Z73: COMPLETADO | AB73: Efectivo
B74: I-0977 | C74: 46218.817 | E74: INGRESOS | H74: BEBIDAS | K74: SALDO A LIQUIDAR - Cantina Bebidas - 12/7/2026 al 15/7/2026 | P74: 29.596.385 | S74: CANTINA | U74: 24000 | X74: 0 | Z74: COMPLETADO | AB74: Efectivo
B75: E-0976 | C75: 46218.652 | E75: EGRESOS | H75: BEBIDAS | K75: 1 Cajon de Brahama + 2 vinos | P75: 71.489.590 | S75: CANTINA | U75: 46750 | X75: 0 | Z75: COMPLETADO | AB75: Efectivo
B76: I-0975 | C76: 46217.927 | E76: INGRESOS | H76: CUOTA | K76: Pago de cuota [F-0042] de Carolina Paredes por actividad de Funcional | P76: 28.162.967 | S76: FITNESS | U76: 6000 | X76: 0 | Z76: COMPLETADO | AB76: Transferencia
B77: E-0974 | C77: 46217.815 | E77: EGRESOS | H77: COMISIÓN | K77: Pago comisión Julio - Taller Arte - Niños - Vanesa Rodriguez | P77: 35.872.158 | S77: AULA | U77: 40000 | X77: 0 | Z77: COMPLETADO | AB77: Efectivo
B78: I-0973 | C78: 46217.755 | E78: INGRESOS | H78: CUOTA | K78: Pago de cuota [T-0062] de Fernanda De Brito por clases de Taekwon-do al profesor Luzmila Cinquetti | P78: 22.222.222 | S78: SALON | U78: 20000 | X78: 0 | Z78: COMPLETADO | AB78: Efectivo
B79: I-0972 | C79: 46217.754 | E79: INGRESOS | H79: CUOTA | K79: Pago de cuota [F-0132] de Ana María Atamañuk por actividad de Funcional | P79: 32.085.811 | S79: FITNESS | U79: 30000 | X79: 0 | Z79: COMPLETADO | AB79: Efectivo
B80: I-0971 | C80: 46217.681 | E80: INGRESOS | H80: VENTAS | K80: Pago (PARCIAL) Tattoo - Minitattoo Silvina | P80: 35.872.158 | S80: LOCAL 1 | U80: 20000 | X80: 0 | Z80: COMPLETADO | AB80: Transferencia
B81: I-0970 | C81: 46217.664 | E81: INGRESOS | H81: CUOTA | K81: Pago de cuota [J-0073] de Horacio Marquez por clases de Jiu Jitsu al profesor Andres Rodriguez | P81: 30.561.519 | S81: SALON | U81: 30000 | X81: 0 | Z81: COMPLETADO | AB81: Transferencia | AD81: GASTOS x CATEGORÍAS
B82: E-0969 | C82: 46217.662 | E82: EGRESOS | H82: COMISIÓN | K82: Pago de SALDO A LIQUIDAR - 14/7/2026 | P82: 35.872.158 | S82: LOCAL 1 | U82: 55000 | X82: 0 | Z82: COMPLETADO | AB82: Transferencia
B83: E-0968 | C83: 46217.661 | E83: EGRESOS | H83: IMPUESTOS | K83: Retención IIBB SIRCUPA | P83: 67.238.712 | S83: TESORERÍA | U83: 9400 | X83: 0 | Z83: COMPLETADO | AB83: Transferencia
B84: I-0967 | C84: 46217.658 | E84: INGRESOS | H84: VENTAS | K84: Pago (PARCIAL) Tattoo - Proyecto Fabian | P84: 35.872.158 | S84: LOCAL 1 | U84: 30000 | X84: 0 | Z84: COMPLETADO | AB84: Transferencia
B85: I-0966 | C85: 46217.653 | E85: INGRESOS | H85: VENTAS | K85: Seña Tattoo - Candela pierna y 2 minitattos | P85: 35.872.158 | S85: LOCAL 1 | U85: 60000 | X85: 0 | Z85: COMPLETADO | AB85: Transferencia
B86: I-0965 | C86: 46217.482 | E86: INGRESOS | H86: CUOTA | K86: Pago de cuota [F-0050] de Rosana Neris por actividad de Funcional | P86: 25.496.779 | S86: FITNESS | U86: 30000 | X86: 0 | Z86: COMPLETADO | AB86: Transferencia
B87: I-0964 | C87: 46216.888 | E87: INGRESOS | H87: CUOTA | K87: Pago de cuota [T-0048] de Maia Jorgelina Maciel por clases de Taekwon-do al profesor Luzmila Cinquetti | P87: 56.407.427 | S87: SALON | U87: 20000 | X87: 0 | Z87: COMPLETADO | AB87: Transferencia
B88: I-0963 | C88: 46216.887 | E88: INGRESOS | H88: CUOTA | K88: Pago de cuota [C-0120] de Daniela Maciel por actividad de Complemento | P88: 50.020.164 | S88: FITNESS | U88: 30000 | X88: 0 | Z88: COMPLETADO | AB88: Transferencia
B89: I-0962 | C89: 46216.881 | E89: INGRESOS | H89: CUOTA | K89: Pago de cuota [J-0030] de Lisandro Kinigsberg por clases de Jiu Jitsu al profesor Andres Rodriguez | P89: 24.509.315 | S89: SALON | U89: 30000 | X89: 0 | Z89: COMPLETADO | AB89: Transferencia
B90: I-0961 | C90: 46216.869 | E90: INGRESOS | H90: CUOTA | K90: Pago de cuota [J-0014] de Hernan Leon por clases de Jiu Jitsu al profesor Andres Rodriguez | P90: 37.157.910 | S90: SALON | U90: 30000 | X90: 0 | Z90: COMPLETADO | AB90: Transferencia
B91: I-0960 | C91: 46216.793 | E91: INGRESOS | H91: CUOTA | K91: Pago de cuota [F-0021] de Marina Leiva por actividad de Funcional | P91: 21.735.346 | S91: FITNESS | U91: 30000 | X91: 0 | Z91: COMPLETADO | AB91: Efectivo
B92: I-0959 | C92: 46216.728 | E92: INGRESOS | H92: CUOTA | K92: Pago de cuota [C-0131] de Tadeo Loyzate por actividad de Complemento | P92: 48.950.707 | S92: FITNESS | U92: 30000 | X92: 0 | Z92: COMPLETADO | AB92: Efectivo
B93: I-0958 | C93: 46216.701 | E93: INGRESOS | H93: CUOTA | K93: Pago de cuota [K-0041] de Yamila Sanches por clases de Karate al profesor Sergio Tabossi | P93: 52.309.166 | S93: SALON | U93: 20000 | X93: 0 | Z93: COMPLETADO | AB93: Efectivo
... B168: I-0883 | C168: 46209.735 | E168: INGRESOS | H168: SEGUROS | K168: Cobro cobertura CELSO - Local 1 Vanesa | P168: 35.872.158 | S168: LOCAL 1 | U168: 27500 | X168: 0 | Z168: COMPLETADO | AB168: Transferencia
B169: I-0882 | C169: 46209.731 | E169: INGRESOS | H169: SEGUROS | K169: Cobro cobertura CELSO - Cantina Jimena | P169: 29.596.385 | S169: CANTINA | U169: 27500 | X169: 0 | Z169: PENDIENTE
B170: E-0881 | C170: 46209.728 | E170: EGRESOS | H170: SEGUROS | K170: Pago cobertura CELSO | P170: 44.013.327 | S170: TESORERÍA | U170: 110000 | X170: 0 | Z170: COMPLETADO | AB170: Transferencia
B171: I-0880 | C171: 46209.708 | E171: INGRESOS | H171: CUOTA | K171: Pago de cuota [C-0046] de Susana Cardozo por actividad de Complemento | P171: 34.366.782 | S171: FITNESS | U171: 30000 | X171: 0 | Z171: COMPLETADO | AB171: Transferencia
B172: I-0879 | C172: 46209.707 | E172: INGRESOS | H172: CUOTA | K172: Pago de cuota [K-0008] de Abril Castro por clases de Karate al profesor Sergio Tabossi | P172: 55.539.127 | S172: SALON | U172: 20000 | X172: 0 | Z172: COMPLETADO | AB172: Transferencia
B173: I-0878 | C173: 46209.706 | E173: INGRESOS | H173: CUOTA | K173: Pago de cuota [K-0009] de Liam Castro por clases de Karate al profesor Sergio Tabossi | P173: 58.603.142 | S173: SALON | U173: 20000 | X173: 0 | Z173: COMPLETADO | AB173: Transferencia
B174: I-0877 | C174: 46209.704 | E174: INGRESOS | H174: CUOTA | K174: Pago de cuota [C-0101] de Liliana Velloso por actividad de Complemento | P174: 31.330.650 | S174: FITNESS | U174: 30000 | X174: 0 | Z174: COMPLETADO | AB174: Efectivo
B175: E-0876 | C175: 46209.447 | E175: EGRESOS | H175: PUBLICIDAD | K175: Publicidad en redes + Insignia Instagram | P175: 35.004.264 | S175: OTROS | U175: 92000 | X175: 0 | Z175: COMPLETADO | AB175: Transferencia
B176: I-0875 | C176: 46209.403 | E176: INGRESOS | H176: CUOTA | K176: Pago de cuota [X-0039] de Graciela Pereyra por actividad de Combo F+C | P176: 30.524.744 | S176: FITNESS | U176: 50000 | X176: 0 | Z176: COMPLETADO | AB176: Efectivo
...

Sheet LOCAL 1
B2: LOCAL 1 | F2: ↓ Actividad ↓ | M2: Inicio de Actividad: | P2: 46089 | T2: SALDO TOTAL | X2: SALDO A LIQUIDAR | AB2: LIQUID. 30 DÍAS | AF2: INGRESO TOTAL | AJ2: EGRESO TOTAL | AN2: BALANCE
F3: Estudio de Tattoo | M3: Estado: | T3: 0 | X3: =((SUMIFS($P$10:$P$801,$E$10:$E$801,"INGRESOS",$G$10:$G$801,"TATTOO",$V$10:$V$801,"*ADO")+SUMIFS($P$10:$P$801,$E$10:$E$801,"INGRESOS",$G$10:$G$801,"VENTAS",$V$10:$V$801,"*ADO")+SUMIFS($P$10:$P$801,$E$10:$E$801,"INGRESOS",$G$10:$G$801,"PIERCING",$V$10:$V$801,"*ADO"))/2)-SUMIFS($P$10:$P$801,$E$10:$E$801,"EGRESOS",$G$10:$G$801,"COMISIÓN",$V$10:$V$801,"PAGADO") -> 0 | AB3: =SUMIFS($P$10:$P$801,$E$10:$E$801,"EGRESOS",$G$10:$G$801,"COMISIÓN",$Y$10:$Y$801,"COMPLETADO",$C$10:$C$801,">="&DASHBOARD!$AY$2-30,$C$10:$C$801,"<="&DASHBOARD!$AY$2) -> 991900 | AF3: =SUMIFS($P$10:$P$801,$E$10:$E$801,"INGRESOS",$G$10:$G801,"VENTAS",$V$10:$V$801,"*ADO")+(SUMIFS($P$10:$P$801,$E$10:$E$801,"INGRESOS",$G$10:$G801,"COMISIÓN",$V$10:$V$801,"*ADO")) -> 6374800 | AJ3: =SUMIFS($P$10:$P$801,$E$10:$E$801,"EGRESOS",$G$10:$G$801,"COMISIÓN",$V$10:$V$801,"*ADO")+SUMIFS($P$10:$P$801,$E$10:$E$801,"EGRESOS",$G$10:$G$801,"CMV",$V$10:$V$801,"*ADO") -> 3087400 | AN3: =AF3-AJ3-X3 -> 3287400
B6: Salud: | F6: Estado Municipal: | I6: En proceso | M6: Estado Financiero: | P6: =IF(T3<0,"Adeudando",IF(X3>0,"Saldo a liquidar",IF(AB3=0,"Sin movimientos",IF(X3=0,"Saldado",)))) -> Saldado | T6: LIQUIDAR TOTAL | X6: LIQUIDAR: → | AB6: 0
B8: MOVIMIENTOS
B9: Id. | C9: Fecha | E9: Tipo | G9: Categoría | I9: Concepto | N9: Contra-parte | P9: Monto | R9: Impuestos | T9: M.P. | V9: Estado Finan. | Y9: Estado | AB9: INGRESOS | AJ9: GASTOS
B10: I-1036 | C10: 46226.844 | E10: INGRESOS | G10: VENTAS | I10: Seña Tattoo - Minitattoo Silvina | N10: 35.872.158 | P10: 20000 | R10: 0 | T10: Transferencia | V10: SEÑADO | Y10: COMPLETADO | AB10: Enero | AD10: =SUMIFS($P$10:$P$811,$C$10:$C$811,">="&DATE(2026,1,1),$C$10:$C$811,"<"&DATE(2026,2,1),$E$10:$E$811,"INGRESOS",$Y$10:$Y$811,"COMPLETADO") -> 0 | AF10: Febrero | AH10: =SUMIFS($P$10:$P$811,$C$10:$C$811,">="&DATE(2026,2,1),$C$10:$C$811,"<"&DATE(2026,3,1),$E$10:$E$811,"INGRESOS",$Y$10:$Y$811,"COMPLETADO") -> 0 | AJ10: Enero | AL10: =-SUMIFS($P$10:$P$811,$C$10:$C$811,">="&DATE(2026,1,1),$C$10:$C$811,"<"&DATE(2026,2,1),$E$10:$E$811,"EGRESOS",$Y$10:$Y$811,"COMPLETADO") -> 0 | AN10: Febrero | AP10: =-SUMIFS($P$10:$P$811,$C$10:$C$811,">="&DATE(2026,2,1),$C$10:$C$811,"<"&DATE(2026,3,1),$E$10:$E$811,"EGRESOS",$Y$10:$Y$811,"COMPLETADO") -> 0
B11: I-1035 | C11: 46226.842 | E11: INGRESOS | G11: VENTAS | I11: Seña Tattoo - Mundialista Pamela | N11: 35.872.158 | P11: 40000 | R11: 0 | T11: Transferencia | V11: SEÑADO | Y11: COMPLETADO | AB11: Marzo | AD11: =SUMIFS($P$10:$P$811,$C$10:$C$811,">="&DATE(2026,3,1),$C$10:$C$811,"<"&DATE(2026,4,1),$E$10:$E$811,"INGRESOS",$Y$10:$Y$811,"COMPLETADO") -> 769000 | AF11: Abril | AH11: =SUMIFS($P$10:$P$811,$C$10:$C$811,">="&DATE(2026,4,1),$C$10:$C$811,"<"&DATE(2026,5,1),$E$10:$E$811,"INGRESOS",$Y$10:$Y$811,"COMPLETADO") -> 1652500 | AJ11: Marzo | AL11: =-SUMIFS($P$10:$P$811,$C$10:$C$811,">="&DATE(2026,3,1),$C$10:$C$811,"<"&DATE(2026,4,1),$E$10:$E$811,"EGRESOS",$Y$10:$Y$811,"COMPLETADO") -> -852065 | AN11: Abril | AP11: =-SUMIFS($P$10:$P$811,$C$10:$C$811,">="&DATE(2026,4,1),$C$10:$C$811,"<"&DATE(2026,5,1),$E$10:$E$811,"EGRESOS",$Y$10:$Y$811,"COMPLETADO") -> -792400
B12: E-1032 | C12: 46226.591 | E12: EGRESOS | G12: COMISIÓN | I12: Pago de SALDO A LIQUIDAR - 23/7/2026 | N12: 35.872.158 | P12: 45000 | R12: 0 | T12: Transferencia | V12: PAGADO | Y12: COMPLETADO | AB12: Mayo | AD12: =SUMIFS($P$10:$P$811,$C$10:$C$811,">="&DATE(2026,5,1),$C$10:$C$811,"<"&DATE(2026,6,1),$E$10:$E$811,"INGRESOS",$Y$10:$Y$811,"COMPLETADO") -> 614500 | AF12: Junio | AH12: =SUMIFS($P$10:$P$811,$C$10:$C$811,">="&DATE(2026,6,1),$C$10:$C$811,"<"&DATE(2026,7,1),$E$10:$E$811,"INGRESOS",$Y$10:$Y$811,"COMPLETADO") -> 1962500 | AJ12: Mayo | AL12: =-SUMIFS($P$10:$P$811,$C$10:$C$811,">="&DATE(2026,5,1),$C$10:$C$811,"<"&DATE(2026,6,1),$E$10:$E$811,"EGRESOS",$Y$10:$Y$811,"COMPLETADO") -> -293500 | AN12: Junio | AP12: =-SUMIFS($P$10:$P$811,$C$10:$C$811,">="&DATE(2026,6,1),$C$10:$C$811,"<"&DATE(2026,7,1),$E$10:$E$811,"EGRESOS",$Y$10:$Y$811,"COMPLETADO") -> -865000
B13: I-1031 | C13: 46226.59 | E13: INGRESOS | G13: VENTAS | I13: Seña Tattoo - minitattoos en la mano Virginia | N13: 35.872.158 | P13: 30000 | R13: 0 | T13: Transferencia | V13: SEÑADO | Y13: COMPLETADO | AB13: Julio | AD13: =SUMIFS($P$10:$P$811,$C$10:$C$811,">="&DATE(2026,7,1),$C$10:$C$811,"<"&DATE(2026,8,1),$E$10:$E$811,"INGRESOS",$Y$10:$Y$811,"COMPLETADO") -> 1736300 | AF13: Agosto | AH13: =SUMIFS($P$10:$P$811,$C$10:$C$811,">="&DATE(2026,8,1),$C$10:$C$811,"<"&DATE(2026,9,1),$E$10:$E$811,"INGRESOS",$Y$10:$Y$811,"COMPLETADO") -> 0 | AJ13: Julio | AL13: =-SUMIFS($P$10:$P$811,$C$10:$C$811,">="&DATE(2026,7,1),$C$10:$C$811,"<"&DATE(2026,8,1),$E$10:$E$811,"EGRESOS",$Y$10:$Y$811,"COMPLETADO") -> -854400 | AN13: Agosto | AP13: =-SUMIFS($P$10:$P$811,$C$10:$C$811,">="&DATE(2026,8,1),$C$10:$C$811,"<"&DATE(2026,9,1),$E$10:$E$811,"EGRESOS",$Y$10:$Y$811,"COMPLETADO") -> 0
B14: E-1024 | C14: 46225.704 | E14: EGRESOS | G14: COMISIÓN | I14: Pago de SALDO A LIQUIDAR - 22/7/2026 | N14: 35.872.158 | P14: 150000 | R14: 0 | T14: Efectivo | V14: PAGADO | Y14: COMPLETADO | AB14: Septiembre | AD14: =SUMIFS($P$10:$P$811,$C$10:$C$811,">="&DATE(2026,9,1),$C$10:$C$811,"<"&DATE(2026,10,1),$E$10:$E$811,"INGRESOS",$Y$10:$Y$811,"COMPLETADO") -> 0 | AF14: Octubre | AH14: =SUMIFS($P$10:$P$811,$C$10:$C$811,">="&DATE(2026,10,1),$C$10:$C$811,"<"&DATE(2026,11,1),$E$10:$E$811,"INGRESOS",$Y$10:$Y$811,"COMPLETADO") -> 0 | AJ14: Septiembre | AL14: =-SUMIFS($P$10:$P$811,$C$10:$C$811,">="&DATE(2026,9,1),$C$10:$C$811,"<"&DATE(2026,10,1),$E$10:$E$811,"EGRESOS",$Y$10:$Y$811,"COMPLETADO") -> 0 | AN14: Octubre | AP14: =-SUMIFS($P$10:$P$811,$C$10:$C$811,">="&DATE(2026,10,1),$C$10:$C$811,"<"&DATE(2026,11,1),$E$10:$E$811,"EGRESOS",$Y$10:$Y$811,"COMPLETADO") -> 0
B15: I-1023 | C15: 46225.702 | E15: INGRESOS | G15: VENTAS | I15: Tattoo - Manga floral Isabel | N15: 35.872.158 | P15: 300000 | R15: 0 | T15: Efectivo | V15: PAGADO | Y15: COMPLETADO | AB15: Noviembre | AD15: =SUMIFS($P$10:$P$811,$C$10:$C$811,">="&DATE(2026,11,1),$C$10:$C$811,"<"&DATE(2026,12,1),$E$10:$E$811,"INGRESOS",$Y$10:$Y$811,"COMPLETADO") -> 0 | AF15: Diciembre | AH15: =SUMIFS($P$10:$P$811,$C$10:$C$811,">="&DATE(2026,12,1),$C$10:$C$811,"<"&DATE(2027,1,1),$E$10:$E$811,"INGRESOS",$Y$10:$Y$811,"COMPLETADO") -> 0 | AJ15: Noviembre | AL15: =-SUMIFS($P$10:$P$811,$C$10:$C$811,">="&DATE(2026,11,1),$C$10:$C$811,"<"&DATE(2026,12,1),$E$10:$E$811,"EGRESOS",$Y$10:$Y$811,"COMPLETADO") -> 0 | AN15: Diciembre | AP15: =-SUMIFS($P$10:$P$811,$C$10:$C$811,">="&DATE(2026,12,1),$C$10:$C$811,"<"&DATE(2027,1,1),$E$10:$E$811,"EGRESOS",$Y$10:$Y$811,"COMPLETADO") -> 0
B16: E-1022 | C16: 46225.699 | E16: EGRESOS | G16: COMISIÓN | I16: Pago de SALDO A LIQUIDAR - 22/7/2026 | N16: 35.872.158 | P16: 25000 | R16: 0 | T16: Transferencia | V16: PAGADO | Y16: COMPLETADO | AB16: TOTAL | AF16: =SUM(AD10:AE15,AH10:AI15) -> 6734800 | AJ16: TOTAL | AN16: =SUM(AL10:AM15,AP10:AQ15) -> -3657365
B17: I-1021 | C17: 46225.697 | E17: INGRESOS | G17: VENTAS | I17: Seña Tattoo - Proyecto cobertura cicatrices Paula | N17: 35.872.158 | P17: 50000 | R17: 0 | T17: Transferencia | V17: SEÑADO | Y17: COMPLETADO
B18: E-1004 | C18: 46222.455 | E18: EGRESOS | G18: COMISIÓN | I18: Pago de SALDO A LIQUIDAR - 19/7/2026 | N18: 35.872.158 | P18: 25000 | R18: 0 | T18: Efectivo | V18: PAGADO | Y18: COMPLETADO | AB18: UTILIDAD | AK18: CRECIM. ECONÓM. | AO18: CRECIM. CLIENTES
B19: I-1003 | C19: 46222.452 | E19: INGRESOS | G19: VENTAS | I19: Tattoo - Manga floral Isabel | N19: 35.872.158 | P19: 50000 | R19: 0 | T19: Efectivo | V19: PAGADO | Y19: COMPLETADO | AB19: Enero | AD19: =AD10+AL10 -> 0 | AF19: Febrero | AH19: =AH10+AP10 -> 0 | AO19: No aplica
B20: E-1002 | C20: 46221.006 | E20: EGRESOS | G20: COMISIÓN | I20: Pago de SALDO A LIQUIDAR - 18/7/2026 | N20: 35.872.158 | P20: 25000 | R20: 0 | T20: Transferencia | V20: PAGADO | Y20: COMPLETADO | AB20: Marzo | AD20: =AD11+AL11 -> -83065 | AF20: Abril | AH20: =AH11+AP11 -> 860100
B21: E-1000 | C21: 46221.004 | E21: EGRESOS | G21: COMISIÓN | I21: Pago de SALDO A LIQUIDAR - 18/7/2026 | N21: 35.872.158 | P21: 75000 | R21: 0 | T21: Efectivo | V21: PAGADO | Y21: COMPLETADO | AB21: Mayo | AD21: =AD12+AL12 -> 321000 | AF21: Junio | AH21: =AH12+AP12 -> 1097500
B22: I-0998 | C22: 46221.003 | E22: INGRESOS | G22: VENTAS | I22: Seña Tattoo - Lineas finas manga Micaela | N22: 35.872.158 | P22: 50000 | R22: 0 | T22: Transferencia | V22: SEÑADO | Y22: COMPLETADO | AB22: Julio | AD22: =AD13+AL13 -> 881900 | AF22: Agosto | AH22: =AH13+AP13 -> 0 | AM22: CRECIMIENTO %
B23: I-0996 | C23: 46221.001 | E23: INGRESOS | G23: VENTAS | I23: Tattoo - Manga floral Isabel | N23: 35.872.158 | P23: 150000 | R23: 0 | T23: Efectivo | V23: PAGADO | Y23: COMPLETADO | AB23: Septiembre | AD23: =AD14+AL14 -> 0 | AF23: Octubre | AH23: =AH14+AP14 -> 0
B24: E-0981 | C24: 46218.825 | E24: EGRESOS | G24: COMISIÓN | I24: Pago de SALDO A LIQUIDAR - 15/7/2026 | N24: 35.872.158 | P24: 35000 | R24: 0 | T24: Transferencia | V24: PAGADO | Y24: COMPLETADO | AB24: Noviembre | AD24: =AD15+AL15 -> 0 | AF24: Diciembre | AH24: =AH15+AP15 -> 0
B25: E-0980 | C25: 46218.823 | E25: EGRESOS | G25: COMISIÓN | I25: Pago de SALDO A LIQUIDAR - 15/7/2026 | N25: 35.872.158 | P25: 70000 | R25: 0 | T25: Efectivo | V25: PAGADO | Y25: COMPLETADO | AB25: TOTAL | AF25: =SUM(AD19:AE24,AH19:AI24) -> 3077435
B26: I-0979 | C26: 46218.822 | E26: INGRESOS | G26: VENTAS | I26: Tattoo - Proyecto Candela Dragones y 2 minitattoos | N26: 35.872.158 | P26: 70000 | R26: 0 | T26: Transferencia | V26: PAGADO | Y26: COMPLETADO
B27: I-0978 | C27: 46218.82 | E27: INGRESOS | G27: VENTAS | I27: Tattoo - Proyecto Candela Dragones y 2 minitattoos | N27: 35.872.158 | P27: 140000 | R27: 0 | T27: Efectivo | V27: PAGADO | Y27: COMPLETADO
B28: I-0971 | C28: 46217.681 | E28: INGRESOS | G28: VENTAS | I28: Pago (PARCIAL) Tattoo - Minitattoo Silvina | N28: 35.872.158 | P28: 20000 | R28: 0 | T28: Transferencia | V28: PAGADO | Y28: COMPLETADO
B29: E-0969 | C29: 46217.662 | E29: EGRESOS | G29: COMISIÓN | I29: Pago de SALDO A LIQUIDAR - 14/7/2026 | N29: 35.872.158 | P29: 55000 | R29: 0 | T29: Transferencia | V29: PAGADO | Y29: COMPLETADO
B30: I-0967 | C30: 46217.658 | E30: INGRESOS | G30: VENTAS | I30: Pago (PARCIAL) Tattoo - Proyecto Fabian | N30: 35.872.158 | P30: 30000 | R30: 0 | T30: Transferencia | V30: PAGADO | Y30: COMPLETADO
B31: I-0966 | C31: 46217.653 | E31: INGRESOS | G31: VENTAS | I31: Seña Tattoo - Candela pierna y 2 minitattos | N31: 35.872.158 | P31: 60000 | R31: 0 | T31: Transferencia | V31: SEÑADO | Y31: COMPLETADO
B32: E-0942 | C32: 46213.865 | E32: EGRESOS | G32: COMISIÓN | I32: Pago de SALDO A LIQUIDAR - 10/7/2026 | N32: 35.872.158 | P32: 40000 | R32: 0 | T32: Efectivo | V32: PAGADO | Y32: COMPLETADO
B33: I-0941 | C33: 46213.864 | E33: INGRESOS | G33: VENTAS | I33: Tattoo - 4 minitattoos nalga | N33: 35.872.158 | P33: 80000 | R33: 0 | T33: Efectivo | V33: PAGADO | Y33: COMPLETADO
B34: E-0930 | C34: 46212.687 | E34: EGRESOS | G34: COMISIÓN | I34: Pago de SALDO A LIQUIDAR - 9/7/2026 | N34: 35.872.158 | P34: 74400 | R34: 0 | T34: Transferencia | V34: PAGADO | Y34: COMPLETADO
B35: I-0929 | C35: 46212.686 | E35: INGRESOS | G35: VENTAS | I35: Tattoo - Nahiara brazo | N35: 35.872.158 | P35: 148800 | R35: 0 | T35: Transferencia | V35: PAGADO | Y35: COMPLETADO
B36: E-0924 | C36: 46211.96 | E36: EGRESOS | G36: COMISIÓN | I36: Pago de SALDO A LIQUIDAR - 8/7/2026 | N36: 35.872.158 | P36: 60000 | R36: 0 | T36: Transferencia | V36: PAGADO | Y36: COMPLETADO
B37: E-0923 | C37: 46211.958 | E37: EGRESOS | G37: COMISIÓN | I37: Pago de SALDO A LIQUIDAR - 8/7/2026 | N37: 35.872.158 | P37: 20000 | R37: 0 | T37: Efectivo | V37: PAGADO | Y37: COMPLETADO
... B172: E-0011 | C172: 46084.852 | E172: EGRESOS | G172: REPARACIONES | I172: Cambio de cerradura | N172: 00.000.000 | P172: 50000 | R172: 0 | T172: Efectivo | V172: PAGADO | Y172: COMPLETADO

Sheet FITNESS
B2: FITNESS | F2: ↓ Actividad ↓ | M2: Inicio de Actividad: | P2: 46111 | T2: SALDO TOTAL | X2: SALDO A LIQUIDAR | AB2: LIQUID. 30 DÍAS | AF2: INGRESO TOTAL | AJ2: EGRESO TOTAL | AN2: BALANCE | AR2: Funcional | AT2: =COUNTIFS($AV$20:$AV$815,"<>Abandonado",$AP$20:$AP$815,AR2) -> 51 | AU2: 26000 | AV2: PPP ($) | AX2: =SUMPRODUCT(AT2:AT6,AU2:AU6)/SUM(AT2:AT6) -> 26480.392
F3: Zona Fitness | M3: Estado: | T3: =(SUMIFS($P$20:$P$800,$G$20:$G$800,"CUOTA",$V$20:$V$800,"PAGADO"))/2 -> 3758500 | X3: =((SUMIFS($P$20:$P$811,$E$20:$E$811,"INGRESOS",$G$20:$G$811,"CUOTA",$V$20:$V$811,"*ADO")+SUMIFS($P$20:$P$811,$E$20:$E$811,"INGRESOS",$G$20:$G$811,"INSCRIPCIÓN",$V$20:$V$811,"*ADO")+SUMIFS($P$20:$P$811,$E$20:$E$811,"INGRESOS",$G$20:$G$811,"CLASES",$V$20:$V$811,"*ADO"))/2)-SUMIFS($P$20:$P$811,$E$20:$E$811,"EGRESOS",$G$20:$G$811,"COMISIÓN",$V$20:$V$811,"PAGADO") -> 923500 | AB3: =SUMIFS($P$20:$P$811,$E$20:$E$811,"EGRESOS",$G$20:$G$811,"COMISIÓN",$Y$20:$Y$811,"COMPLETADO",$C$20:$C$811,">="&DASHBOARD!$AY$2-30,$C$20:$C$811,"<="&DASHBOARD!$AY$2) -> 1085000 | AF3: =SUMIFS($P$20:$P$801,$E$20:$E$801,"INGRESOS",$G$20:$G801,"CUOTA",$V$20:$V$801,"*ADO")+(SUMIFS($P$20:$P$801,$E$20:$E$801,"INGRESOS",$G$20:$G801,"COMISIÓN",$V$20:$V$801,"*ADO")) -> 7517000 | AJ3: =SUMIFS($P$20:$P$801,$E$20:$E$801,"EGRESOS",$G$20:$G$801,"COMISIÓN",$V$20:$V$801,"*ADO")+SUMIFS($P$20:$P$801,$E$20:$E$801,"EGRESOS",$G$20:$G$801,"CMV",$V$20:$V$801,"*ADO") -> 2835000 | AN3: =AF3-AJ3-X3 -> 3758500 | AW3: 25000
AR4: Complemento | AT4: =COUNTIFS($AV$20:$AV$815,"<>Abandonado",$AP$20:$AP$815,AR4) -> 46 | AU4: 25000 | AV4: PP (Real) ($) | AX4: =SUMIFS(AT20:AT815,AT20:AT815,">0",AV20:AV815,"<>Abandonado")/COUNTIFS(AT20:AT815,">0",AV20:AV815,"<>Abandonado") -> 31287.129
B6: Salud: | F6: Estado Municipal: | I6: Iniciando | M6: Estado Financiero: | P6: =IF(T3<0,"Adeudando",IF(X3>0,"Saldo a liquidar",IF(AB3=0,"Sin movimientos",IF(X3=0,"Saldado",)))) -> Saldo a liquidar | T6: LIQUIDAR TOTAL | X6: LIQUIDAR: → | AB6: 0 | AF6: Insc. Activos | AH6: =COUNTIF($AV$20:$AV$815,"<>Abandonado")-COUNTIF($AV$20:$AV$815,"") -> 102 | AR6: Combo F+C | AT6: =COUNTIFS($AV$20:$AV$815,"<>Abandonado",$AP$20:$AP$815,AR6) -> 5 | AU6: 45000 | AV6: Adeudado | AX6: =SUMIF(AV20:AV820,"Adeudando",AT20:AT820) -> 1080000
B8: CARGAR INSCRIPCIÓN | T8: CARGAR PAGO DE CUOTA | AB8: INGRESOS | AJ8: GASTOS | AR8: UTILIDAD
B9: Nombre | E9: Apellido | H9: D.N.I. | J9: Tel. | M9: Actividad | P9: Modalidad | T9: D.N.I. | W9: Nombre | AB9: Enero | AD9: =SUMIFS($P$20:$P$811,$C$20:$C$811,">="&DATE(2026,1,1),$C$20:$C$811,"<"&DATE(2026,2,1),$E$20:$E$811,"INGRESOS",$Y$20:$Y$811,"COMPLETADO") -> 0 | AF9: Febrero | AH9: =SUMIFS($P$20:$P$811,$C$20:$C$811,">="&DATE(2026,2,1),$C$20:$C$811,"<"&DATE(2026,3,1),$E$20:$E$811,"INGRESOS",$Y$20:$Y$811,"COMPLETADO") -> 0 | AJ9: Enero | AL9: =-SUMIFS($P$20:$P$811,$C$20:$C$811,">="&DATE(2026,1,1),$C$20:$C$811,"<"&DATE(2026,2,1),$E$20:$E$811,"EGRESOS",$Y$20:$Y$811,"COMPLETADO") -> 0 | AN9: Febrero | AP9: =-SUMIFS($P$20:$P$811,$C$20:$C$811,">="&DATE(2026,2,1),$C$20:$C$811,"<"&DATE(2026,3,1),$E$20:$E$811,"EGRESOS",$Y$20:$Y$811,"COMPLETADO") -> 0 | AR9: Enero | AT9: =AD9+AL9 -> 0 | AV9: Febrero | AX9: =AH9+AP9 -> 0
AB10: Marzo | AD10: =SUMIFS($P$20:$P$811,$C$20:$C$811,">="&DATE(2026,3,1),$C$20:$C$811,"<"&DATE(2026,4,1),$E$20:$E$811,"INGRESOS",$Y$20:$Y$811,"COMPLETADO") -> 89500 | AF10: Abril | AH10: =SUMIFS($P$20:$P$811,$C$20:$C$811,">="&DATE(2026,4,1),$C$20:$C$811,"<"&DATE(2026,5,1),$E$20:$E$811,"INGRESOS",$Y$20:$Y$811,"COMPLETADO") -> 1622500 | AJ10: Marzo | AL10: =-SUMIFS($P$20:$P$811,$C$20:$C$811,">="&DATE(2026,3,1),$C$20:$C$811,"<"&DATE(2026,4,1),$E$20:$E$811,"EGRESOS",$Y$20:$Y$811,"COMPLETADO") -> -1298067 | AN10: Abril | AP10: =-SUMIFS($P$20:$P$811,$C$20:$C$811,">="&DATE(2026,4,1),$C$20:$C$811,"<"&DATE(2026,5,1),$E$20:$E$811,"EGRESOS",$Y$20:$Y$811,"COMPLETADO") -> -14300 | AR10: Marzo | AT10: =AD10+AL10 -> -1208567 | AV10: Abril | AX10: =AH10+AP10 -> 1608200
B11: Monto de cuota | E11: Descuento (%) | H11: Promoción (-$) | K11: Entrenador | P11: Turno Pref. | T11: Apellido | W11: Monto a pagar | AB11: Mayo | AD11: =SUMIFS($P$20:$P$811,$C$20:$C$811,">="&DATE(2026,5,1),$C$20:$C$811,"<"&DATE(2026,6,1),$E$20:$E$811,"INGRESOS",$Y$20:$Y$811,"COMPLETADO") -> 2141500 | AF11: Junio | AH11: =SUMIFS($P$20:$P$811,$C$20:$C$811,">="&DATE(2026,6,1),$C$20:$C$811,"<"&DATE(2026,7,1),$E$20:$E$811,"INGRESOS",$Y$20:$Y$811,"COMPLETADO") -> 2297500 | AJ11: Mayo | AL11: =-SUMIFS($P$20:$P$811,$C$20:$C$811,">="&DATE(2026,5,1),$C$20:$C$811,"<"&DATE(2026,6,1),$E$20:$E$811,"EGRESOS",$Y$20:$Y$811,"COMPLETADO") -> -837500 | AN11: Junio | AP11: =-SUMIFS($P$20:$P$811,$C$20:$C$811,">="&DATE(2026,6,1),$C$20:$C$811,"<"&DATE(2026,7,1),$E$20:$E$811,"EGRESOS",$Y$20:$Y$811,"COMPLETADO") -> -912500 | AR11: Mayo | AT11: =AD11+AL11 -> 1304000 | AV11: Junio | AX11: =AH11+AP11 -> 1385000
B12: =IF(AND(M10="Funcional",P10="Reducida"),30000,IF(AND(M10="Funcional",P10="Completa"),35000,IF(M10="Complemento",30000,IF(M10="Combo F+C",50000,0))))-H12 -> 0 | AB12: Julio | AD12: =SUMIFS($P$20:$P$811,$C$20:$C$811,">="&DATE(2026,7,1),$C$20:$C$811,"<"&DATE(2026,8,1),$E$20:$E$811,"INGRESOS",$Y$20:$Y$811,"COMPLETADO") -> 1874500 | AF12: Agosto | AH12: =SUMIFS($P$20:$P$811,$C$20:$C$811,">="&DATE(2026,8,1),$C$20:$C$811,"<"&DATE(2026,9,1),$E$20:$E$811,"INGRESOS",$Y$20:$Y$811,"COMPLETADO") -> 0 | AJ12: Julio | AL12: =-SUMIFS($P$20:$P$811,$C$20:$C$811,">="&DATE(2026,7,1),$C$20:$C$811,"<"&DATE(2026,8,1),$E$20:$E$811,"EGRESOS",$Y$20:$Y$811,"COMPLETADO") -> -1085000 | AN12: Agosto | AP12: =-SUMIFS($P$20:$P$811,$C$20:$C$811,">="&DATE(2026,8,1),$C$20:$C$811,"<"&DATE(2026,9,1),$E$20:$E$811,"EGRESOS",$Y$20:$Y$811,"COMPLETADO") -> 0 | AR12: Julio | AT12: =AD12+AL12 -> 789500 | AV12: Agosto | AX12: =AH12+AP12 -> 0
B13: * Condición médica o especificación del estado de salud | T13: Estado | W13: M.P. | AB13: Septiembre | AD13: =SUMIFS($P$20:$P$811,$C$20:$C$811,">="&DATE(2026,9,1),$C$20:$C$811,"<"&DATE(2026,10,1),$E$20:$E$811,"INGRESOS",$Y$20:$Y$811,"COMPLETADO") -> 0 | AF13: Octubre | AH13: =SUMIFS($P$20:$P$811,$C$20:$C$811,">="&DATE(2026,10,1),$C$20:$C$811,"<"&DATE(2026,11,1),$E$20:$E$811,"INGRESOS",$Y$20:$Y$811,"COMPLETADO") -> 0 | AJ13: Septiembre | AL13: =-SUMIFS($P$20:$P$811,$C$20:$C$811,">="&DATE(2026,9,1),$C$20:$C$811,"<"&DATE(2026,10,1),$E$20:$E$811,"EGRESOS",$Y$20:$Y$811,"COMPLETADO") -> 0 | AN13: Octubre | AP13: =-SUMIFS($P$20:$P$811,$C$20:$C$811,">="&DATE(2026,10,1),$C$20:$C$811,"<"&DATE(2026,11,1),$E$20:$E$811,"EGRESOS",$Y$20:$Y$811,"COMPLETADO") -> 0 | AR13: Septiembre | AT13: =AD13+AL13 -> 0 | AV13: Octubre | AX13: =AH13+AP13 -> 0
AB14: Noviembre | AD14: =SUMIFS($P$20:$P$811,$C$20:$C$811,">="&DATE(2026,11,1),$C$20:$C$811,"<"&DATE(2026,12,1),$E$20:$E$811,"INGRESOS",$Y$20:$Y$811,"COMPLETADO") -> 0 | AF14: Diciembre | AH14: =SUMIFS($P$20:$P$811,$C$20:$C$811,">="&DATE(2026,12,1),$C$20:$C$811,"<"&DATE(2027,1,1),$E$20:$E$811,"INGRESOS",$Y$20:$Y$811,"COMPLETADO") -> 0 | AJ14: Noviembre | AL14: =-SUMIFS($P$10:$P$811,$C$10:$C$811,">="&DATE(2026,11,1),$C$10:$C$811,"<"&DATE(2026,12,1),$E$10:$E$811,"EGRESOS",$Y$10:$Y$811,"COMPLETADO") -> 0 | AN14: Diciembre | AP14: =-SUMIFS($P$10:$P$811,$C$10:$C$811,">="&DATE(2026,12,1),$C$10:$C$811,"<"&DATE(2027,1,1),$E$10:$E$811,"EGRESOS",$Y$10:$Y$811,"COMPLETADO") -> 0 | AR14: Noviembre | AT14: =AD14+AL14 -> 0 | AV14: Diciembre | AX14: =AH14+AP14 -> 0
AB15: TOTAL | AF15: =SUM(AD9:AE14,AH9:AI14) -> 8025500 | AJ15: TOTAL | AN15: =SUM(AL9:AM14,AP9:AQ14) -> -4147367 | AR15: TOTAL | AV15: =SUM(AT9:AU14,AX9:AY14) -> 3878133
B18: MOVIMIENTOS | AB18: INSCRIPTOS
B19: Id. | C19: Fecha | E19: Tipo | G19: Categoría | I19: Concepto | N19: Contra-parte | P19: Monto | R19: Impuestos | T19: M.P. | V19: Estado Finan. | Y19: Estado | AB19: Id. | AD19: Fecha | AF19: Nombre | AI19: Apellido | AL19: D.N.I. | AN19: Tel. | AP19: Actividad | AR19: Modalidad | AT19: Cuota | AV19: Estado | AY19: Instructor | BA19: Vence
B20: I-1038 | C20: 46227.655 | E20: INGRESOS | G20: CUOTA | I20: Pago de cuota [F-0027] de Patricia Feldick por actividad de Funcional | N20: 20.118.913 | P20: 0 | R20: 0 | T20: Efectivo | V20: PAGADO | Y20: COMPLETADO | AB20: C-0141 | AD20: 46226.841 | AF20: Rocio Itati | AI20: Araujo | AL20: 42.763.346 | AN20: 3743501958 | AP20: Complemento | AR20: Completa | AT20: 30000 | AV20: Nuevo inscripto | BA20: SIN PAGOS
B21: I-1028 | C21: 46225.829 | E21: INGRESOS | G21: CUOTA | I21: Pago de cuota [F-0018] de Silvina Molina por actividad de Funcional | N21: 33.720.939 | P21: 30000 | R21: 0 | T21: Transferencia | V21: PAGADO | Y21: COMPLETADO | AB21: C-0140 | AD21: 46226.84 | AF21: Mauro Nahuel | AI21: Peña | AL21: 37.460.568 | AN21: 3743555060 | AP21: Complemento | AR21: Completa | AT21: 30000 | AV21: Nuevo inscripto | BA21: SIN PAGOS
B22: I-1026 | C22: 46225.71 | E22: INGRESOS | G22: CUOTA | I22: Pago de cuota [C-0139] de Cristian Gimenez por actividad de Complemento | N22: 33.486.350 | P22: 30000 | R22: 0 | T22: Transferencia | V22: PAGADO | Y22: COMPLETADO | AB22: C-0139 | AD22: 46225.709 | AF22: Cristian | AI22: Gimenez | AL22: 33.486.350 | AN22: 3765103736 | AP22: Complemento | AR22: Completa | AT22: 30000 | AV22: Nuevo inscripto | BA22: 46256
B23: I-1025 | C23: 46225.708 | E23: INGRESOS | G23: CUOTA | I23: Pago de cuota [C-0138] de Daniela Soto por actividad de Complemento | N23: 32.608.369 | P23: 30000 | R23: 0 | T23: Transferencia | V23: PAGADO | Y23: COMPLETADO | AB23: C-0138 | AD23: 46225.707 | AF23: Daniela | AI23: Soto | AL23: 32.608.369 | AN23: 3764355176 | AP23: Complemento | AR23: Completa | AT23: 30000 | AV23: Nuevo inscripto | BA23: 46256
B24: I-1019 | C24: 46224.899 | E24: INGRESOS | G24: CUOTA | I24: Pago de cuota [F-0042] de Carolina Paredes por actividad de Funcional | N24: 28.162.967 | P24: 6000 | R24: 0 | T24: Transferencia | V24: PAGADO | Y24: COMPLETADO | AB24: C-0137 | AD24: 46223.802 | AF24: Wilson William | AI24: Zarza | AL24: 45.135.022 | AN24: 3764815672 | AP24: Complemento | AR24: Completa | AT24: 30000 | AV24: Nuevo inscripto | BA24: SIN PAGOS
B25: I-1014 | C25: 46223.732 | E25: INGRESOS | G25: CUOTA | I25: Pago de cuota [C-0136] de Walter Segovia por actividad de Complemento | N25: 20.060.193 | P25: 30000 | R25: 0 | T25: Transferencia | V25: PAGADO | Y25: COMPLETADO | AB25: C-0136 | AD25: 46223.732 | AF25: Walter | AI25: Segovia | AL25: 20.060.193 | AN25: 3764116489 | AP25: Complemento | AR25: Completa | AT25: 30000 | AV25: Nuevo inscripto | BA25: 46254
B26: I-1011 | C26: 46223.649 | E26: INGRESOS | G26: CUOTA | I26: Pago de cuota [C-0133] de Magdalena Itati Ramos por actividad de Complemento | N26: 37.044.300 | P26: 30000 | R26: 0 | T26: Transferencia | V26: PAGADO | Y26: COMPLETADO | AB26: C-0135 | AD26: 46219.655 | AF26: Victoria | AI26: Weiss | AL26: 50.731.392 | AN26: 3765372200 | AP26: Complemento | AR26: Completa | AT26: 30000 | AV26: Al día | AY26: Natanael | BA26: 46250
B27: I-0993 | C27: 46219.798 | E27: INGRESOS | G27: CUOTA | I27: Pago de cuota [C-0095] de Sergio Rolon por actividad de Complemento | N27: 48.546.483 | P27: 15000 | R27: 0 | T27: Transferencia | V27: PAGADO | Y27: COMPLETADO | AB27: C-0134 | AD27: 46219.654 | AF27: Vanesa | AI27: Campuzano | AL27: 28.818.123 | AN27: 3764851158 | AP27: Complemento | AR27: Completa | AT27: 30000 | AV27: Al día | AY27: Natanael | BA27: 46250
B28: I-0992 | C28: 46219.797 | E28: INGRESOS | G28: CUOTA | I28: Pago de cuota [C-0095] de Sergio Rolon por actividad de Complemento | N28: 48.546.483 | P28: 10000 | R28: 0 | T28: Efectivo | V28: PAGADO | Y28: COMPLETADO | AB28: C-0133 | AD28: 46219.485 | AF28: Magdalena Itati | AI28: Ramos | AL28: 37.044.300 | AN28: 3765414803 | AP28: Complemento | AR28: Completa | AT28: 30000 | AV28: Al día | AY28: Natanael | BA28: 46254
B29: I-0990 | C29: 46219.671 | E29: INGRESOS | G29: CUOTA | I29: Pago de cuota [X-0045] de Claudia Gaona por actividad de Combo F+C | N29: 22.090.381 | P29: 50000 | R29: 0 | T29: Transferencia | V29: PAGADO | Y29: COMPLETADO | AB29: F-0132 | AD29: 46217.753 | AF29: Ana María | AI29: Atamañuk | AL29: 32.085.811 | AN29: 3765043742 | AP29: Funcional | AR29: Reducida | AT29: 30000 | AV29: Al día | AY29: Natanael | BA29: 46248
B30: I-0987 | C30: 46219.659 | E30: INGRESOS | G30: CUOTA | I30: Pago de cuota [C-0135] de Victoria Weiss por actividad de Complemento | N30: 50.731.392 | P30: 25000 | R30: 0 | T30: Efectivo | V30: PAGADO | Y30: COMPLETADO | AB30: C-0131 | AD30: 46216.467 | AF30: Tadeo | AI30: Loyzate | AL30: 48.950.707 | AN30: 3765494643 | AP30: Complemento | AR30: Completa | AT30: 30000 | AV30: Al día | AY30: Natanael | BA30: 46247
B31: I-0986 | C31: 46219.657 | E31: INGRESOS | G31: CUOTA | I31: Pago de cuota [C-0134] de Vanesa Campuzano por actividad de Complemento | N31: 28.818.123 | P31: 25000 | R31: 0 | T31: Efectivo | V31: PAGADO | Y31: COMPLETADO | AB31: F-0130 | AD31: 46213.742 | AF31: Melanie | AI31: Rojas | AL31: 48.649.568 | AN31: 3764198523 | AP31: Funcional | AR31: Reducida | AT31: 30000 | AV31: Al día | AY31: Natanael | BA31: 46244
B32: I-0985 | C32: 46219.627 | E32: INGRESOS | G32: CUOTA | I32: Pago de cuota [F-0127] de Sebastian Borjas por actividad de Funcional | N32: 52.173.302 | P32: 30000 | R32: 0 | T32: Efectivo | V32: PAGADO | Y32: COMPLETADO | AB32: F-0129 | AD32: 46213.74 | AF32: Julian | AI32: Rojas | AL32: 30.531.109 | AN32: 3765093949 | AP32: Funcional | AR32: Reducida | AT32: 30000 | AV32: Al día | AY32: Natanael | BA32: 46244
B33: I-0984 | C33: 46219.624 | E33: INGRESOS | G33: CUOTA | I33: Pago de cuota [F-0123] de Margarita Ayala por actividad de Funcional | N33: 31.914.258 | P33: 35000 | R33: 0 | T33: Efectivo | V33: PAGADO | Y33: COMPLETADO | AB33: C-0128 | AD33: 46205.428 | AF33: Martiniano | AI33: Cañete Azeves | AL33: 48.798.220 | AN33: 3764858687 | AP33: Complemento | AR33: Completa | AT33: 30000 | AV33: Al día | AY33: Natanael | BA33: 46236
B34: I-0975 | C34: 46217.927 | E34: INGRESOS | G34: CUOTA | I34: Pago de cuota [F-0042] de Carolina Paredes por actividad de Funcional | N34: 28.162.967 | P34: 6000 | R34: 0 | T34: Transferencia | V34: PAGADO | Y34: COMPLETADO | AB34: F-0127 | AD34: 46202 | AF34: Sebastian | AI34: Borjas | AL34: 52.173.302 | AN34: 3764902231 | AP34: Funcional | AR34: Reducida | AT34: 30000 | AV34: Al día | AY34: Natanael | BA34: 46250
B35: I-0972 | C35: 46217.754 | E35: INGRESOS | G35: CUOTA | I35: Pago de cuota [F-0132] de Ana María Atamañuk por actividad de Funcional | N35: 32.085.811 | P35: 30000 | R35: 0 | T35: Efectivo | V35: PAGADO | Y35: COMPLETADO | AB35: C-0126 | AD35: 46196.797 | AF35: Thiara | AI35: Zevallos | AL35: 50.572.059 | AN35: 3764107207 | AP35: Complemento | AR35: Completa | AT35: 30000 | AV35: Adeudando | AY35: Natanael | BA35: 46227
B36: I-0965 | C36: 46217.482 | E36: INGRESOS | G36: CUOTA | I36: Pago de cuota [F-0050] de Rosana Neris por actividad de Funcional | N36: 25.496.779 | P36: 30000 | R36: 0 | T36: Transferencia | V36: PAGADO | Y36: COMPLETADO | AB36: F-0125 | AD36: 46196.675 | AF36: Juan Carlos | AI36: Trucheski | AL36: 36.095.636 | AN36: 3764353212 | AP36: Funcional | AR36: Completa | AT36: 35000 | AV36: Adeudando | AY36: Natanael | BA36: 46227
B37: I-0963 | C37: 46216.887 | E37: INGRESOS | G37: CUOTA | I37: Pago de cuota [C-0120] de Daniela Maciel por actividad de Complemento | N37: 50.020.164 | P37: 30000 | R37: 0 | T37: Transferencia | V37: PAGADO | Y37: COMPLETADO | AB37: C-0124 | AD37: 46196.443 | AF37: David | AI37: Raggio | AL37: 45.452.090 | AN37: 3764365497 | AP37: Complemento | AR37: Completa | AT37: 30000 | AV37: Adeudando | AY37: Natanael | BA37: 46227
... B55: I-0897 | C55: 46210.358 | E55: INGRESOS | G55: CUOTA | I55: Pago de cuota [C-0111] de Felipe Palacios por actividad de Complemento | N55: 49.694.411 | P55: 30000 | R55: 0 | T55: Transferencia | V55: PAGADO | Y55: COMPLETADO | AB55: F-0106 | AD55: 46174.789 | AF55: Leandra | AI55: Nuñes | AL55: 25.474.765 | AN55: 3764223119 | AP55: Funcional | AR55: Reducida | AT55: 30000 | AV55: Al día | AY55: Natanael | BA55: 46236
B56: I-0896 | C56: 46210.357 | E56: INGRESOS | G56: CUOTA | I56: Pago de cuota [C-0002] de Ruth Ferreyra por actividad de Complemento | N56: 29.671.795 | P56: 30000 | R56: 0 | T56: Transferencia | V56: PAGADO | Y56: COMPLETADO | AB56: F-0105 | AD56: 46174.431 | AF56: Silvia | AI56: Fernandez | AL56: 28.957.166 | AN56: 3764331464 | AP56: Funcional | AR56: Completa | AT56: 35000 | AV56: Abandonado | AY56: Natanael | BA56: SIN PAGOS
B57: I-0895 | C57: 46209.798 | E57: INGRESOS | G57: CUOTA | I57: Pago de cuota [F-0026] de Zoe Tainski por actividad de Funcional | N57: 36.408.521 | P57: 5000 | R57: 0 | T57: Transferencia | V57: PAGADO | Y57: COMPLETADO | AB57: F-0104 | AD57: 46170.711 | AF57: Dahiana | AI57: Da Silva | AL57: 35.456.307 | AN57: 3764729070 | AP57: Funcional | AR57: Reducida | AT57: 30000 | AV57: Al día | AY57: Natanael | BA57: 46236
B58: I-0894 | C58: 46209.797 | E58: INGRESOS | G58: CUOTA | I58: Pago de cuota [F-0026] de Zoe Tainski por actividad de Funcional | N58: 36.408.521 | P58: 25000 | R58: 0 | T58: Efectivo | V58: PAGADO | Y58: COMPLETADO | AB58: F-0103 | AD58: 46169.989 | AF58: Candela | AI58: Villalba | AL58: 46.551.204 | AN58: 3765103178 | AP58: Funcional | AR58: Reducida | AT58: 30000 | AV58: Adeudando | AY58: Natanael | BA58: 46200
B59: I-0893 | C59: 46209.788 | E59: INGRESOS | G59: CUOTA | I59: Pago de cuota [F-0032] de Gabriela Escobar por actividad de Funcional | N59: 41.761.422 | P59: 30000 | R59: 0 | T59: Efectivo | V59: PAGADO | Y59: COMPLETADO | AB59: C-0102 | AD59: 46169.703 | AF59: Celia Rita | AI59: Montenegro | AL59: 04.789.004 | AN59: 3764812698 | AP59: Complemento | AR59: Completa | AT59: 30000 | AV59: Al día | AY59: Natanael | BA59: 46237
B60: I-0886 | C60: 46209.749 | E60: INGRESOS | G60: CUOTA | I60: Pago de cuota [F-0016] de Amelia Escurdia por actividad de Funcional | N60: 18.438.313 | P60: 30000 | R60: 0 | T60: Efectivo | V60: PAGADO | Y60: COMPLETADO | AB60: C-0101 | AD60: 46168.796 | AF60: Liliana | AI60: Velloso | AL60: 31.330.650 | AN60: 3764534337 | AP60: Complemento | AR60: Completa | AT60: 30000 | AV60: Al día | AY60: Natanael | BA60: 46240
B61: I-0885 | C61: 46209.748 | E61: INGRESOS | G61: CUOTA | I61: Pago de cuota [F-0015] de Antonella Kerber por actividad de Funcional | N61: 46.833.183 | P61: 30000 | R61: 0 | T61: Efectivo | V61: PAGADO | Y61: COMPLETADO | AB61: F-0100 | AD61: 46168.431 | AF61: Camila | AI61: Ortiz | AL61: 44.539.682 | AN61: 3764103083 | AP61: Funcional | AR61: Reducida | AT61: 30000 | AV61: Adeudando | AY61: Natanael | BA61: 46199
B62: I-0884 | C62: 46209.737 | E62: INGRESOS | G62: SEGUROS | I62: Cobro cobertura CELSO - Fitness Natanael | N62: 34.367.425 | P62: 27500 | R62: 0 | T62: Transferencia | V62: PAGADO | Y62: COMPLETADO | AB62: F-0099 | AD62: 46168.425 | AF62: Fabian | AI62: Ortiz | AL62: 23.404.941 | AN62: 3764560219 | AP62: Funcional | AR62: Reducida | AT62: 30000 | AV62: Al día | AY62: Natanael | BA62: 46240
B63: I-0880 | C63: 46209.708 | E63: INGRESOS | G63: CUOTA | I63: Pago de cuota [C-0046] de Susana Cardozo por actividad de Complemento | N63: 34.366.782 | P63: 30000 | R63: 0 | T63: Transferencia | V63: PAGADO | Y63: COMPLETADO | AB63: F-0098 | AD63: 46163.716 | AF63: Agostina | AI63: Duarte | AL63: 49.992.152 | AN63: 3765219000 | AP63: Funcional | AR63: Reducida | AT63: 30000 | AV63: Abandonado | AY63: Natanael | BA63: 46194
B64: I-0877 | C64: 46209.704 | E64: INGRESOS | G64: CUOTA | I64: Pago de cuota [C-0101] de Liliana Velloso por actividad de Complemento | N64: 31.330.650 | P64: 30000 | R64: 0 | T64: Efectivo | V64: PAGADO | Y64: COMPLETADO | AB64: F-0097 | AD64: 46163.429 | AF64: Clair | AI64: Hildebrand | AL64: 18.767.528 | AN64: 3764225322 | AP64: Funcional | AR64: Reducida | AT64: 30000 | AV64: Al día | AY64: Natanael | BA64: 46240
B65: I-0875 | C65: 46209.403 | E65: INGRESOS | G65: CUOTA | I65: Pago de cuota [X-0039] de Graciela Pereyra por actividad de Combo F+C | N65: 30.524.744 | P65: 50000 | R65: 0 | T65: Efectivo | V65: PAGADO | Y65: COMPLETADO | AB65: F-0096 | AD65: 46161.623 | AF65: Elisa | AI65: Reineck | AL65: 25.774.145 | AN65: 3764522088 | AP65: Funcional | AR65: Reducida | AT65: 30000 | AV65: Abandonado | AY65: Natanael | BA65: 46192
B66: I-0874 | C66: 46209.33 | E66: INGRESOS | G66: CUOTA | I66: Pago de cuota [F-0097] de Clair Hildebrand por actividad de Funcional | N66: 18.767.528 | P66: 30000 | R66: 0 | T66: Efectivo | V66: PAGADO | Y66: COMPLETADO | AB66: C-0095 | AD66: 46161.612 | AF66: Sergio | AI66: Rolon | AL66: 48.546.483 | AN66: 3765040200 | AP66: Complemento | AR66: Completa | AT66: 30000 | AV66: Al día | AY66: Natanael | BA66: 46250
B67: I-0873 | C67: 46209.329 | E67: INGRESOS | G67: CUOTA | I67: Pago de cuota [F-0099] de Fabian Ortiz por actividad de Funcional | N67: 23.404.941 | P67: 30000 | R67: 0 | T67: Efectivo | V67: PAGADO | Y67: COMPLETADO | AB67: C-0094 | AD67: 46160.785 | AF67: Anyelina | AI67: Viera | AL67: 49.788.322 | AN67: 3764180558 | AP67: Complemento | AR67: Completa | AT67: 30000 | AV67: Abandonado | AY67: Natanael | BA67: 46191
B68: I-0858 | C68: 46206.667 | E68: INGRESOS | G68: CUOTA | I68: Pago de cuota [C-0102] de Celia Rita Montenegro por actividad de Complemento | N68: 04.789.004 | P68: 30000 | R68: 0 | T68: Efectivo | V68: CANCELADOS | Y68: ANULADO | AB68: C-0093 | AD68: 46160.72 | AF68: Sol Priscila | AI68: Godoy | AL68: 46.730.092 | AN68: 3764383676 | AP68: Complemento | AR68: Completa | AT68: 30000 | AV68: Adeudando | AY68: Natanael | BA68: 46226
... B71: I-0854 | C71: 46206.475 | E71: INGRESOS | G71: CUOTA | I71: Pago de cuota [F-0030] de María Carla Nuñez por actividad de Funcional | N71: 26.258.617 | P71: 30000 | R71: 0 | T71: Efectivo | V71: PAGADO | Y71: COMPLETADO | AB71: C-0090 | AD71: 46156.444 | AF71: Alba | AI71: Gomes | AL71: 13.197.015 | AN71: 3764660205 | AP71: Complemento | AR71: Completa | AT71: 30000 | AV71: Al día | AY71: Natanael | BA71: 46247
B72: I-0847 | C72: 46205.843 | E72: INGRESOS | G72: CUOTA | I72: Pago de cuota [F-0044] de Mia Alfonso por actividad de Complemento | N72: 53.089.524 | P72: 30000 | R72: 0 | T72: Transferencia | V72: PAGADO | Y72: COMPLETADO | AB72: C-0089 | AD72: 46155.75 | AF72: Elisa | AI72: Delgado | AL72: 25.774.016 | AN72: 3764125381 | AP72: Complemento | AR72: Completa | AT72: 30000 | AV72: Abandonado | AY72: Natanael | BA72: SIN PAGOS
B73: I-0846 | C73: 46205.842 | E73: INGRESOS | G73: CUOTA | I73: Pago de cuota [F-0043] de Evana Alfonso por actividad de Complemento | N73: 50.939.699 | P73: 30000 | R73: 0 | T73: Transferencia | V73: PAGADO | Y73: COMPLETADO | AB73: F-0088 | AD73: 46154.621 | AF73: Alejandra | AI73: Fleitas | AL73: 35.838.425 | AN73: 3764264094 | AP73: Funcional | AR73: Completa | AT73: 35000 | AV73: Abandonado | AY73: Natanael | BA73: 46185
B74: I-0843 | C74: 46205.711 | E74: INGRESOS | G74: CUOTA | I74: Pago de cuota [F-0104] de Dahiana Da Silva por actividad de Funcional | N74: 35.456.307 | P74: 30000 | R74: 0 | T74: Transferencia | V74: PAGADO | Y74: COMPLETADO | AB74: F-0087 | AD74: 46153.797 | AF74: Agustina | AI74: Rosas | AL74: 43.619.951 | AN74: 3764174048 | AP74: Funcional | AR74: Reducida | AT74: 30000 | AV74: Al día | AY74: Natanael | BA74: 46244
B75: I-0841 | C75: 46205.669 | E75: INGRESOS | G75: CUOTA | I75: Pago de cuota [F-0085] de Ramon Diaz por actividad de Funcional | N75: 30.216.036 | P75: 30000 | R75: 0 | T75: Efectivo | V75: PAGADO | Y75: COMPLETADO | AB75: C-0086 | AD75: 46153.635 | AF75: Alexandra | AI75: Da Rosa | AL75: 44.073.634 | AN75: 3765192140 | AP75: Complemento | AR75: Completa | AT75: 30000 | AV75: Al día | AY75: Natanael | BA75: 46233
B76: I-0840 | C76: 46205.665 | E76: INGRESOS | G76: CUOTA | I76: Pago de cuota [F-0084] de Marta Ocampo por actividad de Funcional | N76: 31.262.846 | P76: 30000 | R76: 0 | T76: Efectivo | V76: PAGADO | Y76: COMPLETADO | AB76: F-0085 | AD76: 46149.738 | AF76: Ramon | AI76: Diaz | AL76: 30.216.036 | AN76: 3764187013 | AP76: Funcional | AR76: Reducida | AT76: 30000 | AV76: Al día | AY76: Natanael | BA76: 46236
B77: I-0838 | C77: 46205.646 | E77: INGRESOS | G77: CUOTA | I77: Pago de cuota [F-0025] de Valentino Bochman por actividad de Funcional | N77: 49.388.730 | P77: 30000 | R77: 0 | T77: Efectivo | V77: PAGADO | Y77: COMPLETADO | AB77: F-0084 | AD77: 46149.73 | AF77: Marta | AI77: Ocampo | AL77: 31.262.846 | AN77: 3764165515 | AP77: Funcional | AR77: Reducida | AT77: 30000 | AV77: Al día | AY77: Natanael | BA77: 46236
B78: I-0837 | C78: 46205.63 | E78: INGRESOS | G78: CUOTA | I78: Pago de cuota [C-0107] de Jesus Carre Nuñez por actividad de Complemento | N78: 50.942.543 | P78: 30000 | R78: 0 | T78: Efectivo | V78: PAGADO | Y78: COMPLETADO | AB78: F-0083 | AD78: 46148.8 | AF78: Yamila | AI78: Godoy | AL78: 37.589.901 | AN78: 3764117383 | AP78: Funcional | AR78: Reducida | AT78: 30000 | AV78: Adeudando | AY78: Natanael | BA78: 46207
B79: I-0836 | C79: 46205.62 | E79: INGRESOS | G79: CUOTA | I79: Pago de cuota [F-0106] de Leandra Nuñes por actividad de Funcional | N79: 25.474.765 | P79: 30000 | R79: 0 | T79: Efectivo | V79: PAGADO | Y79: COMPLETADO | AB79: F-0082 | AD79: 46148.729 | AF79: Yolanda Isabel | AI79: Segovia | AL79: 20.583.635 | AN79: 3764164504 | AP79: Funcional | AR79: Reducida | AT79: 30000 | AV79: Abandonado | AY79: Natanael | BA79: 46179
B80: I-0833 | C80: 46205.43 | E80: INGRESOS | G80: CUOTA | I80: Pago de cuota [C-0128] de Martiniano Cañete Azeves por actividad de Complemento | N80: 48.798.220 | P80: 25000 | R80: 0 | T80: Transferencia | V80: PAGADO | Y80: COMPLETADO | AB80: F-0081 | AD80: 46147.74 | AF80: Maria Cristina | AI80: Acuña | AL80: 26.974.101 | AN80: 3764742913 | AP80: Funcional | AR80: Reducida | AT80: 30000 | AV80: Adeudando | AY80: Natanael | BA80: 46220
B81: I-0832 | C81: 46205.429 | E81: INGRESOS | G81: CUOTA | I81: Pago de cuota [F-0029] de Natalia Azeves por actividad de Combo F+C | N81: 23.841.749 | P81: 50000 | R81: 0 | T81: Transferencia | V81: PAGADO | Y81: COMPLETADO | AB81: F-0080 | AD81: 46147.739 | AF81: Carmen | AI81: Viveros | AL81: 23.800.457 | AN81: 3764317179 | AP81: Funcional | AR81: Reducida | AT81: 30000 | AV81: Abandonado | AY81: Natanael | BA81: 46185
B82: I-0827 | C82: 46204.823 | E82: INGRESOS | G82: CUOTA | I82: Pago de cuota [X-0108] de Laura Isabel Mendes por actividad de Funcional | N82: 31.262.685 | P82: 35000 | R82: 0 | T82: Transferencia | V82: PAGADO | Y82: COMPLETADO | AB82: F-0079 | AD82: 46147.738 | AF82: Maria Andrea | AI82: Reyes | AL82: 18.216.523 | AN82: 3757417785 | AP82: Complemento | AR82: Completa | AT82: 30000 | AV82: Adeudando | AY82: Natanael | BA82: 46215
B83: I-0826 | C83: 46204.768 | E83: INGRESOS | G83: CUOTA | I83: Pago de cuota [C-0109] de Franco Mendoza por actividad de Complemento | N83: 45.025.248 | P83: 30000 | R83: 0 | T83: Efectivo | V83: PAGADO | Y83: COMPLETADO | AB83: F-0078 | AD83: 46147.732 | AF83: Silvia Karina | AI83: Reyes | AL83: 21.598.362 | AN83: 3764687148 | AP83: Funcional | AR83: Reducida | AT83: 30000 | AV83: Adeudando | AY83: Natanael | BA83: 46215
B84: E-0823 | C84: 46204.466 | E84: EGRESOS | G84: COMISIÓN | I84: Pago de SALDO A LIQUIDAR - 1/7/2026 | N84: 34.367.425 | P84: 1085000 | R84: 0 | T84: Transferencia | V84: PAGADO | Y84: COMPLETADO | AB84: C-0077 | AD84: 46147.427 | AF84: Juana | AI84: Brizuela | AL84: 24.254.958 | AN84: 3765056562 | AP84: Complemento | AR84: Completa | AT84: 30000 | AV84: Al día | AY84: Natanael | BA84: 46241
B85: I-0822 | C85: 46204.421 | E85: INGRESOS | G85: CUOTA | I85: Pago de cuota [C-0113] de Marta Ortellado por actividad de Complemento | N85: 13.197.678 | P85: 30000 | R85: 0 | T85: Efectivo | V85: PAGADO | Y85: COMPLETADO | AB85: C-0076 | AD85: 46146.794 | AF85: Mateo | AI85: Rios | AL85: 53.364.274 | AN85: 3764246183 | AP85: Complemento | AR85: Completa | AT85: 30000 | AV85: Abandonado | AY85: Natanael | BA85: SIN PAGOS
B86: I-0821 | C86: 46204.411 | E86: INGRESOS | G86: CUOTA | I86: Pago de cuota [F-0053] de Belen Da Silva por actividad de Funcional | N86: 38.265.308 | P86: 30000 | R86: 0 | T86: Transferencia | V86: PAGADO | Y86: COMPLETADO | AB86: C-0075 | AD86: 46146.792 | AF86: Benjamin | AI86: Silva | AL86: 50.116.490 | AN86: 3765036442 | AP86: Complemento | AR86: Completa | AT86: 30000 | AV86: Abandonado | AY86: Natanael | BA86: 46177
B87: I-0818 | C87: 46202 | E87: INGRESOS | G87: CUOTA | I87: Pago de cuota [F-0063] de Oscar Ricardo Gamboa por actividad de Funcional | N87: 23.642.681 | P87: 25000 | R87: 0 | T87: Efectivo | V87: PAGADO | Y87: COMPLETADO | AB87: X-0074 | AD87: 46146.766 | AF87: Andrea | AI87: Castro | AL87: 40.821.597 | AN87: 3764357532 | AP87: Combo F+C | AR87: Completa | AT87: 50000 | AV87: Al día | AY87: Natanael | BA87: 46242
B88: I-0816 | C88: 46202 | E88: INGRESOS | G88: CUOTA | I88: Pago de cuota [F-0127] de Sebastian Borjas por actividad de Funcional | N88: 52.173.302 | P88: 25000 | R88: 0 | T88: Efectivo | V88: PAGADO | Y88: COMPLETADO | AB88: C-0073 | AD88: 46146.764 | AF88: Hector | AI88: Montenegro | AL88: 10.957.647 | AN88: 3764351013 | AP88: Complemento | AR88: Completa | AT88: 30000 | AV88: Abandonado | AY88: Natanael | BA88: 46177
B89: I-0815 | C89: 46202 | E89: INGRESOS | G89: CUOTA | I89: Pago de cuota [C-0086] de Alexandra Da Rosa por actividad de Complemento | N89: 44.073.634 | P89: 25000 | R89: 0 | T89: Transferencia | V89: PAGADO | Y89: COMPLETADO | AB89: C-0072 | AD89: 46146.759 | AF89: Andrés | AI89: Rodriguez | AL89: 31.911.595 | AN89: 3764239892 | AP89: Complemento | AR89: Completa | AT89: 30000 | AV89: Abandonado | AY89: Natanael | BA89: 46177
B90: I-0792 | C90: 46198.665 | E90: INGRESOS | G90: CUOTA | I90: Pago de cuota [F-0020] de Soledad Bareyro por actividad de Funcional | N90: 29.138.738 | P90: 25000 | R90: 0 | T90: Transferencia | V90: PAGADO | Y90: COMPLETADO | AB90: C-0071 | AD90: 46146.668 | AF90: Cristina | AI90: Mongelo | AL90: 29.138.812 | AN90: 3764604563 | AP90: Complemento | AR90: Completa | AT90: 30000 | AV90: Abandonado | AY90: Natanael | BA90: 46177
B91: I-0786 | C91: 46197.617 | E91: INGRESOS | G91: CUOTA | I91: Pago de cuota [F-0053] de Belen Da Silva por actividad de Funcional | N91: 38.265.308 | P91: 25000 | R91: 0 | T91: Transferencia | V91: PAGADO | Y91: COMPLETADO | AB91: C-0070 | AD91: 46146.667 | AF91: Virginia | AI91: Zurko | AL91: 29.905.335 | AN91: 3764856161 | AP91: Complemento | AR91: Completa | AT91: 30000 | AV91: Abandonado | AY91: Natanael | BA91: 46177
B92: I-0785 | C92: 46196.798 | E92: INGRESOS | G92: CUOTA | I92: Pago de cuota [C-0126] de Thiara Zevallos por actividad de Complemento | N92: 50.572.059 | P92: 25000 | R92: 0 | T92: Transferencia | V92: PAGADO | Y92: COMPLETADO | AB92: C-0069 | AD92: 46146.356 | AF92: Hugo | AI92: Velozo | AL92: 30.935.948 | AN92: 3764678337 | AP92: Complemento | AR92: Completa | AT92: 30000 | AV92: Abandonado | AY92: Natanael | BA92: 46177
B93: I-0779 | C93: 46196.675 | E93: INGRESOS | G93: CUOTA | I93: Pago de cuota [F-0125] de Juan Carlos Trucheski por actividad de Funcional | N93: 36.095.636 | P93: 30000 | R93: 0 | T93: Transferencia | V93: PAGADO | Y93: COMPLETADO | AB93: C-0068 | AD93: 46146.355 | AF93: Carolina | AI93: Cortes | AL93: 32.330.058 | AN93: 3765123983 | AP93: Complemento | AR93: Completa | AT93: 30000 | AV93: Abandonado | AY93: Natanael | BA93: 46177
B94: I-0778 | C94: 46196.626 | E94: INGRESOS | G94: CUOTA | I94: Pago de cuota [F-0059] de Gabriel Gamboa por actividad de Funcional | N94: 41.694.543 | P94: 25000 | R94: 0 | T94: Efectivo | V94: PAGADO | Y94: COMPLETADO | AB94: C-0067 | AD94: 46146.34 | AF94: Sandra | AI94: Lezcano | AL94: 27.403.221 | AN94: 3764758416 | AP94: Complemento | AR94: Completa | AT94: 30000 | AV94: Adeudando | AY94: Natanael | BA94: 46208
B95: I-0777 | C95: 46196.625 | E95: INGRESOS | G95: CUOTA | I95: Pago de cuota [F-0058] de Lorena Gimenez por actividad de Funcional | N95: 30.524.260 | P95: 25000 | R95: 0 | T95: Efectivo | V95: PAGADO | Y95: COMPLETADO | AB95: C-0066 | AD95: 46142.81 | AF95: Sofía | AI95: Tamburo | AL95: 48.266.113 | AN95: 3764355253 | AP95: Complemento | AR95: Completa | AT95: 30000 | AV95: Abandonado | AY95: Natanael | BA95: 46214
B96: I-0776 | C96: 46196.444 | E96: INGRESOS | G96: CUOTA | I96: Pago de cuota [C-0124] de David Raggio por actividad de Complemento | N96: 45.452.090 | P96: 25000 | R96: 0 | T96: Efectivo | V96: PAGADO | Y96: COMPLETADO | AB96: F-0065 | AD96: 46141.834 | AF96: Ismael | AI96: Duarte | AL96: 49.660.432 | AN96: 3764167183 | AP96: Funcional | AR96: Reducida | AT96: 30000 | AV96: Adeudando | AY96: Natanael | BA96: 46214
B97: I-0772 | C97: 46195.833 | E97: INGRESOS | G97: CUOTA | I97: Pago de cuota [F-0017] de Araceli Olivera por actividad de Funcional | N97: 37.748.021 | P97: 25000 | R97: 0 | T97: Transferencia | V97: PAGADO | Y97: COMPLETADO | AB97: F-0064 | AD97: 46141.833 | AF97: Yhuliana | AI97: Almada | AL97: 49.659.993 | AN97: 3764871309 | AP97: Funcional | AR97: Reducida | AT97: 30000 | AV97: Adeudando | AY97: Natanael | BA97: 46214
... B125: I-0693 | C125: 46182.772 | E125: INGRESOS | G125: CUOTA | I125: Pago de cuota [C-0117] de Mirta Ferreyra por actividad de Complemento | N125: 16.650.378 | P125: 25000 | R125: 0 | T125: Transferencia | V125: PAGADO | Y125: COMPLETADO | AB125: C-0036 | AD125: 46121.703 | AF125: María Gabriela | AI125: Sanchez | AL125: 18.146.279 | AN125: 3764653668 | AP125: Complemento | AR125: Completa | AT125: 30000 | AV125: Al día | AY125: Natanael | BA125: 46244
B126: I-0691 | C126: 46182.705 | E126: INGRESOS | G126: CUOTA | I126: Pago de cuota [C-0037] de Silvina Sanchez por actividad de Complemento | N126: 20.475.024 | P126: 25000 | R126: 0 | T126: Transferencia | V126: PAGADO | Y126: COMPLETADO | AB126: F-0035 | AD126: 46118.885 | AF126: Noelia | AI126: Duarte | AL126: 35.014.171 | AN126: 3764836352 | AP126: Funcional | AR126: Reducida | AT126: 30000 | AV126: Abandonado | AY126: Natanael | BA126: SIN PAGOS
B127: I-0690 | C127: 46182.704 | E127: INGRESOS | G127: CUOTA | I127: Pago de cuota [C-0036] de María Gabriela Sanchez por actividad de Complemento | N127: 18.146.279 | P127: 25000 | R127: 0 | T127: Transferencia | V127: PAGADO | Y127: COMPLETADO | AB127: F-0034 | AD127: 46118.838 | AF127: Fernanda | AI127: Ovelar | AL127: 41.616.482 | AN127: 3764934160 | AP127: Funcional | AR127: Reducida | AT127: 30000 | AV127: Adeudando | AY127: Natanael | BA127: 46214
B128: I-0688 | C128: 46182.683 | E128: INGRESOS | G128: CUOTA | I128: Pago de cuota [C-0040] de Cecilia Caceres por actividad de Complemento | N128: 35.012.250 | P128: 25000 | R128: 0 | T128: Transferencia | V128: PAGADO | Y128: COMPLETADO | AB128: F-0033 | AD128: 46118.795 | AF128: Daiana | AI128: Vega | AL128: 37.583.958 | AN128: 3764168513 | AP128: Funcional | AR128: Reducida | AT128: 30000 | AV128: Abandonado | AY128: Natanael | BA128: 46149
B129: I-0687 | C129: 46182.664 | E129: INGRESOS | G129: CUOTA | I129: Pago de cuota [F-0005] de Marlene Sanabria por actividad de Combo F+C | N129: 28.610.836 | P129: 45000 | R129: 0 | T129: Transferencia | V129: PAGADO | Y129: COMPLETADO | AB129: F-0032 | AD129: 46118.793 | AF129: Gabriela | AI129: Escobar | AL129: 41.761.422 | AN129: 3764181000 | AP129: Funcional | AR129: Reducida | AT129: 30000 | AV129: Al día | AY129: Natanael | BA129: 46240
B130: I-0686 | C130: 46182.62 | E130: INGRESOS | G130: CUOTA | I130: Pago de cuota [F-0006] de Carolina Maliszewski por actividad de Combo F+C | N130: 28.675.956 | P130: 45000 | R130: 0 | T130: Efectivo | V130: PAGADO | Y130: COMPLETADO | AB130: F-0031 | AD130: 46118.462 | AF130: Zulema | AI130: Galeano | AL130: 18.776.248 | AN130: 3764272091 | AP130: Funcional | AR130: Completa | AT130: 35000 | AV130: Al día | AY130: Natanael | BA130: 46247
B131: I-0685 | C131: 46182.454 | E131: INGRESOS | G131: CUOTA | I131: Pago de cuota [F-0031] de Zulema Galeano por actividad de Funcional | N131: 18.776.248 | P131: 30000 | R131: 0 | T131: Efectivo | V131: PAGADO | Y131: COMPLETADO | AB131: F-0030 | AD131: 46118.447 | AF131: María Carla | AI131: Nuñez | AL131: 26.258.617 | AN131: 3764812051 | AP131: Funcional | AR131: Reducida | AT131: 30000 | AV131: Al día | AY131: Natanael | BA131: 46237
B132: I-0683 | C132: 46182.387 | E132: INGRESOS | G132: CUOTA | I132: Pago de cuota [C-0116] de Eliana Micaela Neis por actividad de Complemento | N132: 46.553.502 | P132: 25000 | R132: 0 | T132: Transferencia | V132: PAGADO | Y132: COMPLETADO | AB132: F-0029 | AD132: 46118.446 | AF132: Natalia | AI132: Azeves | AL132: 23.841.749 | AN132: 3764201910 | AP132: Combo F+C | AR132: Completa | AT132: 50000 | AV132: Al día | AY132: Natanael | BA132: 46236
B133: I-0682 | C133: 46182.385 | E133: INGRESOS | G133: CUOTA | I133: Pago de cuota [X-0039] de Graciela Pereyra por actividad de Combo F+C | N133: 30.524.744 | P133: 45000 | R133: 0 | T133: Efectivo | V133: PAGADO | Y133: COMPLETADO | AB133: C-0028 | AD133: 46118.443 | AF133: José Ubaldo | AI133: Rojas | AL133: 11.902.928 | AN133: 3764695832 | AP133: Complemento | AR133: Completa | AT133: 30000 | AV133: Abandonado | AY133: Natanael | BA133: 46181
B134: I-0679 | C134: 46181.821 | E134: INGRESOS | G134: CUOTA | I134: Pago de cuota [C-0109] de Franco Mendoza por actividad de Complemento | N134: 45.025.248 | P134: 25000 | R134: 0 | T134: Efectivo | V134: PAGADO | Y134: COMPLETADO | AB134: F-0027 | AD134: 46113.838 | AF134: Patricia | AI134: Feldick | AL134: 20.118.913 | AN134: 3764801963 | AP134: Funcional | AR134: Completa | AT134: 0 | AV134: Al día | AY134: Natanael | BA134: 46258
B135: I-0676 | C135: 46181.748 | E135: INGRESOS | G135: CUOTA | I135: Pago de cuota [F-0014] de Griselda Bareyro por actividad de Funcional | N135: 32.036.021 | P135: 25000 | R135: 0 | T135: Transferencia | V135: PAGADO | Y135: COMPLETADO | AB135: F-0026 | AD135: 46113.816 | AF135: Zoe | AI135: Tainski | AL135: 36.408.521 | AN135: 3764100452 | AP135: Funcional | AR135: Reducida | AT135: 30000 | AV135: Al día | AY135: Natanael | BA135: 46240
B136: I-0662 | C136: 46178.802 | E136: INGRESOS | G136: CUOTA | I136: Pago de cuota [F-0041] de Abigail Valentino por actividad de Funcional | N136: 32.187.480 | P136: 25000 | R136: 0 | T136: Transferencia | V136: PAGADO | Y136: COMPLETADO | AB136: F-0025 | AD136: 46113.814 | AF136: Valentino | AI136: Bochman | AL136: 49.388.730 | AN136: 3765132100 | AP136: Funcional | AR136: Reducida | AT136: 30000 | AV136: Al día | AY136: Natanael | BA136: 46236
B137: I-0661 | C137: 46178.8 | E137: INGRESOS | G137: CUOTA | I137: Pago de cuota [C-0113] de Marta Ortellado por actividad de Complemento | N137: 13.197.678 | P137: 25000 | R137: 0 | T137: Efectivo | V137: PAGADO | Y137: COMPLETADO | AB137: F-0024 | AD137: 46113.813 | AF137: Adrian | AI137: Andino | AL137: 37.591.797 | AN137: 3765136160 | AP137: Funcional | AR137: Completa | AT137: 35000 | AV137: Abandonado | AY137: Natanael | BA137: 46144
B138: I-0656 | C138: 46177.777 | E138: INGRESOS | G138: CUOTA | I138: Pago de cuota [X-0074] de Andrea Castro por actividad de Combo F+C | N138: 40.821.597 | P138: 45000 | R138: 0 | T138: Efectivo | V138: PAGADO | Y138: COMPLETADO | AB138: F-0023 | AD138: 46113.812 | AF138: Yesica | AI138: Alvez | AL138: 35.014.574 | AN138: 3764159669 | AP138: Funcional | AR138: Completa | AT138: 35000 | AV138: Abandonado | AY138: Natanael | BA138: 46144
... B152: I-0619 | C152: 46175.84 | E152: INGRESOS | G152: CUOTA | I152: Pago de cuota de Ruth Ferreyra | N152: 29.671.795 | P152: 25000 | R152: 0 | T152: Transferencia | V152: PAGADO | Y152: COMPLETADO | AB152: F-0009 | AD152: 46113.402 | AF152: Verónica | AI152: Diaz | AL152: 33.720.810 | AN152: 3764843527 | AP152: Complemento | AR152: Completa | AT152: 30000 | AV152: Adeudando | AY152: Natanael | BA152: 46205
B153: I-0614 | C153: 46175.763 | E153: INGRESOS | G153: CUOTA | I153: Pago de cuota de Alexis Barone | N153: 38.380.602 | P153: 25000 | R153: 0 | T153: Efectivo | V153: PAGADO | Y153: COMPLETADO | AB153: F-0008 | AD153: 46113.401 | AF153: Monica | AI153: Aquino | AL153: 26.327.667 | AN153: 3764564964 | AP153: Funcional | AR153: Reducida | AT153: 30000 | AV153: Abandonado | AY153: Natanael | BA153: SIN PAGOS
B154: I-0610 | C154: 46175.717 | E154: INGRESOS | G154: CUOTA | I154: Pago de cuota de Sandra Boja | N154: 21.113.616 | P154: 25000 | R154: 0 | T154: Efectivo | V154: PAGADO | Y154: COMPLETADO | AB154: F-0007 | AD154: 46113.399 | AF154: Lorena | AI154: Chemes | AL154: 24.601.395 | AN154: 3764171156 | AP154: Funcional | AR154: Reducida | AT154: 30000 | AV154: Adeudando | AY154: Natanael | BA154: 46205
B155: I-0609 | C155: 46175.716 | E155: INGRESOS | G155: CUOTA | I155: Pago de cuota de Ramon Diaz | N155: 30.216.036 | P155: 25000 | R155: 0 | T155: Efectivo | V155: PAGADO | Y155: COMPLETADO | AB155: F-0006 | AD155: 46113.398 | AF155: Carolina | AI155: Maliszewski | AL155: 28.675.956 | AN155: 3764845885 | AP155: Complemento | AR155: Completa | AT155: 30000 | AV155: Al día | AY155: Natanael | BA155: 46247
B156: I-0608 | C156: 46175.715 | E156: INGRESOS | G156: CUOTA | I156: Pago de cuota de Marta Ocampo | N156: 31.262.846 | P156: 25000 | R156: 0 | T156: Efectivo | V156: PAGADO | Y156: COMPLETADO | AB156: F-0005 | AD156: 46113.397 | AF156: Marlene | AI156: Sanabria | AL156: 28.610.836 | AN156: 3764626169 | AP156: Combo F+C | AR156: Completa | AT156: 50000 | AV156: Adeudando | AY156: Natanael | BA156: 46213
B157: I-0607 | C157: 46175.669 | E157: INGRESOS | G157: CUOTA | I157: Pago de cuota de Dahiana Da Silva | N157: 35.456.307 | P157: 25000 | R157: 0 | T157: Transferencia | V157: PAGADO | Y157: COMPLETADO | AB157: F-0004 | AD157: 46113.396 | AF157: Miriam | AI157: Machuca | AL157: 40.336.313 | AN157: 3764391251 | AP157: Funcional | AR157: Reducida | AT157: 30000 | AV157: Abandonado | AY157: Natanael | BA157: 46149
B158: I-0606 | C158: 46175.661 | E158: INGRESOS | G158: CUOTA | I158: Pago de cuota de Oscar Ricardo Gamboa | N158: 23.642.681 | P158: 25000 | R158: 0 | T158: Efectivo | V158: PAGADO | Y158: COMPLETADO | AB158: C-0003 | AD158: 46113.053 | AF158: Sergio | AI158: Alvarez | AL158: 28.818.488 | AN158: 3764296078 | AP158: Complemento | AR158: Completa | AT158: 30000 | AV158: Abandonado | AY158: Natanael | BA158: SIN PAGOS
B159: I-0602 | C159: 46175.442 | E159: INGRESOS | G159: CUOTA | I159: Pago de cuota de Maria Liliana Alberto | N159: 14.985.607 | P159: 25000 | R159: 0 | T159: Efectivo | V159: PAGADO | Y159: COMPLETADO | AB159: C-0002 | AD159: 46113.052 | AF159: Ruth | AI159: Ferreyra | AL159: 29.671.795 | AN159: 3764562820 | AP159: Complemento | AR159: Completa | AT159: 30000 | AV159: Al día | AY159: Natanael | BA159: 46241
B160: I-0601 | C160: 46175.406 | E160: INGRESOS | G160: CUOTA | I160: Pago de cuota de Natalia Azeves | N160: 23.841.749 | P160: 45000 | R160: 0 | T160: Transferencia | V160: PAGADO | Y160: COMPLETADO | AB160: C-0001 | AD160: 46112.12 | AF160: Fernando | AI160: Ramos | AL160: 35.004.264 | AN160: 3765302043 | AP160: Complemento | AR160: Completa | AT160: 0 | AV160: Abandonado | AY160: Natanael | BA160: 46178
B161: I-0595 | C161: 46174.828 | E161: INGRESOS | G161: CUOTA | I161: Pago de cuota de Laura Isabel Mendes | N161: 31.252.685 | P161: 45000 | R161: 0 | T161: Transferencia | V161: PAGADO | Y161: COMPLETADO
B162: I-0594 | C162: 46174.82 | E162: INGRESOS | G162: CUOTA | I162: Pago de cuota de Jesus Carre Nuñez | N162: 50.942.543 | P162: 25000 | R162: 0 | T162: Efectivo | V162: PAGADO | Y162: COMPLETADO
B163: I-0593 | C163: 46174.819 | E163: INGRESOS | G163: CUOTA | I163: Pago de cuota de Leandra Nuñes | N163: 25.474.765 | P163: 25000 | R163: 0 | T163: Efectivo | V163: PAGADO | Y163: COMPLETADO
B164: I-0592 | C164: 46174.801 | E164: INGRESOS | G164: CUOTA | I164: Pago de cuota de Zoe Tainski | N164: 36.408.521 | P164: 25000 | R164: 0 | T164: Transferencia | V164: PAGADO | Y164: COMPLETADO
...

Sheet SALON
B2: SALON | F2: ↓ Actividad ↓ | M2: Inicio de Actividad: | P2: 46118 | T2: SALDO TOTAL | X2: SALDO A LIQUIDAR | AB2: LIQUID. 30 DÍAS | AG2: LUNES | AI2: MARTES | AK2: MIÉRC. | AM2: JUEVES | AO2: VIERNES | AQ2: SÁBADO | AT2: EVENTOS | AX2: PRECIOS
F3: Actividades de Bienestar | M3: Estado: | T3: 0 | X3: =AB19 -> -10000 | AB3: =SUMIFS($P$34:$P$825,$G$34:$G$825,"COMISIÓN",V34:V825,"PAGADO") -> 730000 | AF3: 0.375 | AG3: - | AI3: - | AK3: - | AM3: - | AO3: - | AQ3: - | AT3: D.N.I. | AX3: BÁSICA
AF4: 0.41666667 | AX4: 9:00 - 14:00 | AZ4: 15:00 - 20:00
AF5: 0.4375 | AG5: - | AI5: Yoga | AK5: - | AM5: Yoga | AO5: - | AQ5: - | AT5: Nombre | AX5: 65000 | AZ5: 65000
B6: Salud: | F6: Estado Municipal: | I6: En proceso | M6: Estado Financiero: | P6: =IF(T3<0,"Adeudando",IF(X3<>0,"Saldo a liquidar",IF(AB3=0,"Sin movimientos",IF(X3=0,"Saldado",)))) -> Saldo a liquidar | T6: LIQUIDAR TOTAL | X6: LIQUIDAR: → | AB6: 0 | AF6: 0.47916667 | AX6: 21:00 - 2:00 | AZ6: 21:00 - 5:00
AF7: 0.48958333 | AG7: - | AI7: - | AK7: - | AM7: - | AO7: - | AQ7: - | AT7: Apellido | AX7: 90000 | AZ7: 160000
B8: CARGAR INSCRIPCIÓN | T8: CARGAR PAGO DE CUOTA | AF8: 0.53125 | AX8: DÍA COMPLETO (9:00 - 20:00)
B9: Nombre | E9: Apellido | H9: D.N.I. | J9: Tel. | M9: Actividad | P9: Modalidad | T9: D.N.I. | W9: Nombre | AA9: Apellido | AF9: 0.59375 | AG9: - | AI9: Zumba | AK9: - | AM9: Zumba | AO9: - | AQ9: - | AT9: Modalidad | AX9: 160000
AF10: 0.63541667
B11: Monto de cuota | E11: Descuento (%) | H11: Promoción (-$) | K11: Instructor | P11: Horario | T11: Actividad | W11: Insctructor | AA11: Monto a pagar | AF11: 0.64583333 | AG11: - | AI11: - | AK11: - | AM11: - | AO11: - | AQ11: - | AT11: Turno | AX11: NIÑOS
B12: =IF(M10="",0,VLOOKUP(M10,C18:R30,15,FALSE)) -> 0 | K12: =IF(M10="","",VLOOKUP(M10,C18:I30,5,FALSE)) | AF12: 0.6875 | AX12: 9:00 - 14:00 | AZ12: 15:00 - 20:00
B13: * Condición médica o especificación del estado de salud | T13: Estado | W13: M.P. | AA13: -Descuento (%) | AF13: 0.69791667 | AG13: Karate | AI13: Ritmos Urbanos | AK13: Karate | AM13: Ritmos Urbanos | AO13: Karate | AQ13: - | AT13: Opción | AX13: 220000 | AZ13: 220000
AA14: 0 | AF14: 0.73958333 | AX14: DÍA COMPLETO (9:00 - 20:00)
AF15: 0.75 | AG15: Jiu Jitsu KIDS | AI15: Taekwon-do | AK15: Jiu Jitsu KIDS | AM15: Taekwon-do | AO15: - | AQ15: - | AT15: Sub-total | AX15: 490000
AF16: 0.79166667 | AT16: =IF(AND(AT14="BASE",AT10="Reducido"),65000,IF(AND(AT14="BASE",AT10="Completo"),150000,IF(AND(AT14="CATERING",AT10="Reducido"),(65000+AT18),IF(AND(AT14="CATERING",AT10="Completo"),(150000+AT18),IF(AND(AT14="INFANTIL",AT10="Reducido"),220000,IF(AND(AT14="INFANTIL",AT10="Completo"),450000,0)))))) -> 0
B17: Est. | C17: Disciplina | G17: Instructor | J17: D.N.I. | L17: Horas | N17: Paga | P17: Insc. | Q17: Precio | S17: Saldo a Liq. | U17: Mes | AF17: 0.80208333 | AG17: Jiu Jitsu | AI17: Samba Brasilera | AK17: Jiu Jitsu | AM17: Samba Brasilera | AO17: Jiu Jitsu | AQ17: - | AT17: Adicionales | AX17: EVENTOS
B18: EC | C18: Karate | G18: Sergio Tabossi | J18: 27.574.895 | L18: =COUNTIFS($AG$3:$AR$20,$C18) -> 3 | N18: =VLOOKUP($L18,System!$P$4:$R$16,2,FALSE) -> 110000 | P18: =COUNTIFS($AV$34:$AV$825,"<>Abandonado",$AP$34:$AP$825,C18) -> 14 | Q18: 20000 | S18: {=LET( mesTxt,LOWER(TRIM($U18)), meses,{"enero";"febrero";"marzo";"abril";"mayo";"junio";"julio";"agosto";"septiembre";"octubre";"noviembre";"diciembre"}, mesNum,IFERROR(MATCH(mesTxt,meses,0),0), anio,YEAR(DASHBOARD!$AY$2), inicio,DATE(anio,mesNum,1), fin,EOMONTH(inicio,0), disciplina,LOWER(TRIM($C18)), instructor,LOWER(TRIM($G18)), dniProfesor,TRIM($J18), paga,N($N18), fechas,$C$34:$C$825, tipos,UPPER(TRIM($E$34:$E$825)), categorias,UPPER(TRIM($G$34:$G$825)), conceptos,LOWER(TRIM($I$34:$I$825)), contrapartes,TRIM($N$34:$N$825), montos,$P$34:$P$825, estados,UPPER(TRIM($Y$34:$Y$825)), relacionado, ( IFERROR(ISNUMBER(SEARCH(disciplina,conceptos)),FALSE) * IFERROR(ISNUMBER(SEARCH(instructor,conceptos)),FALSE) ) + IF(dniProfesor="",FALSE,contrapartes=dniProfesor), ingresosCuotas,IF( mesNum=0, 0, SUMPRODUCT( --(fechas>=inicio), --(fechas<=fin), --(tipos="INGRESOS"), --(estados="COMPLETADO"), --ISNUMBER(MATCH(categorias,{"CUOTA";"INSCRIPCIÓN";"INSCRIPCION"},0)), --(relacionado>0), montos ) ), ingresosComision,IF( mesNum=0, 0, SUMPRODUCT( --(fechas>=inicio), --(fechas<=fin), --(tipos="INGRESOS"), --(estados="COMPLETADO"), --ISNUMBER(MATCH(categorias,{"COMISIÓN";"COMISION"},0)), --(relacionado>0), montos ) ), egresosComision,IF( mesNum=0, 0, SUMPRODUCT( --(fechas>=inicio), --(fechas<=fin), --(tipos="EGRESOS"), --(estados="COMPLETADO"), --ISNUMBER(MATCH(categorias,{"COMISIÓN";"COMISION"},0)), --(relacionado>0), montos ) ), IF(mesNum=0,"",ingresosCuotas+ingresosComision-egresosComision-paga) )} -> 110000 | U18: Julio | X18: INGRESO CLUB | AB18: SALDO A LIQ. | AF18: 0.84375 | AT18: 0 | AX18: 8:00 - 14:00 | AZ18: 15:00 - 21:00
B19: EC | C19: Taekwon-do | G19: Luzmila Cinquetti | J19: 48.651.728 | L19: =COUNTIFS($AG$3:$AR$20,$C19) -> 2 | N19: =VLOOKUP($L19,System!$P$4:$R$16,2,FALSE) -> 85000 | P19: =COUNTIFS($AV$34:$AV$825,"<>Abandonado",$AP$34:$AP$825,C19) -> 14 | Q19: 20000 | S19: {=LET( mesTxt,LOWER(TRIM($U19)), meses,{"enero";"febrero";"marzo";"abril";"mayo";"junio";"julio";"agosto";"septiembre";"octubre";"noviembre";"diciembre"}, mesNum,IFERROR(MATCH(mesTxt,meses,0),0), anio,YEAR(DASHBOARD!$AY$2), inicio,DATE(anio,mesNum,1), fin,EOMONTH(inicio,0), disciplina,LOWER(TRIM($C19)), instructor,LOWER(TRIM($G19)), dniProfesor,TRIM($J19), paga,N($N19), fechas,$C$34:$C$825, tipos,UPPER(TRIM($E$34:$E$825)), categorias,UPPER(TRIM($G$34:$G$825)), conceptos,LOWER(TRIM($I$34:$I$825)), contrapartes,TRIM($N$34:$N$825), montos,$P$34:$P$825, estados,UPPER(TRIM($Y$34:$Y$825)), relacionado, ( IFERROR(ISNUMBER(SEARCH(disciplina,conceptos)),FALSE) * IFERROR(ISNUMBER(SEARCH(instructor,conceptos)),FALSE) ) + IF(dniProfesor="",FALSE,contrapartes=dniProfesor), ingresosCuotas,IF( mesNum=0, 0, SUMPRODUCT( --(fechas>=inicio), --(fechas<=fin), --(tipos="INGRESOS"), --(estados="COMPLETADO"), --ISNUMBER(MATCH(categorias,{"CUOTA";"INSCRIPCIÓN";"INSCRIPCION"},0)), --(relacionado>0), montos ) ), ingresosComision,IF( mesNum=0, 0, SUMPRODUCT( --(fechas>=inicio), --(fechas<=fin), --(tipos="INGRESOS"), --(estados="COMPLETADO"), --ISNUMBER(MATCH(categorias,{"COMISIÓN";"COMISION"},0)), --(relacionado>0), montos ) ), egresosComision,IF( mesNum=0, 0, SUMPRODUCT( --(fechas>=inicio), --(fechas<=fin), --(tipos="EGRESOS"), --(estados="COMPLETADO"), --ISNUMBER(MATCH(categorias,{"COMISIÓN";"COMISION"},0)), --(relacionado>0), montos ) ), IF(mesNum=0,"",ingresosCuotas+ingresosComision-egresosComision-paga) )} -> -25000 | U19: Julio | X19: =SUMIF(B18:B30,"EC",N18:N30) -> 600000 | AB19: =SUMIF(B18:B30,"EC",S18:T30) -> -10000 | AF19: 0.85416667 | AG19: Jiu Jitsu | AI19: Kickboxing | AK19: Jiu Jitsu | AM19: Kickboxing | AO19: Jiu Jitsu | AQ19: - | AX19: 110000 | AZ19: 110000
B20: EC | C20: Samba Brasilera | G20: Oriana Cubilla | J20: 46.730.014 | L20: =COUNTIFS($AG$3:$AR$20,$C20) -> 2 | N20: =VLOOKUP($L20,System!$P$4:$R$16,2,FALSE) -> 85000 | P20: =COUNTIFS($AV$34:$AV$825,"<>Abandonado",$AP$34:$AP$825,C20) -> 4 | Q20: 20000 | S20: {=LET( mesTxt,LOWER(TRIM($U20)), meses,{"enero";"febrero";"marzo";"abril";"mayo";"junio";"julio";"agosto";"septiembre";"octubre";"noviembre";"diciembre"}, mesNum,IFERROR(MATCH(mesTxt,meses,0),0), anio,YEAR(DASHBOARD!$AY$2), inicio,DATE(anio,mesNum,1), fin,EOMONTH(inicio,0), disciplina,LOWER(TRIM($C20)), instructor,LOWER(TRIM($G20)), dniProfesor,TRIM($J20), paga,N($N20), fechas,$C$34:$C$825, tipos,UPPER(TRIM($E$34:$E$825)), categorias,UPPER(TRIM($G$34:$G$825)), conceptos,LOWER(TRIM($I$34:$I$825)), contrapartes,TRIM($N$34:$N$825), montos,$P$34:$P$825, estados,UPPER(TRIM($Y$34:$Y$825)), relacionado, ( IFERROR(ISNUMBER(SEARCH(disciplina,conceptos)),FALSE) * IFERROR(ISNUMBER(SEARCH(instructor,conceptos)),FALSE) ) + IF(dniProfesor="",FALSE,contrapartes=dniProfesor), ingresosCuotas,IF( mesNum=0, 0, SUMPRODUCT( --(fechas>=inicio), --(fechas<=fin), --(tipos="INGRESOS"), --(estados="COMPLETADO"), --ISNUMBER(MATCH(categorias,{"CUOTA";"INSCRIPCIÓN";"INSCRIPCION"},0)), --(relacionado>0), montos ) ), ingresosComision,IF( mesNum=0, 0, SUMPRODUCT( --(fechas>=inicio), --(fechas<=fin), --(tipos="INGRESOS"), --(estados="COMPLETADO"), --ISNUMBER(MATCH(categorias,{"COMISIÓN";"COMISION"},0)), --(relacionado>0), montos ) ), egresosComision,IF( mesNum=0, 0, SUMPRODUCT( --(fechas>=inicio), --(fechas<=fin), --(tipos="EGRESOS"), --(estados="COMPLETADO"), --ISNUMBER(MATCH(categorias,{"COMISIÓN";"COMISION"},0)), --(relacionado>0), montos ) ), IF(mesNum=0,"",ingresosCuotas+ingresosComision-egresosComision-paga) )} -> -85000 | U20: Julio | AF20: 0.89583333 | AX20: DÍA COMPLETO (9:00 - 20:00)
B21: P | C21: Ritmos Urbanos | G21: Lujan Rodriguez | J21: 42.353.243 | L21: =COUNTIFS($AG$3:$AR$20,$C21) -> 2 | N21: =VLOOKUP($L21,System!$P$4:$R$16,2,FALSE) -> 85000 | P21: =COUNTIFS($AV$34:$AV$825,"<>Abandonado",$AP$34:$AP$825,C21) -> 0 | Q21: 25000 | S21: {=LET( mesTxt,LOWER(TRIM($U21)), meses,{"enero";"febrero";"marzo";"abril";"mayo";"junio";"julio";"agosto";"septiembre";"octubre";"noviembre";"diciembre"}, mesNum,IFERROR(MATCH(mesTxt,meses,0),0), anio,YEAR(DASHBOARD!$AY$2), inicio,DATE(anio,mesNum,1), fin,EOMONTH(inicio,0), disciplina,LOWER(TRIM($C21)), instructor,LOWER(TRIM($G21)), dniProfesor,TRIM($J21), paga,N($N21), fechas,$C$34:$C$825, tipos,UPPER(TRIM($E$34:$E$825)), categorias,UPPER(TRIM($G$34:$G$825)), conceptos,LOWER(TRIM($I$34:$I$825)), contrapartes,TRIM($N$34:$N$825), montos,$P$34:$P$825, estados,UPPER(TRIM($Y$34:$Y$825)), relacionado, ( IFERROR(ISNUMBER(SEARCH(disciplina,conceptos)),FALSE) * IFERROR(ISNUMBER(SEARCH(instructor,conceptos)),FALSE) ) + IF(dniProfesor="",FALSE,contrapartes=dniProfesor), ingresosCuotas,IF( mesNum=0, 0, SUMPRODUCT( --(fechas>=inicio), --(fechas<=fin), --(tipos="INGRESOS"), --(estados="COMPLETADO"), --ISNUMBER(MATCH(categorias,{"CUOTA";"INSCRIPCIÓN";"INSCRIPCION"},0)), --(relacionado>0), montos ) ), ingresosComision,IF( mesNum=0, 0, SUMPRODUCT( --(fechas>=inicio), --(fechas<=fin), --(tipos="INGRESOS"), --(estados="COMPLETADO"), --ISNUMBER(MATCH(categorias,{"COMISIÓN";"COMISION"},0)), --(relacionado>0), montos ) ), egresosComision,IF( mesNum=0, 0, SUMPRODUCT( --(fechas>=inicio), --(fechas<=fin), --(tipos="EGRESOS"), --(estados="COMPLETADO"), --ISNUMBER(MATCH(categorias,{"COMISIÓN";"COMISION"},0)), --(relacionado>0), montos ) ), IF(mesNum=0,"",ingresosCuotas+ingresosComision-egresosComision-paga) )} -> -85000 | U21: Julio | AX21: 270000
B22: EC | C22: Yoga | G22: Estefanía Solis | J22: 28.553.991 | L22: =COUNTIFS($AG$3:$AR$20,$C22) -> 2 | N22: =VLOOKUP($L22,System!$P$4:$R$16,2,FALSE) -> 85000 | P22: =COUNTIFS($AV$34:$AV$825,"<>Abandonado",$AP$34:$AP$825,C22) -> 4 | Q22: 30000 | S22: {=LET( mesTxt,LOWER(TRIM($U22)), meses,{"enero";"febrero";"marzo";"abril";"mayo";"junio";"julio";"agosto";"septiembre";"octubre";"noviembre";"diciembre"}, mesNum,IFERROR(MATCH(mesTxt,meses,0),0), anio,YEAR(DASHBOARD!$AY$2), inicio,DATE(anio,mesNum,1), fin,EOMONTH(inicio,0), disciplina,LOWER(TRIM($C22)), instructor,LOWER(TRIM($G22)), dniProfesor,TRIM($J22), paga,N($N22), fechas,$C$34:$C$825, tipos,UPPER(TRIM($E$34:$E$825)), categorias,UPPER(TRIM($G$34:$G$825)), conceptos,LOWER(TRIM($I$34:$I$825)), contrapartes,TRIM($N$34:$N$825), montos,$P$34:$P$825, estados,UPPER(TRIM($Y$34:$Y$825)), relacionado, ( IFERROR(ISNUMBER(SEARCH(disciplina,conceptos)),FALSE) * IFERROR(ISNUMBER(SEARCH(instructor,conceptos)),FALSE) ) + IF(dniProfesor="",FALSE,contrapartes=dniProfesor), ingresosCuotas,IF( mesNum=0, 0, SUMPRODUCT( --(fechas>=inicio), --(fechas<=fin), --(tipos="INGRESOS"), --(estados="COMPLETADO"), --ISNUMBER(MATCH(categorias,{"CUOTA";"INSCRIPCIÓN";"INSCRIPCION"},0)), --(relacionado>0), montos ) ), ingresosComision,IF( mesNum=0, 0, SUMPRODUCT( --(fechas>=inicio), --(fechas<=fin), --(tipos="INGRESOS"), --(estados="COMPLETADO"), --ISNUMBER(MATCH(categorias,{"COMISIÓN";"COMISION"},0)), --(relacionado>0), montos ) ), egresosComision,IF( mesNum=0, 0, SUMPRODUCT( --(fechas>=inicio), --(fechas<=fin), --(tipos="EGRESOS"), --(estados="COMPLETADO"), --ISNUMBER(MATCH(categorias,{"COMISIÓN";"COMISION"},0)), --(relacionado>0), montos ) ), IF(mesNum=0,"",ingresosCuotas+ingresosComision-egresosComision-paga) )} -> 35000 | U22: Julio | AX22: NOCTURNO (Fiestas)
B23: A | C23: -- | G23: - | J23: - | L23: =COUNTIFS($AG$3:$AR$20,$C23) -> 0 | N23: =VLOOKUP($L23,System!$P$4:$R$16,2,FALSE) -> 0 | P23: =COUNTIFS($AV$34:$AV$825,"<>Abandonado",$AP$34:$AP$825,C23) -> 0 | Q23: - | S23: {=LET( mesTxt,LOWER(TRIM($U23)), meses,{"enero";"febrero";"marzo";"abril";"mayo";"junio";"julio";"agosto";"septiembre";"octubre";"noviembre";"diciembre"}, mesNum,IFERROR(MATCH(mesTxt,meses,0),0), anio,YEAR(DASHBOARD!$AY$2), inicio,DATE(anio,mesNum,1), fin,EOMONTH(inicio,0), disciplina,LOWER(TRIM($C23)), instructor,LOWER(TRIM($G23)), dniProfesor,TRIM($J23), paga,N($N23), fechas,$C$34:$C$825, tipos,UPPER(TRIM($E$34:$E$825)), categorias,UPPER(TRIM($G$34:$G$825)), conceptos,LOWER(TRIM($I$34:$I$825)), contrapartes,TRIM($N$34:$N$825), montos,$P$34:$P$825, estados,UPPER(TRIM($Y$34:$Y$825)), relacionado, ( IFERROR(ISNUMBER(SEARCH(disciplina,conceptos)),FALSE) * IFERROR(ISNUMBER(SEARCH(instructor,conceptos)),FALSE) ) + IF(dniProfesor="",FALSE,contrapartes=dniProfesor), ingresosCuotas,IF( mesNum=0, 0, SUMPRODUCT( --(fechas>=inicio), --(fechas<=fin), --(tipos="INGRESOS"), --(estados="COMPLETADO"), --ISNUMBER(MATCH(categorias,{"CUOTA";"INSCRIPCIÓN";"INSCRIPCION"},0)), --(relacionado>0), montos ) ), ingresosComision,IF( mesNum=0, 0, SUMPRODUCT( --(fechas>=inicio), --(fechas<=fin), --(tipos="INGRESOS"), --(estados="COMPLETADO"), --ISNUMBER(MATCH(categorias,{"COMISIÓN";"COMISION"},0)), --(relacionado>0), montos ) ), egresosComision,IF( mesNum=0, 0, SUMPRODUCT( --(fechas>=inicio), --(fechas<=fin), --(tipos="EGRESOS"), --(estados="COMPLETADO"), --ISNUMBER(MATCH(categorias,{"COMISIÓN";"COMISION"},0)), --(relacionado>0), montos ) ), IF(mesNum=0,"",ingresosCuotas+ingresosComision-egresosComision-paga) )} | X23: INGRESOS | AF23: GASTOS | AN23: UTILIDAD | AX23: 280000
B24: A | C24: -- | G24: - | J24: - | L24: =COUNTIFS($AG$3:$AR$20,$C24) -> 0 | N24: =VLOOKUP($L24,System!$P$4:$R$16,2,FALSE) -> 0 | P24: =COUNTIFS($AV$34:$AV$825,"<>Abandonado",$AP$34:$AP$825,C24) -> 0 | Q24: - | S24: {=LET( mesTxt,LOWER(TRIM($U24)), meses,{"enero";"febrero";"marzo";"abril";"mayo";"junio";"julio";"agosto";"septiembre";"octubre";"noviembre";"diciembre"}, mesNum,IFERROR(MATCH(mesTxt,meses,0),0), anio,YEAR(DASHBOARD!$AY$2), inicio,DATE(anio,mesNum,1), fin,EOMONTH(inicio,0), disciplina,LOWER(TRIM($C24)), instructor,LOWER(TRIM($G24)), dniProfesor,TRIM($J24), paga,N($N24), fechas,$C$34:$C$825, tipos,UPPER(TRIM($E$34:$E$825)), categorias,UPPER(TRIM($G$34:$G$825)), conceptos,LOWER(TRIM($I$34:$I$825)), contrapartes,TRIM($N$34:$N$825), montos,$P$34:$P$825, estados,UPPER(TRIM($Y$34:$Y$825)), relacionado, ( IFERROR(ISNUMBER(SEARCH(disciplina,conceptos)),FALSE) * IFERROR(ISNUMBER(SEARCH(instructor,conceptos)),FALSE) ) + IF(dniProfesor="",FALSE,contrapartes=dniProfesor), ingresosCuotas,IF( mesNum=0, 0, SUMPRODUCT( --(fechas>=inicio), --(fechas<=fin), --(tipos="INGRESOS"), --(estados="COMPLETADO"), --ISNUMBER(MATCH(categorias,{"CUOTA";"INSCRIPCIÓN";"INSCRIPCION"},0)), --(relacionado>0), montos ) ), ingresosComision,IF( mesNum=0, 0, SUMPRODUCT( --(fechas>=inicio), --(fechas<=fin), --(tipos="INGRESOS"), --(estados="COMPLETADO"), --ISNUMBER(MATCH(categorias,{"COMISIÓN";"COMISION"},0)), --(relacionado>0), montos ) ), egresosComision,IF( mesNum=0, 0, SUMPRODUCT( --(fechas>=inicio), --(fechas<=fin), --(tipos="EGRESOS"), --(estados="COMPLETADO"), --ISNUMBER(MATCH(categorias,{"COMISIÓN";"COMISION"},0)), --(relacionado>0), montos ) ), IF(mesNum=0,"",ingresosCuotas+ingresosComision-egresosComision-paga) )} | X24: Enero | Z24: =SUMIFS($P$34:$P$825,$C$34:$C$825,">="&DATE(2026,1,1),$C$34:$C$825,"<"&DATE(2026,2,1),$E$34:$E$825,"INGRESOS",$Y$34:$Y$825,"COMPLETADO") -> 0 | AB24: Febrero | AD24: =SUMIFS($P$34:$P$825,$C$34:$C$825,">="&DATE(2026,2,1),$C$34:$C$825,"<"&DATE(2026,3,1),$E$34:$E$825,"INGRESOS",$Y$34:$Y$825,"COMPLETADO") -> 0 | AF24: Enero | AH24: =-SUMIFS($P$34:$P$825,$C$34:$C$825,">="&DATE(2026,1,1),$C$34:$C$825,"<"&DATE(2026,2,1),$E$34:$E$825,"EGRESOS",$Y$34:$Y$825,"COMPLETADO") -> 0 | AJ24: Febrero | AL24: =-SUMIFS($P$34:$P$825,$C$34:$C$825,">="&DATE(2026,2,1),$C$34:$C$825,"<"&DATE(2026,3,1),$E$34:$E$825,"EGRESOS",$Y$34:$Y$825,"COMPLETADO") -> 0 | AN24: Enero | AP24: =Z24+AH24 -> 0 | AR24: Febrero | AT24: =AD24+AL24 -> 0
B25: A | C25: -- | G25: - | J25: - | L25: =COUNTIFS($AG$3:$AR$20,$C25) -> 0 | N25: =VLOOKUP($L25,System!$P$4:$R$16,2,FALSE) -> 0 | P25: =COUNTIFS($AV$34:$AV$825,"<>Abandonado",$AP$34:$AP$825,C25) -> 0 | Q25: - | S25: {=LET( mesTxt,LOWER(TRIM($U25)), meses,{"enero";"febrero";"marzo";"abril";"mayo";"junio";"julio";"agosto";"septiembre";"octubre";"noviembre";"diciembre"}, mesNum,IFERROR(MATCH(mesTxt,meses,0),0), anio,YEAR(DASHBOARD!$AY$2), inicio,DATE(anio,mesNum,1), fin,EOMONTH(inicio,0), disciplina,LOWER(TRIM($C25)), instructor,LOWER(TRIM($G25)), dniProfesor,TRIM($J25), paga,N($N25), fechas,$C$34:$C$825, tipos,UPPER(TRIM($E$34:$E$825)), categorias,UPPER(TRIM($G$34:$G$825)), conceptos,LOWER(TRIM($I$34:$I$825)), contrapartes,TRIM($N$34:$N$825), montos,$P$34:$P$825, estados,UPPER(TRIM($Y$34:$Y$825)), relacionado, ( IFERROR(ISNUMBER(SEARCH(disciplina,conceptos)),FALSE) * IFERROR(ISNUMBER(SEARCH(instructor,conceptos)),FALSE) ) + IF(dniProfesor="",FALSE,contrapartes=dniProfesor), ingresosCuotas,IF( mesNum=0, 0, SUMPRODUCT( --(fechas>=inicio), --(fechas<=fin), --(tipos="INGRESOS"), --(estados="COMPLETADO"), --ISNUMBER(MATCH(categorias,{"CUOTA";"INSCRIPCIÓN";"INSCRIPCION"},0)), --(relacionado>0), montos ) ), ingresosComision,IF( mesNum=0, 0, SUMPRODUCT( --(fechas>=inicio), --(fechas<=fin), --(tipos="INGRESOS"), --(estados="COMPLETADO"), --ISNUMBER(MATCH(categorias,{"COMISIÓN";"COMISION"},0)), --(relacionado>0), montos ) ), egresosComision,IF( mesNum=0, 0, SUMPRODUCT( --(fechas>=inicio), --(fechas<=fin), --(tipos="EGRESOS"), --(estados="COMPLETADO"), --ISNUMBER(MATCH(categorias,{"COMISIÓN";"COMISION"},0)), --(relacionado>0), montos ) ), IF(mesNum=0,"",ingresosCuotas+ingresosComision-egresosComision-paga) )} | X25: Marzo | Z25: =SUMIFS($P$34:$P$825,$C$34:$C$825,">="&DATE(2026,3,1),$C$34:$C$825,"<"&DATE(2026,4,1),$E$34:$E$825,"INGRESOS",$Y$34:$Y$825,"COMPLETADO") -> 0 | AB25: Abril | AD25: =SUMIFS($P$34:$P$825,$C$34:$C$825,">="&DATE(2026,4,1),$C$34:$C$825,"<"&DATE(2026,5,1),$E$34:$E$825,"INGRESOS",$Y$34:$Y$825,"COMPLETADO") -> 392500 | AF25: Marzo | AH25: =-SUMIFS($P$34:$P$825,$C$34:$C$825,">="&DATE(2026,3,1),$C$34:$C$825,"<"&DATE(2026,4,1),$E$34:$E$825,"EGRESOS",$Y$34:$Y$825,"COMPLETADO") -> -653000 | AJ25: Abril | AL25: =-SUMIFS($P$34:$P$825,$C$34:$C$825,">="&DATE(2026,4,1),$C$34:$C$825,"<"&DATE(2026,5,1),$E$34:$E$825,"EGRESOS",$Y$34:$Y$825,"COMPLETADO") -> -55000 | AN25: Marzo | AP25: =Z25+AH25 -> -653000 | AR25: Abril | AT25: =AD25+AL25 -> 337500 | AW25: INGRESO TOTAL | AZ25: EGRESO TOTAL
B26: S | C26: Zumba | G26: Alejandra Gonzalez | J26: 29.058.004 | L26: =COUNTIFS($AG$3:$AR$20,$C26) -> 2 | N26: =VLOOKUP($L26,System!$P$4:$R$16,2,FALSE) -> 85000 | P26: =COUNTIFS($AV$34:$AV$825,"<>Abandonado",$AP$34:$AP$825,C26) -> 0 | Q26: 20000 | S26: {=LET( mesTxt,LOWER(TRIM($U26)), meses,{"enero";"febrero";"marzo";"abril";"mayo";"junio";"julio";"agosto";"septiembre";"octubre";"noviembre";"diciembre"}, mesNum,IFERROR(MATCH(mesTxt,meses,0),0), anio,YEAR(DASHBOARD!$AY$2), inicio,DATE(anio,mesNum,1), fin,EOMONTH(inicio,0), disciplina,LOWER(TRIM($C26)), instructor,LOWER(TRIM($G26)), dniProfesor,TRIM($J26), paga,N($N26), fechas,$C$34:$C$825, tipos,UPPER(TRIM($E$34:$E$825)), categorias,UPPER(TRIM($G$34:$G$825)), conceptos,LOWER(TRIM($I$34:$I$825)), contrapartes,TRIM($N$34:$N$825), montos,$P$34:$P$825, estados,UPPER(TRIM($Y$34:$Y$825)), relacionado, ( IFERROR(ISNUMBER(SEARCH(disciplina,conceptos)),FALSE) * IFERROR(ISNUMBER(SEARCH(instructor,conceptos)),FALSE) ) + IF(dniProfesor="",FALSE,contrapartes=dniProfesor), ingresosCuotas,IF( mesNum=0, 0, SUMPRODUCT( --(fechas>=inicio), --(fechas<=fin), --(tipos="INGRESOS"), --(estados="COMPLETADO"), --ISNUMBER(MATCH(categorias,{"CUOTA";"INSCRIPCIÓN";"INSCRIPCION"},0)), --(relacionado>0), montos ) ), ingresosComision,IF( mesNum=0, 0, SUMPRODUCT( --(fechas>=inicio), --(fechas<=fin), --(tipos="INGRESOS"), --(estados="COMPLETADO"), --ISNUMBER(MATCH(categorias,{"COMISIÓN";"COMISION"},0)), --(relacionado>0), montos ) ), egresosComision,IF( mesNum=0, 0, SUMPRODUCT( --(fechas>=inicio), --(fechas<=fin), --(tipos="EGRESOS"), --(estados="COMPLETADO"), --ISNUMBER(MATCH(categorias,{"COMISIÓN";"COMISION"},0)), --(relacionado>0), montos ) ), IF(mesNum=0,"",ingresosCuotas+ingresosComision-egresosComision-paga) )} -> -85000 | U26: Julio | X26: Mayo | Z26: =SUMIFS($P$34:$P$825,$C$34:$C$825,">="&DATE(2026,5,1),$C$34:$C$825,"<"&DATE(2026,6,1),$E$34:$E$825,"INGRESOS",$Y$34:$Y$825,"COMPLETADO") -> 665000 | AB26: Junio | AD26: =SUMIFS($P$34:$P$825,$C$34:$C$825,">="&DATE(2026,6,1),$C$34:$C$825,"<"&DATE(2026,7,1),$E$34:$E$825,"INGRESOS",$Y$34:$Y$825,"COMPLETADO") -> 810000 | AF26: Mayo | AH26: =-SUMIFS($P$34:$P$825,$C$34:$C$825,">="&DATE(2026,5,1),$C$34:$C$825,"<"&DATE(2026,6,1),$E$34:$E$825,"EGRESOS",$Y$34:$Y$825,"COMPLETADO") -> -65000 | AJ26: Junio | AL26: =-SUMIFS($P$34:$P$825,$C$34:$C$825,">="&DATE(2026,6,1),$C$34:$C$825,"<"&DATE(2026,7,1),$E$34:$E$825,"EGRESOS",$Y$34:$Y$825,"COMPLETADO") -> -454050 | AN26: Mayo | AP26: =Z26+AH26 -> 600000 | AR26: Junio | AT26: =AD26+AL26 -> 355950 | AW26: =SUMIFS($P$34:$P$825,$E$34:$E$825,"INGRESOS",$G$34:$G825,"CUOTA",$V$34:$V$825,"*ADO")+(SUMIFS($P$34:$P$825,$E$34:$E$825,"INGRESOS",$G$34:$G825,"COMISIÓN",$V$34:$V$825,"*ADO")) -> 2412500 | AZ26: =SUMIFS($P$34:$P$825,$E$34:$E$825,"EGRESOS",$G$34:$G825,"COMISIÓN",$V$34:$V$825,"*ADO")+SUMIFS($P$34:$P$825,$E$34:$E$825,"EGRESOS",$G$34:$G$825,"CMV",$V$34:$V$825,"*ADO") -> 445000
B27: EC | C27: Kickboxing | G27: Natalia Ortiz | J27: 32.261.469 | L27: =COUNTIFS($AG$3:$AR$20,$C27) -> 2 | N27: =VLOOKUP($L27,System!$P$4:$R$16,2,FALSE) -> 85000 | P27: =COUNTIFS($AV$34:$AV$825,"<>Abandonado",$AP$34:$AP$825,C27) -> 2 | Q27: 20000 | S27: {=LET( mesTxt,LOWER(TRIM($U27)), meses,{"enero";"febrero";"marzo";"abril";"mayo";"junio";"julio";"agosto";"septiembre";"octubre";"noviembre";"diciembre"}, mesNum,IFERROR(MATCH(mesTxt,meses,0),0), anio,YEAR(DASHBOARD!$AY$2), inicio,DATE(anio,mesNum,1), fin,EOMONTH(inicio,0), disciplina,LOWER(TRIM($C27)), instructor,LOWER(TRIM($G27)), dniProfesor,TRIM($J27), paga,N($N27), fechas,$C$34:$C$825, tipos,UPPER(TRIM($E$34:$E$825)), categorias,UPPER(TRIM($G$34:$G$825)), conceptos,LOWER(TRIM($I$34:$I$825)), contrapartes,TRIM($N$34:$N$825), montos,$P$34:$P$825, estados,UPPER(TRIM($Y$34:$Y$825)), relacionado, ( IFERROR(ISNUMBER(SEARCH(disciplina,conceptos)),FALSE) * IFERROR(ISNUMBER(SEARCH(instructor,conceptos)),FALSE) ) + IF(dniProfesor="",FALSE,contrapartes=dniProfesor), ingresosCuotas,IF( mesNum=0, 0, SUMPRODUCT( --(fechas>=inicio), --(fechas<=fin), --(tipos="INGRESOS"), --(estados="COMPLETADO"), --ISNUMBER(MATCH(categorias,{"CUOTA";"INSCRIPCIÓN";"INSCRIPCION"},0)), --(relacionado>0), montos ) ), ingresosComision,IF( mesNum=0, 0, SUMPRODUCT( --(fechas>=inicio), --(fechas<=fin), --(tipos="INGRESOS"), --(estados="COMPLETADO"), --ISNUMBER(MATCH(categorias,{"COMISIÓN";"COMISION"},0)), --(relacionado>0), montos ) ), egresosComision,IF( mesNum=0, 0, SUMPRODUCT( --(fechas>=inicio), --(fechas<=fin), --(tipos="EGRESOS"), --(estados="COMPLETADO"), --ISNUMBER(MATCH(categorias,{"COMISIÓN";"COMISION"},0)), --(relacionado>0), montos ) ), IF(mesNum=0,"",ingresosCuotas+ingresosComision-egresosComision-paga) )} -> -45000 | U27: Julio | X27: Julio | Z27: =SUMIFS($P$34:$P$825,$C$34:$C$825,">="&DATE(2026,7,1),$C$34:$C$825,"<"&DATE(2026,8,1),$E$34:$E$825,"INGRESOS",$Y$34:$Y$825,"COMPLETADO") -> 660000 | AB27: Agosto | AD27: =SUMIFS($P$34:$P$825,$C$34:$C$825,">="&DATE(2026,8,1),$C$34:$C$825,"<"&DATE(2026,9,1),$E$34:$E$825,"INGRESOS",$Y$34:$Y$825,"COMPLETADO") -> 0 | AF27: Julio | AH27: =-SUMIFS($P$34:$P$825,$C$34:$C$825,">="&DATE(2026,7,1),$C$34:$C$825,"<"&DATE(2026,8,1),$E$34:$E$825,"EGRESOS",$Y$34:$Y$825,"COMPLETADO") -> 0 | AJ27: Agosto | AL27: =-SUMIFS($P$34:$P$825,$C$34:$C$825,">="&DATE(2026,8,1),$C$34:$C$825,"<"&DATE(2026,9,1),$E$34:$E$825,"EGRESOS",$Y$34:$Y$825,"COMPLETADO") -> 0 | AN27: Julio | AP27: =Z27+AH27 -> 660000 | AR27: Agosto | AT27: =AD27+AL27 -> 0
B28: EC | C28: Jiu Jitsu | G28: Andres Rodriguez | J28: 31.911.595 | L28: =COUNTIFS($AG$3:$AR$20,$C28) -> 6 | N28: =VLOOKUP($L28,System!$P$4:$R$16,2,FALSE) -> 150000 | P28: =COUNTIFS($AV$34:$AV$825,"<>Abandonado",$AP$34:$AP$825,C28) -> 10 | Q28: 30000 | S28: {=LET( mesTxt,LOWER(TRIM($U28)), meses,{"enero";"febrero";"marzo";"abril";"mayo";"junio";"julio";"agosto";"septiembre";"octubre";"noviembre";"diciembre"}, mesNum,IFERROR(MATCH(mesTxt,meses,0),0), anio,YEAR(DASHBOARD!$AY$2), inicio,DATE(anio,mesNum,1), fin,EOMONTH(inicio,0), disciplina,LOWER(TRIM($C28)), instructor,LOWER(TRIM($G28)), dniProfesor,TRIM($J28), paga,N($N28), fechas,$C$34:$C$825, tipos,UPPER(TRIM($E$34:$E$825)), categorias,UPPER(TRIM($G$34:$G$825)), conceptos,LOWER(TRIM($I$34:$I$825)), contrapartes,TRIM($N$34:$N$825), montos,$P$34:$P$825, estados,UPPER(TRIM($Y$34:$Y$825)), relacionado, ( IFERROR(ISNUMBER(SEARCH(disciplina,conceptos)),FALSE) * IFERROR(ISNUMBER(SEARCH(instructor,conceptos)),FALSE) ) + IF(dniProfesor="",FALSE,contrapartes=dniProfesor), ingresosCuotas,IF( mesNum=0, 0, SUMPRODUCT( --(fechas>=inicio), --(fechas<=fin), --(tipos="INGRESOS"), --(estados="COMPLETADO"), --ISNUMBER(MATCH(categorias,{"CUOTA";"INSCRIPCIÓN";"INSCRIPCION"},0)), --(relacionado>0), montos ) ), ingresosComision,IF( mesNum=0, 0, SUMPRODUCT( --(fechas>=inicio), --(fechas<=fin), --(tipos="INGRESOS"), --(estados="COMPLETADO"), --ISNUMBER(MATCH(categorias,{"COMISIÓN";"COMISION"},0)), --(relacionado>0), montos ) ), egresosComision,IF( mesNum=0, 0, SUMPRODUCT( --(fechas>=inicio), --(fechas<=fin), --(tipos="EGRESOS"), --(estados="COMPLETADO"), --ISNUMBER(MATCH(categorias,{"COMISIÓN";"COMISION"},0)), --(relacionado>0), montos ) ), IF(mesNum=0,"",ingresosCuotas+ingresosComision-egresosComision-paga) )} -> 0 | U28: Julio | X28: Septiembre | Z28: =SUMIFS($P$34:$P$825,$C$34:$C$825,">="&DATE(2026,9,1),$C$34:$C$825,"<"&DATE(2026,10,1),$E$34:$E$825,"INGRESOS",$Y$34:$Y$825,"COMPLETADO") -> 0 | AB28: Octubre | AD28: =SUMIFS($P$34:$P$825,$C$34:$C$825,">="&DATE(2026,10,1),$C$34:$C$825,"<"&DATE(2026,11,1),$E$34:$E$825,"INGRESOS",$Y$34:$Y$825,"COMPLETADO") -> 0 | AF28: Septiembre | AH28: =SUMIFS($P$34:$P$825,$C$34:$C$825,">="&DATE(2026,9,1),$C$34:$C$825,"<"&DATE(2026,10,1),$E$34:$E$825,"EGRESOS",$Y$34:$Y$825,"COMPLETADO") -> 0 | AJ28: Octubre | AL28: =-SUMIFS($P$34:$P$825,$C$34:$C$825,">="&DATE(2026,10,1),$C$34:$C$825,"<"&DATE(2026,11,1),$E$34:$E$825,"EGRESOS",$Y$34:$Y$825,"COMPLETADO") -> 0 | AN28: Septiembre | AP28: =Z28+AH28 -> 0 | AR28: Octubre | AT28: =AD28+AL28 -> 0 | AW28: BALANCE
B29: S | C29: Jiu Jitsu KIDS | G29: Andres Rodriguez | J29: 31.911.595 | L29: =COUNTIFS($AG$3:$AR$20,$C29) -> 2 | N29: =VLOOKUP($L29,System!$P$4:$R$16,2,FALSE) -> 85000 | P29: =COUNTIFS($AV$34:$AV$825,"<>Abandonado",$AP$34:$AP$825,C29) -> 0 | Q29: 25000 | S29: {=LET( mesTxt,LOWER(TRIM($U29)), meses,{"enero";"febrero";"marzo";"abril";"mayo";"junio";"julio";"agosto";"septiembre";"octubre";"noviembre";"diciembre"}, mesNum,IFERROR(MATCH(mesTxt,meses,0),0), anio,YEAR(DASHBOARD!$AY$2), inicio,DATE(anio,mesNum,1), fin,EOMONTH(inicio,0), disciplina,LOWER(TRIM($C29)), instructor,LOWER(TRIM($G29)), paga,N($N29), fechas,$C$34:$C$825, tipos,UPPER(TRIM($E$34:$E$825)), categorias,UPPER(TRIM($G$34:$G$825)), conceptos,LOWER(TRIM($I$34:$I$825)), montos,$P$34:$P$825, estados,UPPER(TRIM($Y$34:$Y$825)), ingresos,IF( mesNum=0, 0, SUMPRODUCT( --(fechas>=inicio), --(fechas<=fin), --(tipos="INGRESOS"), --(estados="COMPLETADO"), --ISNUMBER(MATCH(categorias,{"CUOTA";"INSCRIPCIÓN";"INSCRIPCION"},0)), --IFERROR(ISNUMBER(SEARCH(disciplina,conceptos)),FALSE), --IFERROR(ISNUMBER(SEARCH(instructor,conceptos)),FALSE), montos ) ), IF(mesNum=0,"",ingresos-paga) )} -> -85000 | U29: Julio | X29: Noviembre | Z29: =SUMIFS($P$34:$P$825,$C$34:$C$825,">="&DATE(2026,11,1),$C$34:$C$825,"<"&DATE(2026,12,1),$E$34:$E$825,"INGRESOS",$Y$34:$Y$825,"COMPLETADO") -> 0 | AB29: Diciembre | AD29: =SUMIFS($P$34:$P$825,$C$34:$C$825,">="&DATE(2026,12,1),$C$34:$C$825,"<"&DATE(2027,1,1),$E$34:$E$825,"INGRESOS",$Y$34:$Y$825,"COMPLETADO") -> 0 | AF29: Noviembre | AH29: =-SUMIFS($P$34:$P$825,$C$34:$C$825,">="&DATE(2026,11,1),$C$34:$C$825,"<"&DATE(2026,12,1),$E$34:$E$825,"EGRESOS",$Y$34:$Y$825,"COMPLETADO") -> 0 | AJ29: Diciembre | AL29: =-SUMIFS($P$34:$P$825,$C$34:$C$825,">="&DATE(2026,12,1),$C$34:$C$825,"<"&DATE(2027,1,1),$E$34:$E$825,"EGRESOS",$Y$34:$Y$825,"COMPLETADO") -> 0 | AN29: Noviembre | AP29: =Z29+AH29 -> 0 | AR29: Diciembre | AT29: =AD29+AL29 -> 0 | AW29: =AW26-AZ26-X3 -> 1977500
C30: -- | G30: . | J30: . | L30: =COUNTIFS($AG$3:$AR$20,$C30) -> 0 | N30: =VLOOKUP($L30,System!$P$4:$R$16,2,FALSE) -> 0 | P30: =COUNTIFS($AV$34:$AV$825,"<>Abandonado",$AP$34:$AP$825,C30) -> 0 | Q30: . | S30: {=LET( mesTxt,LOWER(TRIM($U30)), meses,{"enero";"febrero";"marzo";"abril";"mayo";"junio";"julio";"agosto";"septiembre";"octubre";"noviembre";"diciembre"}, mesNum,IFERROR(MATCH(mesTxt,meses,0),0), anio,YEAR(DASHBOARD!$AY$2), inicio,DATE(anio,mesNum,1), fin,EOMONTH(inicio,0), disciplina,LOWER(TRIM($C30)), instructor,LOWER(TRIM($G30)), paga,N($N30), fechas,$C$34:$C$825, tipos,UPPER(TRIM($E$34:$E$825)), categorias,UPPER(TRIM($G$34:$G$825)), conceptos,LOWER(TRIM($I$34:$I$825)), montos,$P$34:$P$825, estados,UPPER(TRIM($Y$34:$Y$825)), ingresos,IF( mesNum=0, 0, SUMPRODUCT( --(fechas>=inicio), --(fechas<=fin), --(tipos="INGRESOS"), --(estados="COMPLETADO"), --ISNUMBER(MATCH(categorias,{"CUOTA";"INSCRIPCIÓN";"INSCRIPCION"},0)), --IFERROR(ISNUMBER(SEARCH(disciplina,conceptos)),FALSE), --IFERROR(ISNUMBER(SEARCH(instructor,conceptos)),FALSE), montos ) ), IF(mesNum=0,"",ingresos-paga) )} | X30: TOTAL | AB30: =SUM(Z24:AA29,AD24:AE29) -> 2527500 | AF30: TOTAL | AJ30: =SUM(AH24:AI29,AL24:AM29) -> -1227050 | AN30: TOTAL | AR30: =SUM(AP24:AQ29,AT24:AU29) -> 1300450
P31: =SUM(P18:P30) -> 48
B32: MOVIMIENTOS | AB32: INSCRIPTOS
B33: Id. | C33: Fecha | E33: Tipo | G33: Categoría | I33: Concepto | N33: Contra-parte | P33: Monto | R33: Impuestos | T33: M.P. | V33: Estado Finan. | Y33: Estado | AB33: Id. | AD33: Fecha | AF33: Nombre | AI33: Apellido | AL33: D.N.I. | AN33: Tel. | AP33: Actividad | AR33: Modalidad | AT33: Cuota | AV33: Estado | AY33: Instructor | BB33: Vence
B34: I-1020 | C34: 46224.925 | E34: INGRESOS | G34: CUOTA | I34: Pago de cuota [K-0075] de Ginna Caruso por clases de Kickboxing al profesor Natalia Ortiz | N34: 37.704.699 | P34: 20000 | R34: 0 | T34: Efectivo | V34: PAGADO | Y34: COMPLETADO | AB34: K-0075 | AD34: 46224.925 | AF34: Ginna | AI34: Caruso | AL34: 37.704.699 | AN34: 3765234403 | AP34: Kickboxing | AR34: Completo | AT34: 20000 | AV34: Nuevo inscripto | AY34: Natalia Ortiz | BB34: 46255
B35: I-1013 | C35: 46223.7 | E35: INGRESOS | G35: CUOTA | I35: Pago de cuota [K-0064] de Javier Agustin Caceres Velazquez por clases de Karate al profesor Sergio Tabossi | N35: 54.376.352 | P35: 20000 | R35: 0 | T35: Efectivo | V35: PAGADO | Y35: COMPLETADO | AB35: T-0074 | AD35: 46219.761 | AF35: Abril | AI35: Ferreira | AL35: 54.714.692 | AN35: 3765523822 | AP35: Taekwon-do | AR35: Completo | AT35: 20000 | AV35: Nuevo inscripto | AY35: Luzmila Cinquetti | BB35: SIN PAGOS
B36: I-0991 | C36: 46219.785 | E36: INGRESOS | G36: CUOTA | I36: Pago de cuota [T-0047] de Isaias Silva por clases de Taekwon-do al profesor Luzmila Cinquetti | N36: 58.036.520 | P36: 20000 | R36: 0 | T36: Transferencia | V36: PAGADO | Y36: COMPLETADO | AB36: J-0073 | AD36: 46217.663 | AF36: Horacio | AI36: Marquez | AL36: 30.561.519 | AN36: 3764285836 | AP36: Jiu Jitsu | AR36: Completo | AT36: 30000 | AV36: Al día | AY36: Andres Rodriguez | BB36: 46248
B37: I-0973 | C37: 46217.755 | E37: INGRESOS | G37: CUOTA | I37: Pago de cuota [T-0062] de Fernanda De Brito por clases de Taekwon-do al profesor Luzmila Cinquetti | N37: 22.222.222 | P37: 20000 | R37: 0 | T37: Efectivo | V37: PAGADO | Y37: COMPLETADO | AB37: S-0072 | AD37: 46210.861 | AF37: Juana | AI37: Cubilla | AL37: 44.444.444 | AN37: 3765529519 | AP37: Samba Brasilera | AR37: Completo | AT37: 20000 | AV37: Adeudando | AY37: Oriana Cubilla | BB37: SIN PAGOS
B38: I-0970 | C38: 46217.664 | E38: INGRESOS | G38: CUOTA | I38: Pago de cuota [J-0073] de Horacio Marquez por clases de Jiu Jitsu al profesor Andres Rodriguez | N38: 30.561.519 | P38: 30000 | R38: 0 | T38: Transferencia | V38: PAGADO | Y38: COMPLETADO | AB38: S-0071 | AD38: 46210.859 | AF38: Alma | AI38: Cubilla | AL38: 33.333.333 | AN38: 3765529519 | AP38: Samba Brasilera | AR38: Completo | AT38: 20000 | AV38: Adeudando | AY38: Oriana Cubilla | BB38: SIN PAGOS
B39: I-0964 | C39: 46216.888 | E39: INGRESOS | G39: CUOTA | I39: Pago de cuota [T-0048] de Maia Jorgelina Maciel por clases de Taekwon-do al profesor Luzmila Cinquetti | N39: 56.407.427 | P39: 20000 | R39: 0 | T39: Transferencia | V39: PAGADO | Y39: COMPLETADO | AB39: S-0070 | AD39: 46210.858 | AF39: Gianella | AI39: Barrios | AL39: 46.551.235 | AN39: 3765126887 | AP39: Samba Brasilera | AR39: Completo | AT39: 20000 | AV39: Adeudando | AY39: Oriana Cubilla | BB39: SIN PAGOS
B40: I-0962 | C40: 46216.881 | E40: INGRESOS | G40: CUOTA | I40: Pago de cuota [J-0030] de Lisandro Kinigsberg por clases de Jiu Jitsu al profesor Andres Rodriguez | N40: 24.509.315 | P40: 30000 | R40: 0 | T40: Transferencia | V40: PAGADO | Y40: COMPLETADO | AB40: S-0069 | AD40: 46210.85 | AF40: Mia | AI40: Ayala | AL40: 57.828.818 | AN40: 3765025183 | AP40: Samba Brasilera | AR40: Completo | AT40: 20000 | AV40: Adeudando | AY40: Oriana Cubilla | BB40: SIN PAGOS
B41: I-0961 | C41: 46216.869 | E41: INGRESOS | G41: CUOTA | I41: Pago de cuota [J-0014] de Hernan Leon por clases de Jiu Jitsu al profesor Andres Rodriguez | N41: 37.157.910 | P41: 30000 | R41: 0 | T41: Transferencia | V41: PAGADO | Y41: COMPLETADO | AB41: K-0068 | AD41: 46204.683 | AF41: Isaias Omar | AI41: Flores | AL41: 46.168.324 | AN41: 3764386436 | AP41: Kickboxing | AR41: Completo | AT41: 20000 | AV41: Al día | AY41: Natalia Ortiz | BB41: 46235
B42: I-0958 | C42: 46216.701 | E42: INGRESOS | G42: CUOTA | I42: Pago de cuota [K-0041] de Yamila Sanches por clases de Karate al profesor Sergio Tabossi | N42: 52.309.166 | P42: 20000 | R42: 0 | T42: Efectivo | V42: PAGADO | Y42: COMPLETADO | AB42: T-0067 | AD42: 46196.759 | AF42: Emir | AI42: Rodriguez | AL42: 56.371.497 | AN42: 3764138449 | AP42: Taekwon-do | AR42: Completo | AT42: 20000 | AV42: Al día | AY42: Luzmila Cinquetti | BB42: 46227
B43: I-0957 | C43: 46216.699 | E43: INGRESOS | G43: CUOTA | I43: Pago de cuota [K-0040] de Maytena Riquelme por clases de Karate al profesor Sergio Tabossi | N43: 57.147.388 | P43: 20000 | R43: 0 | T43: Efectivo | V43: PAGADO | Y43: COMPLETADO | AB43: T-0066 | AD43: 46196.757 | AF43: Luana Anahi | AI43: Rios | AL43: 53.538.984 | AN43: 3764657340 | AP43: Taekwon-do | AR43: Completo | AT43: 20000 | AV43: Al día | AY43: Luzmila Cinquetti | BB43: 46227
B44: I-0951 | C44: 46216.447 | E44: INGRESOS | G44: CUOTA | I44: Pago de cuota [Y-0021] de Alba Gomes por clases de Yoga al profesor Estefanía Solis | N44: 13.197.015 | P44: 30000 | R44: 0 | T44: Efectivo | V44: PAGADO | Y44: COMPLETADO | AB44: T-0065 | AD44: 46191.758 | AF44: Nicole | AI44: Frigola | AL44: 53.862.148 | AN44: 3765030985 | AP44: Taekwon-do | AR44: Completo | AT44: 20000 | AV44: Adeudando | AY44: Luzmila Cinquetti | BB44: 46222
B45: I-0943 | C45: 46213.868 | E45: INGRESOS | G45: CUOTA | I45: Pago de cuota [J-0016] de Edgardo Ayala por clases de Jiu Jitsu al profesor Andres Rodriguez | N45: 29.318.353 | P45: 30000 | R45: 0 | T45: Efectivo | V45: PAGADO | Y45: COMPLETADO | AB45: K-0064 | AD45: 46183.705 | AF45: Javier Agustin | AI45: Caceres Velazquez | AL45: 54.376.352 | AN45: 3764909371 | AP45: Karate | AR45: Completo | AT45: 20000 | AV45: Al día | AY45: Sergio Tabossi | BB45: 46254
B46: I-0931 | C46: 46213.707 | E46: INGRESOS | G46: CUOTA | I46: Pago de cuota [K-0033] de Sara Santander por clases de Karate al profesor Sergio Tabossi | N46: 57.051.294 | P46: 20000 | R46: 0 | T46: Transferencia | V46: PAGADO | Y46: COMPLETADO | AB46: J-0063 | AD46: 46182.8 | AF46: Gaspar André | AI46: Silva | AL46: 55.617.062 | AN46: 3764551734 | AP46: Jiu Jitsu | AR46: Completo | AT46: 30000 | AV46: Adeudando | AY46: Andres Rodriguez | BB46: 46213
B47: I-0926 | C47: 46212.676 | E47: INGRESOS | G47: CUOTA | I47: Pago de cuota [Y-0020] de Rosa Kal por clases de Yoga al profesor Estefanía Solis | N47: 12.118.208 | P47: 30000 | R47: 0 | T47: Transferencia | V47: PAGADO | Y47: COMPLETADO | AB47: T-0062 | AD47: 46182.773 | AF47: Fernanda | AI47: De Brito | AL47: 22.222.222 | AN47: 3743481389 | AP47: Taekwon-do | AR47: Completo | AT47: 20000 | AV47: Al día | AY47: Luzmila Cinquetti | BB47: 46248
B48: I-0920 | C48: 46211.934 | E48: INGRESOS | G48: CUOTA | I48: Pago de cuota [J-0034] de Lucas Nicolas Dudych por clases de Jiu Jitsu al profesor Andres Rodriguez | N48: 49.027.532 | P48: 30000 | R48: 0 | T48: Transferencia | V48: PAGADO | Y48: COMPLETADO | AB48: T-0061 | AD48: 46182.77 | AF48: Ruben Alexander | AI48: Lencina | AL48: 11.111.111 | AN48: 3764173383 | AP48: Taekwon-do | AR48: Completo | AT48: 20000 | AV48: Al día | AY48: Luzmila Cinquetti | BB48: 46227
B49: I-0918 | C49: 46211.76 | E49: INGRESOS | G49: CUOTA | I49: Pago de cuota [K-0043] de Elliot Gabriel Baena por clases de Karate al profesor Sergio Tabossi | N49: 58.604.283 | P49: 20000 | R49: 0 | T49: Transferencia | V49: PAGADO | Y49: COMPLETADO | AB49: T-0060 | AD49: 46182.752 | AF49: Bautista | AI49: Bonblan | AL49: 54.947.690 | AN49: 3764678856 | AP49: Taekwon-do | AR49: Completo | AT49: 20000 | AV49: Al día | AY49: Luzmila Cinquetti | BB49: 46227
B50: I-0917 | C50: 46211.758 | E50: INGRESOS | G50: CUOTA | I50: Pago de cuota [K-0044] de Federica Agustina Baena por clases de Karate al profesor Sergio Tabossi | N50: 54.075.781 | P50: 20000 | R50: 0 | T50: Transferencia | V50: PAGADO | Y50: COMPLETADO | AB50: J-0059 | AD50: 46182.73 | AF50: Natalia | AI50: Villaverde | AL50: 34.802.440 | AN50: 3764186066 | AP50: Jiu Jitsu | AR50: Completo | AT50: 30000 | AV50: Adeudando | AY50: Andres Rodriguez | BB50: 46213
B51: I-0912 | C51: 46211.751 | E51: INGRESOS | G51: CUOTA | I51: Pago de cuota [K-0049] de Chloe Valentina Romero por clases de Karate al profesor Sergio Tabossi | N51: 57.851.293 | P51: 20000 | R51: 0 | T51: Efectivo | V51: PAGADO | Y51: COMPLETADO | AB51: Y-0058 | AD51: 46182.437 | AF51: María Beatriz | AI51: Castro | AL51: 12.372.687 | AN51: 3764969799 | AP51: Yoga | AR51: Completo | AT51: 30000 | AV51: Al día | AY51: Estefanía Solis | BB51: 46241
B52: I-0907 | C52: 46210.457 | E52: INGRESOS | G52: CUOTA | I52: Pago de cuota [Y-0058] de María Beatriz Castro por clases de Yoga al profesor Estefanía Solis | N52: 12.372.687 | P52: 30000 | R52: 0 | T52: Efectivo | V52: PAGADO | Y52: COMPLETADO | AB52: J-0057 | AD52: 46181.58 | AF52: Pablo Alejandro | AI52: Silva | AL52: 29.218.595 | AN52: 3764551734 | AP52: Jiu Jitsu | AR52: Completo | AT52: 30000 | AV52: Adeudando | AY52: Andres Rodriguez | BB52: 46212
... B55: I-0878 | C55: 46209.706 | E55: INGRESOS | G55: CUOTA | I55: Pago de cuota [K-0009] de Liam Castro por clases de Karate al profesor Sergio Tabossi | N55: 58.603.142 | P55: 20000 | R55: 0 | T55: Transferencia | V55: PAGADO | Y55: COMPLETADO | AB55: J-0054 | AD55: 46176.903 | AF55: Diamela | AI55: Tavares | AL55: 54.714.612 | AN55: 3764354362 | AP55: Jiu Jitsu | AR55: Completo | AT55: 30000 | AV55: Adeudando | AY55: Andres Rodriguez | BB55: 46216
B56: I-0869 | C56: 46208.91 | E56: INGRESOS | G56: ALQUILER | I56: Alquiler Salon - Evento - Muay Thai | N56: 32.261.469 | P56: 20000 | R56: 0 | T56: Efectivo | V56: PAGADO | Y56: COMPLETADO | AB56: K-0053 | AD56: 46176.754 | AF56: Diamela | AI56: Tavares | AL56: 54.714.612 | AN56: 3764354362 | AP56: Karate | AR56: Completo | AT56: 20000 | AV56: Abandonado | AY56: Sergio Tabossi | BB56: SIN PAGOS
B57: I-0868 | C57: 46208.909 | E57: INGRESOS | G57: ALQUILER | I57: Alquiler Salon - Evento - Muay Thai | N57: 32.261.469 | P57: 50000 | R57: 0 | T57: Transferencia | V57: PAGADO | Y57: COMPLETADO | AB57: K-0052 | AD57: 46176.753 | AF57: David | AI57: Gavilan | AL57: 49.994.729 | AN57: 3764617931 | AP57: Kickboxing | AR57: Completo | AT57: 20000 | AV57: Abandonado | AY57: Natalia Ortiz | BB57: SIN PAGOS
B58: I-0865 | C58: 46206.766 | E58: INGRESOS | G58: CUOTA | I58: Pago de cuota [K-0039] de Carina Zarate por clases de Karate al profesor Sergio Tabossi | N58: 29.854.898 | P58: 20000 | R58: 0 | T58: Efectivo | V58: PAGADO | Y58: COMPLETADO | AB58: K-0051 | AD58: 46176.714 | AF58: Kiara | AI58: Godoy | AL58: 58.189.502 | AN58: 3764671121 | AP58: Karate | AR58: Completo | AT58: 20000 | AV58: Adeudando | AY58: Sergio Tabossi | BB58: SIN PAGOS
B59: I-0863 | C59: 46206.762 | E59: INGRESOS | G59: CUOTA | I59: Pago de cuota [K-0007] de Emanuel Vivar por clases de Karate al profesor Sergio Tabossi | N59: 58.920.455 | P59: 20000 | R59: 0 | T59: Efectivo | V59: PAGADO | Y59: COMPLETADO | AB59: K-0050 | AD59: 46176.713 | AF59: Jana Belen | AI59: Godoy | AL59: 57.146.521 | AN59: 3764671121 | AP59: Karate | AR59: Completo | AT59: 20000 | AV59: Adeudando | AY59: Sergio Tabossi | BB59: SIN PAGOS
B60: E-0853 | C60: 46202 | E60: EGRESOS | G60: COMISIÓN | I60: PAGO POR USO - Junio - Clases de Yoga - Estefanía Solis | N60: 28.553.991 | P60: 5000 | R60: 0 | T60: Efectivo | V60: PAGADO | Y60: COMPLETADO | AB60: K-0049 | AD60: 46176.706 | AF60: Chloe Valentina | AI60: Romero | AL60: 57.851.293 | AN60: 3765007745 | AP60: Karate | AR60: Completo | AT60: 20000 | AV60: Al día | AY60: Sergio Tabossi | BB60: 46242
B61: I-0852 | C61: 46202 | E61: INGRESOS | G61: COMISIÓN | I61: PAGO POR USO - Junio - Clases de Zumba - Alejandra Gonzalez | N61: 29.058.004 | P61: 85000 | R61: 0 | V61: PENDIENTE | Y61: PENDIENTE | AB61: T-0048 | AD61: 46175.798 | AF61: Maia Jorgelina | AI61: Maciel | AL61: 56.407.427 | AN61: 3704760015 | AP61: Taekwon-do | AR61: Completo | AT61: 20000 | AV61: Al día | AY61: Luzmila Cinquetti | BB61: 46247
B62: E-0851 | C62: 46202 | E62: EGRESOS | G62: COMISIÓN | I62: PAGO POR USO - Junio - Clases de Karate - Sergio Tabossi | N62: 27.574.895 | P62: 130000 | R62: 0 | T62: Transferencia | V62: PAGADO | Y62: COMPLETADO | AB62: T-0047 | AD62: 46175.797 | AF62: Isaias | AI62: Silva | AL62: 58.036.520 | AN62: 3764354362 | AP62: Taekwon-do | AR62: Completo | AT62: 20000 | AV62: Al día | AY62: Luzmila Cinquetti | BB62: 46250
B63: E-0850 | C63: 46202 | E63: EGRESOS | G63: COMISIÓN | I63: PAGO POR USO - Junio - Clases de Taekwon-do - Luzmila Cinquetti | N63: 48.651.728 | P63: 190000 | R63: 0 | T63: Transferencia | V63: PAGADO | Y63: COMPLETADO | AB63: T-0046 | AD63: 46175.796 | AF63: Miqueas | AI63: Silva | AL63: 59.052.039 | AN63: 3765238807 | AP63: Taekwon-do | AR63: Completo | AT63: 20000 | AV63: Abandonado | AY63: Luzmila Cinquetti | BB63: 46222
B64: I-0849 | C64: 46202 | E64: INGRESOS | G64: COMISIÓN | I64: PAGO POR USO - Junio - Clases de Kickboxing - Natalia Ortiz | N64: 32.261.469 | P64: 85000 | R64: 0 | V64: PENDIENTE | Y64: PENDIENTE | AB64: T-0045 | AD64: 46170.983 | AF64: Thomas | AI64: Figueredo | AL64: 57.280.872 | AN64: 3764759993 | AP64: Taekwon-do | AR64: Completo | AT64: 20000 | AV64: Adeudando | AY64: Luzmila Cinquetti | BB64: 46206
B65: I-0825 | C65: 46204.684 | E65: INGRESOS | G65: CUOTA | I65: Pago de cuota [K-0068] de Isaias Omar Flores por clases de Kickboxing al profesor Natalia Ortiz | N65: 46.168.324 | P65: 20000 | R65: 0 | T65: Efectivo | V65: PAGADO | Y65: COMPLETADO | AB65: K-0044 | AD65: 46170.722 | AF65: Federica Agustina | AI65: Baena | AL65: 54.075.781 | AN65: 3764217643 | AP65: Karate | AR65: Completo | AT65: 20000 | AV65: Al día | AY65: Sergio Tabossi | BB65: 46242
B66: E-0803 | C66: 46199.552 | E66: EGRESOS | G66: COMISIÓN | I66: PAGO POR USO - Junio - Clases de Taekwon-do - Luzmila Cinquetti | N66: 48.651.728 | P66: 25000 | R66: 0 | T66: Transferencia | V66: PAGADO | Y66: COMPLETADO | AB66: K-0043 | AD66: 46170.721 | AF66: Elliot Gabriel | AI66: Baena | AL66: 58.604.283 | AN66: 3764217643 | AP66: Karate | AR66: Completo | AT66: 20000 | AV66: Al día | AY66: Sergio Tabossi | BB66: 46242
B67: E-0801 | C67: 46199.548 | E67: EGRESOS | G67: COMISIÓN | I67: PAGO POR USO - Junio - Clases de Jiu Jitsu - Andres Rodriguez | N67: 31.911.595 | P67: 30000 | R67: 0 | T67: Transferencia | V67: PAGADO | Y67: COMPLETADO | AB67: K-0042 | AD67: 46169.986 | AF67: Briana | AI67: Sanches | AL67: 00.000.000 | AN67: 3765170404 | AP67: Karate | AR67: Completo | AT67: 20000 | AV67: Adeudando | AY67: Sergio Tabossi | BB67: 46214
B68: I-0784 | C68: 46196.792 | E68: INGRESOS | G68: CUOTA | I68: Pago de cuota [T-0056] de Pilar Vivero Damus por clases de Taekwon-do al profesor Luzmila Cinquetti | N68: 56.821.230 | P68: 20000 | R68: 0 | T68: Efectivo | V68: PAGADO | Y68: COMPLETADO | AB68: K-0041 | AD68: 46169.986 | AF68: Yamila | AI68: Sanches | AL68: 52.309.166 | AN68: 3765170404 | AP68: Karate | AR68: Completo | AT68: 20000 | AV68: Al día | AY68: Sergio Tabossi | BB68: 46247
B69: I-0783 | C69: 46196.76 | E69: INGRESOS | G69: CUOTA | I69: Pago de cuota [T-0067] de Emir Rodriguez por clases de Taekwon-do al profesor Luzmila Cinquetti | N69: 56.371.497 | P69: 20000 | R69: 0 | T69: Efectivo | V69: PAGADO | Y69: COMPLETADO | AB69: K-0040 | AD69: 46169.985 | AF69: Maytena | AI69: Riquelme | AL69: 57.147.388 | AN69: 3765170404 | AP69: Karate | AR69: Completo | AT69: 20000 | AV69: Al día | AY69: Sergio Tabossi | BB69: 46247
B70: I-0782 | C70: 46196.758 | E70: INGRESOS | G70: CUOTA | I70: Pago de cuota [T-0066] de Luana Anahi Rios por clases de Taekwon-do al profesor Luzmila Cinquetti | N70: 53.538.984 | P70: 20000 | R70: 0 | T70: Efectivo | V70: PAGADO | Y70: COMPLETADO | AB70: K-0039 | AD70: 46169.981 | AF70: Carina | AI70: Zarate | AL70: 29.854.898 | AN70: 3764210489 | AP70: Karate | AR70: Completo | AT70: 20000 | AV70: Al día | AY70: Sergio Tabossi | BB70: 46237
B71: I-0781 | C71: 46196.756 | E71: INGRESOS | G71: CUOTA | I71: Pago de cuota [T-0060] de Bautista Bonblan por clases de Taekwon-do al profesor Luzmila Cinquetti | N71: 54.947.690 | P71: 20000 | R71: 0 | T71: Efectivo | V71: PAGADO | Y71: COMPLETADO | AB71: T-0038 | AD71: 46168.798 | AF71: Giovana | AI71: Ramos | AL71: 56.734.699 | AN71: 3786402682 | AP71: Taekwon-do | AR71: Completo | AT71: 20000 | AV71: Abandonado | AY71: Luzmila Cinquetti | BB71: 46199
B72: I-0780 | C72: 46196.755 | E72: INGRESOS | G72: CUOTA | I72: Pago de cuota [T-0061] de Ruben Alexander Lencina por clases de Taekwon-do al profesor Luzmila Cinquetti | N72: 11.111.111 | P72: 20000 | R72: 0 | T72: Efectivo | V72: PAGADO | Y72: COMPLETADO | AB72: T-0037 | AD72: 46154.781 | AF72: Gio | AI72: Abrahamsson | AL72: 55.778.470 | AN72: 3757648784 | AP72: Taekwon-do | AR72: Completo | AT72: 20000 | AV72: Abandonado | AY72: Luzmila Cinquetti | BB72: 46185
B73: I-0755 | C73: 46191.759 | E73: INGRESOS | G73: CUOTA | I73: Pago de cuota [T-0065] de Nicole Frigola por clases de Taekwon-do al profesor Luzmila Cinquetti | N73: 53.862.148 | P73: 20000 | R73: 0 | T73: Efectivo | V73: PAGADO | Y73: COMPLETADO | AB73: Z-0036 | AD73: 46154.597 | AF73: Maria Isabel | AI73: Luis | AL73: 24.850.885 | AN73: 3764308954 | AP73: Zumba | AR73: Completo | AT73: 20000 | AV73: Abandonado | AY73: Alejandra Gonzalez | BB73: 46185
B74: I-0753 | C74: 46191.633 | E74: INGRESOS | G74: CUOTA | I74: Pago de cuota [T-0046] de Miqueas Silva por clases de Taekwon-do al profesor Luzmila Cinquetti | N74: 59.052.039 | P74: 20000 | R74: 0 | T74: Transferencia | V74: PAGADO | Y74: COMPLETADO | AB74: Z-0035 | AD74: 46154.593 | AF74: Viviana | AI74: Gimenez | AL74: 24.573.496 | AN74: 3764621001 | AP74: Zumba | AR74: Completo | AT74: 20000 | AV74: Abandonado | AY74: Alejandra Gonzalez | BB74: 46185
B75: I-0736 | C75: 46189.437 | E75: INGRESOS | G75: CUOTA | I75: Pago de cuota [Y-0020] de Rosa Kal por clases de Yoga al profesor Estefanía Solis | N75: 12.118.208 | P75: 30000 | R75: 0 | T75: Efectivo | V75: PAGADO | Y75: COMPLETADO | AB75: J-0034 | AD75: 46153.782 | AF75: Lucas Nicolas | AI75: Dudych | AL75: 49.027.532 | AN75: 3764586111 | AP75: Jiu Jitsu | AR75: Completo | AT75: 30000 | AV75: Al día | AY75: Andres Rodriguez | BB75: 46242
B76: I-0730 | C76: 46185.788 | E76: INGRESOS | G76: CUOTA | I76: Pago de cuota [J-0054] de Diamela Tavares por clases de Jiu Jitsu al profesor Andres Rodriguez | N76: 54.714.612 | P76: 30000 | R76: 0 | T76: Transferencia | V76: PAGADO | Y76: COMPLETADO | AB76: K-0033 | AD76: 46153.744 | AF76: Sara | AI76: Santander | AL76: 57.051.294 | AN76: 3764299998 | AP76: Karate | AR76: Completo | AT76: 20000 | AV76: Al día | AY76: Sergio Tabossi | BB76: 46244
B77: I-0729 | C77: 46185.786 | E77: INGRESOS | G77: CUOTA | I77: Pago de cuota [T-0047] de Isaias Silva por clases de Taekwon-do al profesor Luzmila Cinquetti | N77: 58.036.520 | P77: 20000 | R77: 0 | T77: Transferencia | V77: PAGADO | Y77: COMPLETADO | AB77: J-0032 | AD77: 46148.887 | AF77: Gonzalo | AI77: Silva | AL77: 57.486.458 | AN77: 3765040426 | AP77: Jiu Jitsu | AR77: Completo | AT77: 30000 | AV77: Abandonado | AY77: Andres Rodriguez | BB77: SIN PAGOS
B78: I-0725 | C78: 46185.696 | E78: INGRESOS | G78: CUOTA | I78: Pago de cuota [K-0041] de Yamila Sanches por clases de Karate al profesor Sergio Tabossi | N78: 52.309.166 | P78: 20000 | R78: 0 | T78: Efectivo | V78: PAGADO | Y78: COMPLETADO | AB78: J-0031 | AD78: 46148.882 | AF78: Martin Hernan | AI78: Rivera | AL78: 29.537.617 | AN78: 3764290541 | AP78: Jiu Jitsu | AR78: Completo | AT78: 30000 | AV78: Abandonado | AY78: Andres Rodriguez | BB78: 46179
B79: E-0708 | C79: 46183.736 | E79: EGRESOS | G79: REPARACIONES | I79: Cisterna y flotador para baño | N79: 70.862.918 | P79: 25050 | R79: 0 | T79: Transferencia | V79: PAGADO | Y79: COMPLETADO | AB79: J-0030 | AD79: 46148.849 | AF79: Lisandro | AI79: Kinigsberg | AL79: 24.509.315 | AN79: 3764563173 | AP79: Jiu Jitsu | AR79: Completo | AT79: 30000 | AV79: Al día | AY79: Andres Rodriguez | BB79: 46247
B80: I-0705 | C80: 46183.705 | E80: INGRESOS | G80: CUOTA | I80: Pago de cuota [K-0064] de Javier Agustin Caceres Velazquez por clases de Karate al profesor Sergio Tabossi | N80: 54.375.352 | P80: 20000 | R80: 0 | T80: Efectivo | V80: PAGADO | Y80: COMPLETADO | AB80: K-0029 | AD80: 46148.432 | AF80: Emely | AI80: Navarro | AL80: 47.426.537 | AN80: 3764887660 | AP80: Kickboxing | AR80: Completo | AT80: 15000 | AV80: Abandonado | AY80: Natalia Ortiz | BB80: 46193
B81: I-0704 | C81: 46183.702 | E81: INGRESOS | G81: CUOTA | I81: Pago de cuota [K-0042] de Briana Sanches por clases de Karate al profesor Sergio Tabossi | N81: 00.000.000 | P81: 20000 | R81: 0 | T81: Efectivo | V81: PAGADO | Y81: COMPLETADO | AB81: K-0028 | AD81: 46148.431 | AF81: Mia | AI81: Romero Vergara | AL81: 47.535.551 | AN81: 3765306596 | AP81: Kickboxing | AR81: Completo | AT81: 15000 | AV81: Abandonado | AY81: Natalia Ortiz | BB81: SIN PAGOS
B82: I-0698 | C82: 46183.534 | E82: INGRESOS | G82: CUOTA | I82: Pago de cuota [Y-0021] de Alba Gomes por clases de Yoga al profesor Estefanía Solis | N82: 13.197.015 | P82: 30000 | R82: 0 | T82: Efectivo | V82: PAGADO | Y82: COMPLETADO | AB82: Z-0027 | AD82: 46147.85 | AF82: Sofia | AI82: Fleitas | AL82: 56.679.377 | AN82: 3764761894 | AP82: Zumba | AR82: Completo | AT82: 15000 | AV82: Abandonado | AY82: Alejandra Gonzalez | BB82: 46178
B83: I-0696 | C83: 46182.801 | E83: INGRESOS | G83: CUOTA | I83: Pago de cuota [J-0063] de Gaspar André Silva por clases de Jiu Jitsu al profesor Andres Rodriguez | N83: 55.617.062 | P83: 30000 | R83: 0 | T83: Transferencia | V83: PAGADO | Y83: COMPLETADO | AB83: Z-0026 | AD83: 46147.849 | AF83: Fabiana | AI83: Quiroz | AL83: 34.086.439 | AN83: 3764761894 | AP83: Zumba | AR83: Completo | AT83: 15000 | AV83: Abandonado | AY83: Alejandra Gonzalez | BB83: 46178
B84: E-0695 | C84: 46182.777 | E84: EGRESOS | G84: IMPUESTOS | I84: Habilitación Salón - Pago de bomberos | N84: 67.239.463 | P84: 49000 | R84: 0 | T84: Efectivo | V84: PAGADO | Y84: COMPLETADO | AB84: Z-0025 | AD84: 46147.848 | AF84: Mara | AI84: Acuña | AL84: 49.640.210 | AN84: 3757452622 | AP84: Zumba | AR84: Completo | AT84: 20000 | AV84: Abandonado | AY84: Alejandra Gonzalez | BB84: 46178
B85: I-0694 | C85: 46182.775 | E85: INGRESOS | G85: CUOTA | I85: Pago de cuota [T-0062] de Fernanda De Brito por clases de Taekwon-do al profesor Luzmila Cinquetti | N85: 22.222.222 | P85: 20000 | R85: 0 | T85: Efectivo | V85: PAGADO | Y85: COMPLETADO | AB85: Z-0024 | AD85: 46147.779 | AF85: Alejandra | AI85: Rolon | AL85: 32.608.046 | AN85: 3764252883 | AP85: Zumba | AR85: Completo | AT85: 20000 | AV85: Abandonado | AY85: Alejandra Gonzalez | BB85: 46178
B86: I-0692 | C86: 46182.733 | E86: INGRESOS | G86: CUOTA | I86: Pago de cuota [J-0059] de Natalia Villaverde por clases de Jiu Jitsu al profesor Andres Rodriguez | N86: 34.802.440 | P86: 30000 | R86: 0 | T86: Transferencia | V86: PAGADO | Y86: COMPLETADO | AB86: Z-0023 | AD86: 46147.65 | AF86: Angelica | AI86: Da Luz | AL86: 17.980.046 | AN86: 3764656093 | AP86: Zumba | AR86: Completo | AT86: 15000 | AV86: Abandonado | AY86: Alejandra Gonzalez | BB86: 46178
B87: I-0684 | C87: 46182.438 | E87: INGRESOS | G87: CUOTA | I87: Pago de cuota [Y-0058] de María Beatriz Castro por clases de Yoga al profesor Estefanía Solis | N87: 12.372.687 | P87: 30000 | R87: 0 | T87: Efectivo | V87: PAGADO | Y87: COMPLETADO | AB87: Z-0022 | AD87: 46147.65 | AF87: Claudia | AI87: Luis | AL87: 28.902.325 | AN87: 3764713974 | AP87: Zumba | AR87: Completo | AT87: 15000 | AV87: Abandonado | AY87: Alejandra Gonzalez | BB87: 46178
B88: I-0674 | C88: 46181.616 | E88: INGRESOS | G88: CUOTA | I88: Pago de cuota [J-0057] de Pablo Alejandro Silva por clases de Jiu Jitsu al profesor Andres Rodriguez | N88: 29.218.595 | P88: 30000 | R88: 0 | T88: Transferencia | V88: PAGADO | Y88: COMPLETADO | AB88: Y-0021 | AD88: 46147.493 | AF88: Alba | AI88: Gomes | AL88: 13.197.015 | AN88: 3764660205 | AP88: Yoga | AR88: Completo | AT88: 30000 | AV88: Al día | AY88: Estefanía Solis | BB88: 46247
B89: I-0667 | C89: 46178.883 | E89: INGRESOS | G89: CUOTA | I89: Pago de cuota [J-0013] de Giovani Magri por clases de Jiu Jitsu al profesor Andres Rodriguez | N89: 30.398.294 | P89: 30000 | R89: 0 | T89: Transferencia | V89: PAGADO | Y89: COMPLETADO | AB89: Y-0020 | AD89: 46147.491 | AF89: Rosa | AI89: Kal | AL89: 12.118.208 | AN89: 3764535654 | AP89: Yoga | AR89: Completo | AT89: 30000 | AV89: Al día | AY89: Estefanía Solis | BB89: 46243
B90: I-0660 | C90: 46178.798 | E90: INGRESOS | G90: CUOTA | I90: Pago de cuota [J-0016] de Edgardo Ayala por clases de Jiu Jitsu al profesor Andres Rodriguez | N90: 29.318.353 | P90: 30000 | R90: 0 | T90: Efectivo | V90: PAGADO | Y90: COMPLETADO | AB90: J-0019 | AD90: 46146.894 | AF90: Javier | AI90: Batista | AL90: 38.776.514 | AN90: 3517725490 | AP90: Jiu Jitsu | AR90: Completo | AT90: 30000 | AV90: Abandonado | AY90: Andres Rodriguez | BB90: 46179
B91: I-0659 | C91: 46178.793 | E91: INGRESOS | G91: CUOTA | I91: Pago de cuota [K-0039] de Carina Zarate por clases de Karate al profesor Sergio Tabossi | N91: 29.854.898 | P91: 20000 | R91: 0 | T91: Efectivo | V91: PAGADO | Y91: COMPLETADO | AB91: J-0018 | AD91: 46146.893 | AF91: Mayra | AI91: Azor | AL91: 37.043.909 | AN91: 3765383230 | AP91: Jiu Jitsu | AR91: Completo | AT91: 30000 | AV91: Abandonado | AY91: Andres Rodriguez | BB91: SIN PAGOS
B92: I-0658 | C92: 46178.703 | E92: INGRESOS | G92: CUOTA | I92: Pago de cuota [K-0007] de Emanuel Vivar por clases de Karate al profesor Sergio Tabossi | N92: 58.920.455 | P92: 20000 | R92: 0 | T92: Efectivo | V92: PAGADO | Y92: COMPLETADO | AB92: J-0017 | AD92: 46146.888 | AF92: Juanjo | AI92: Galeano | AL92: 30.381.475 | AN92: 3764839380 | AP92: Jiu Jitsu | AR92: Completo | AT92: 30000 | AV92: Abandonado | AY92: Andres Rodriguez | BB92: 46179
B93: I-0657 | C93: 46177.804 | E93: INGRESOS | G93: CUOTA | I93: Pago de cuota [T-0056] de Pilar Vivero Damus por clases de Taekwon-do al profesor Luzmila Cinquetti | N93: 56.821.230 | P93: 20000 | R93: 0 | T93: Transferencia | V93: PAGADO | Y93: COMPLETADO | AB93: J-0016 | AD93: 46146.886 | AF93: Edgardo | AI93: Ayala | AL93: 29.318.353 | AN93: 3764598609 | AP93: Jiu Jitsu | AR93: Completo | AT93: 30000 | AV93: Al día | AY93: Andres Rodriguez | BB93: 46244
B94: I-0655 | C94: 46177.763 | E94: INGRESOS | G94: CUOTA | I94: Pago de cuota [T-0055] de Benjamin Romero por clases de Taekwon-do al profesor Luzmila Cinquetti | N94: 57.729.635 | P94: 20000 | R94: 0 | T94: Transferencia | V94: PAGADO | Y94: COMPLETADO | AB94: J-0015 | AD94: 46146.884 | AF94: Agustin | AI94: Silva | AL94: 55.129.495 | AN94: 3764246183 | AP94: Jiu Jitsu | AR94: Completo | AT94: 30000 | AV94: Abandonado | AY94: Andres Rodriguez | BB94: SIN PAGOS
B95: I-0654 | C95: 46177.76 | E95: INGRESOS | G95: CUOTA | I95: Pago de cuota [T-0005] de Tiziano Rojas por clases de Taekwon-do al profesor Luzmila Cinquetti | N95: 32.418.265 | P95: 20000 | R95: 0 | T95: Transferencia | V95: PAGADO | Y95: COMPLETADO | AB95: J-0014 | AD95: 46146.883 | AF95: Hernan | AI95: Leon | AL95: 37.157.910 | AN95: 3764864622 | AP95: Jiu Jitsu | AR95: Completo | AT95: 30000 | AV95: Al día | AY95: Andres Rodriguez | BB95: 46247
B96: I-0653 | C96: 46177.747 | E96: INGRESOS | G96: CUOTA | I96: Pago de cuota [T-0048] de Maia Jorgelina Maciel por clases de Taekwon-do al profesor Luzmila Cinquetti | N96: 56.407.427 | P96: 20000 | R96: 0 | T96: Transferencia | V96: PAGADO | Y96: COMPLETADO | AB96: J-0013 | AD96: 46146.819 | AF96: Giovani | AI96: Magri | AL96: 30.398.294 | AN96: 3764147818 | AP96: Jiu Jitsu | AR96: Completo | AT96: 30000 | AV96: Adeudando | AY96: Andres Rodriguez | BB96: 46209
B97: I-0637 | C97: 46176.91 | E97: INGRESOS | G97: CUOTA | I97: Pago de cuota [K-0053] de Diamela Tavares por clases de Karate al profesor Sergio Tabossi | N97: 54.714.612 | P97: 20000 | R97: 0 | T97: Efectivo | V97: CANCELADOS | Y97: ANULADO | AB97: K-0012 | AD97: 46146.463 | AF97: Ivan | AI97: Mercado | AL97: 43.331.519 | AN97: 3764565529 | AP97: Kickboxing | AR97: Completo | AT97: 20000 | AV97: Abandonado | AY97: Natalia Ortiz | BB97: SIN PAGOS
B98: I-0636 | C98: 46176.91 | E98: INGRESOS | G98: CUOTA | I98: Pago de cuota [J-0054] de Diamela Tavares por clases de Jiu Jitsu al profesor Andres Rodriguez | N98: 54.714.612 | P98: 30000 | R98: 0 | T98: Efectivo | V98: CANCELADOS | Y98: ANULADO | AB98: T-0011 | AD98: 46142.771 | AF98: Bruno | AI98: Gomez | AL98: 55.046.047 | AN98: 3764858773 | AP98: Taekwon-do | AR98: Completo | AT98: 20000 | AV98: Adeudando | AY98: Luzmila Cinquetti | BB98: 46206
B99: I-0630 | C99: 46176.752 | E99: INGRESOS | G99: CUOTA | I99: Pago de cuota de Sara Santander por clases de Karate al profesor Sergio Tabossi | N99: 57.051.294 | P99: 20000 | R99: 0 | T99: Transferencia | V99: PAGADO | Y99: COMPLETADO | AB99: I-0010 | AD99: 46140.654 | AF99: Martina | AI99: Fernandez | AL99: 57.148.787 | AN99: 3764827467 | AP99: Iniciación a la Danza | AR99: Completo | AT99: 20000 | AV99: Abandonado | AY99: Fiorela Correa | BB99: SIN PAGOS
B100: I-0626 | C100: 46176.707 | E100: INGRESOS | G100: CUOTA | I100: Pago de cuota de Chloe Valentina Romero por clases de Karate al profesor Sergio Tabossi | N100: 57.851.293 | P100: 20000 | R100: 0 | T100: Efectivo | V100: PAGADO | Y100: COMPLETADO | AB100: K-0009 | AD100: 46132 | AF100: Liam | AI100: Castro | AL100: 58.603.142 | AN100: 3764739616 | AP100: Karate | AR100: Completo | AT100: 20000 | AV100: Al día | AY100: Sergio Tabossi | BB100: 46240
B101: I-0616 | C101: 46175.793 | E101: INGRESOS | G101: CUOTA | I101: Pago de cuota de Bruno Gomez por clases de Taekwon-do al profesor Luzmila Cinquetti | N101: 55.046.047 | P101: 20000 | R101: 0 | T101: Efectivo | V101: PAGADO | Y101: COMPLETADO | AB101: K-0008 | AD101: 46132 | AF101: Abril | AI101: Castro | AL101: 55.539.127 | AN101: 3764739616 | AP101: Karate | AR101: Completo | AT101: 20000 | AV101: Al día | AY101: Sergio Tabossi | BB101: 46240
B102: I-0615 | C102: 46175.783 | E102: INGRESOS | G102: CUOTA | I102: Pago de cuota de Thomas Figueredo por clases de Taekwon-do al profesor Luzmila Cinquetti | N102: 57.280.872 | P102: 20000 | R102: 0 | T102: Transferencia | V102: PAGADO | Y102: COMPLETADO | AB102: K-0007 | AD102: 46132 | AF102: Emanuel | AI102: Vivar | AL102: 58.920.455 | AN102: 3764210489 | AP102: Karate | AR102: Completo | AT102: 20000 | AV102: Al día | AY102: Sergio Tabossi | BB102: 46237
B103: I-0612 | C103: 46175.72 | E103: INGRESOS | G103: CUOTA | I103: Pago de cuota de Federica Agustina Baena por clases de Karate al profesor Sergio Tabossi | N103: 54.075.781 | P103: 20000 | R103: 0 | T103: Efectivo | V103: PAGADO | Y103: COMPLETADO | AB103: I-0006 | AD103: 46128 | AF103: Stephany | AI103: Gomez | AL103: 47.761.422 | AN103: 3764128139 | AP103: Iniciación a la Danza | AR103: Completo | AT103: 20000 | AV103: Abandonado | AY103: Fiorela Correa | BB103: SIN PAGOS
...

Sheet AULA
B2: AULA | F2: ↓ Actividad ↓ | M2: Inicio de Actividad: | P2: 46140 | T2: SALDO TOTAL | X2: SALDO A LIQUIDAR | AB2: LIQUID. 30 DÍAS | AG2: LUNES | AI2: MARTES | AK2: MIÉRC. | AM2: JUEVES | AO2: VIERNES | AQ2: SÁBADO | AT2: EVENTOS
F3: Clases, cursos y talleres | M3: Estado: | T3: 0 | X3: =AB19 -> 116000 | AB3: =SUMIFS($P$34:$P$825,$E$34:$E$825,"EGRESOS",$G$34:$G$825,"COMISIÓN") -> 397000 | AF3: 0.41666667 | AG3: - | AI3: - | AK3: - | AM3: - | AO3: - | AQ3: - | AT3: D.N.I.
AF4: 0.45833333
AF5: 0.45833333 | AG5: - | AI5: - | AK5: - | AM5: - | AO5: - | AQ5: - | AT5: Nombre
B6: Salud: | F6: Estado Municipal: | I6: En proceso | M6: Estado Financiero: | P6: =IF(T3<0,"Adeudando",IF(X3>0,"Saldo a liquidar",IF(AB3=0,"Sin movimientos",IF(X3=0,"Saldado",)))) -> Saldo a liquidar | T6: LIQUIDAR TOTAL | X6: LIQUIDAR: → | AB6: 0 | AF6: 0.5
AF7: 0.58333333 | AG7: - | AI7: - | AK7: - | AM7: - | AO7: - | AQ7: - | AT7: Apellido
B8: CARGAR INSCRIPCIÓN | T8: CARGAR PAGO DE CUOTA | AF8: 0.625
B9: Nombre | E9: Apellido | H9: D.N.I. | J9: Tel. | M9: Actividad | P9: Modalidad | T9: D.N.I. | W9: Nombre | AA9: Apellido | AF9: 0.625 | AG9: - | AI9: Arte - niños | AK9: - | AM9: Arte - niños | AO9: - | AQ9: - | AT9: Modalidad
AF10: 0.66666667
B11: Monto de cuota | E11: Descuento (%) | H11: Promoción (-$) | K11: Instructor | P11: Horario | T11: Actividad | W11: Insctructor | AA11: Monto a pagar | AF11: 0.66666667 | AG11: - | AI11: - | AK11: - | AM11: Taller de Fotografía | AO11: - | AQ11: - | AT11: Turno
B12: =IF(M10="",0,VLOOKUP(M10,C18:R30,15,FALSE)) -> 0 | K12: =IF(M10="","",VLOOKUP(M10,C18:I30,5,FALSE)) | AF12: 0.70833333
B13: * Condición médica o especificación del estado de salud | T13: Estado | W13: M.P. | AA13: -Descuento (%) | AF13: 0.70833333 | AG13: - | AI13: Arte - niños | AK13: - | AM13: Arte - niños | AO13: - | AQ13: - | AT13: Opción
AA14: 0 | AF14: 0.75
AF15: 0.75 | AG15: - | AI15: - | AK15: - | AM15: - | AO15: - | AQ15: - | AT15: Sub-total
AF16: 0.79166667 | AT16: =IF(AND(AT14="BASE",AT10="Reducido"),65000,IF(AND(AT14="BASE",AT10="Completo"),150000,IF(AND(AT14="CATERING",AT10="Reducido"),(65000+AT18),IF(AND(AT14="CATERING",AT10="Completo"),(150000+AT18),IF(AND(AT14="INFANTIL",AT10="Reducido"),220000,IF(AND(AT14="INFANTIL",AT10="Completo"),450000,0)))))) -> 0
B17: Est. | C17: Disciplina | G17: Instructor | J17: D.N.I. | L17: % | N17: Paga | P17: Insc. | Q17: Precio | S17: Saldo a Liq. | U17: Mes | AF17: 0.79166667 | AG17: - | AI17: - | AK17: - | AM17: - | AO17: - | AQ17: - | AT17: Adicionales
B18: EC | C18: Arte - niños | G18: =VLOOKUP(C18,System!$B$17:$H$40,3,FALSE) -> Vanesa Rodriguez | J18: 35.872.158 | L18: 0.4 | N18: {=LET( mesTxt,LOWER(TRIM(INDEX($U18:$V18,1,1))), meses,{"enero";"febrero";"marzo";"abril";"mayo";"junio";"julio";"agosto";"septiembre";"octubre";"noviembre";"diciembre"}, mesNum,IFERROR(MATCH(mesTxt,meses,0),0), anio,YEAR(DASHBOARD!$AY$2), inicio,DATE(anio,mesNum,1), fin,EOMONTH(inicio,0), disciplina,LOWER(TRIM(INDEX($C18:$D18,1,1))), instructor,LOWER(TRIM(INDEX($G18:$I18,1,1))), porcentaje,N(INDEX($L18:$M18,1,1)), fechas,$C$34:$C$820, tipos,UPPER(TRIM($E$34:$E$820)), categorias,UPPER(TRIM($G$34:$G$820)), conceptos,LOWER(TRIM($I$34:$I$820)), montos,$P$34:$P$820, estados,UPPER(TRIM($Y$34:$Y$820)), ingresos,IF( mesNum=0, 0, SUMPRODUCT( --(fechas>=inicio), --(fechas<=fin), --(tipos="INGRESOS"), --(estados="COMPLETADO"), --ISNUMBER(MATCH(categorias,{"CUOTA";"INSCRIPCIÓN";"INSCRIPCION";"CLASES"},0)), --IFERROR(ISNUMBER(SEARCH(disciplina,conceptos)),FALSE), --IFERROR(ISNUMBER(SEARCH(instructor,conceptos)),FALSE), montos ) ), IF(mesNum=0,"",ingresos*porcentaje) )} -> 90000 | P18: =COUNTIFS($AV$34:$AV$825,"<>Abandonado",$AP$34:$AP$825,C18) -> 19 | Q18: 25000 | S18: {=LET( mesTxt,LOWER(TRIM(INDEX($U18:$V18,1,1))), meses,{"enero";"febrero";"marzo";"abril";"mayo";"junio";"julio";"agosto";"septiembre";"octubre";"noviembre";"diciembre"}, mesNum,IFERROR(MATCH(mesTxt,meses,0),0), anio,YEAR(DASHBOARD!$AY$2), inicio,DATE(anio,mesNum,1), fin,EOMONTH(inicio,0), disciplina,LOWER(TRIM(INDEX($C18:$D18,1,1))), instructor,LOWER(TRIM(INDEX($G18:$I18,1,1))), paga,N(INDEX($N18:$O18,1,1)), fechas,$C$34:$C$820, tipos,UPPER(TRIM($E$34:$E$820)), categorias,UPPER(TRIM($G$34:$G$820)), conceptos,LOWER(TRIM($I$34:$I$820)), montos,$P$34:$P$820, estados,UPPER(TRIM($Y$34:$Y$820)), relacionado, IFERROR(ISNUMBER(SEARCH(disciplina,conceptos)),FALSE) * IFERROR(ISNUMBER(SEARCH(instructor,conceptos)),FALSE), ingresosCuotas,IF( mesNum=0, 0, SUMPRODUCT( --(fechas>=inicio), --(fechas<=fin), --(tipos="INGRESOS"), --(estados="COMPLETADO"), --ISNUMBER(MATCH(categorias,{"CUOTA";"INSCRIPCIÓN";"INSCRIPCION"},0)), --(relacionado>0), montos ) ), ingresosComision,IF( mesNum=0, 0, SUMPRODUCT( --(fechas>=inicio), --(fechas<=fin), --(tipos="INGRESOS"), --(estados="COMPLETADO"), --ISNUMBER(MATCH(categorias,{"COMISIÓN";"COMISION"},0)), --(relacionado>0), montos ) ), egresosComision,IF( mesNum=0, 0, SUMPRODUCT( --(fechas>=inicio), --(fechas<=fin), --(tipos="EGRESOS"), --(estados="COMPLETADO"), --ISNUMBER(MATCH(categorias,{"COMISIÓN";"COMISION"},0)), --(relacionado>0), montos ) ), IF(mesNum=0,"",ingresosCuotas+ingresosComision-egresosComision-paga) )} -> 95000 | U18: Julio | X18: INGRESO CLUB | AB18: INGRESO PROFES | AF18: 0.83333333 | AT18: 0
B19: P | C19: Taller de Fotografía | G19: =VLOOKUP(C19,System!$B$17:$H$40,3,FALSE) -> Camila Alarcon | L19: 0 | N19: {=LET( mesTxt,LOWER(TRIM(INDEX($U19:$V19,1,1))), meses,{"enero";"febrero";"marzo";"abril";"mayo";"junio";"julio";"agosto";"septiembre";"octubre";"noviembre";"diciembre"}, mesNum,IFERROR(MATCH(mesTxt,meses,0),0), anio,YEAR(DASHBOARD!$AY$2), inicio,DATE(anio,mesNum,1), fin,EOMONTH(inicio,0), disciplina,LOWER(TRIM(INDEX($C19:$D19,1,1))), instructor,LOWER(TRIM(INDEX($G19:$I19,1,1))), porcentaje,N(INDEX($L19:$M19,1,1)), fechas,$C$34:$C$820, tipos,UPPER(TRIM($E$34:$E$820)), categorias,UPPER(TRIM($G$34:$G$820)), conceptos,LOWER(TRIM($I$34:$I$820)), montos,$P$34:$P$820, estados,UPPER(TRIM($Y$34:$Y$820)), ingresos,IF( mesNum=0, 0, SUMPRODUCT( --(fechas>=inicio), --(fechas<=fin), --(tipos="INGRESOS"), --(estados="COMPLETADO"), --ISNUMBER(MATCH(categorias,{"CUOTA";"INSCRIPCIÓN";"INSCRIPCION";"CLASES"},0)), --IFERROR(ISNUMBER(SEARCH(disciplina,conceptos)),FALSE), --IFERROR(ISNUMBER(SEARCH(instructor,conceptos)),FALSE), montos ) ), IF(mesNum=0,"",ingresos*porcentaje) )} -> 0 | P19: =COUNTIFS($AV$34:$AV$825,"<>Abandonado",$AP$34:$AP$825,C19) -> 0 | Q19: 30000 | S19: {=LET( mesTxt,LOWER(TRIM(INDEX($U19:$V19,1,1))), meses,{"enero";"febrero";"marzo";"abril";"mayo";"junio";"julio";"agosto";"septiembre";"octubre";"noviembre";"diciembre"}, mesNum,IFERROR(MATCH(mesTxt,meses,0),0), anio,YEAR(DASHBOARD!$AY$2), inicio,DATE(anio,mesNum,1), fin,EOMONTH(inicio,0), disciplina,LOWER(TRIM(INDEX($C19:$D19,1,1))), instructor,LOWER(TRIM(INDEX($G19:$I19,1,1))), paga,N(INDEX($N19:$O19,1,1)), fechas,$C$34:$C$820, tipos,UPPER(TRIM($E$34:$E$820)), categorias,UPPER(TRIM($G$34:$G$820)), conceptos,LOWER(TRIM($I$34:$I$820)), montos,$P$34:$P$820, estados,UPPER(TRIM($Y$34:$Y$820)), relacionado, IFERROR(ISNUMBER(SEARCH(disciplina,conceptos)),FALSE) * IFERROR(ISNUMBER(SEARCH(instructor,conceptos)),FALSE), ingresosCuotas,IF( mesNum=0, 0, SUMPRODUCT( --(fechas>=inicio), --(fechas<=fin), --(tipos="INGRESOS"), --(estados="COMPLETADO"), --ISNUMBER(MATCH(categorias,{"CUOTA";"INSCRIPCIÓN";"INSCRIPCION"},0)), --(relacionado>0), montos ) ), ingresosComision,IF( mesNum=0, 0, SUMPRODUCT( --(fechas>=inicio), --(fechas<=fin), --(tipos="INGRESOS"), --(estados="COMPLETADO"), --ISNUMBER(MATCH(categorias,{"COMISIÓN";"COMISION"},0)), --(relacionado>0), montos ) ), egresosComision,IF( mesNum=0, 0, SUMPRODUCT( --(fechas>=inicio), --(fechas<=fin), --(tipos="EGRESOS"), --(estados="COMPLETADO"), --ISNUMBER(MATCH(categorias,{"COMISIÓN";"COMISION"},0)), --(relacionado>0), montos ) ), IF(mesNum=0,"",ingresosCuotas+ingresosComision-egresosComision-paga) )} -> 0 | U19: Julio | X19: =SUM(N18:O30) -> 104000 | AB19: =SUMIF(B18:B30,"EC",S18:T30) -> 116000 | AF19: 0.83333333 | AG19: - | AI19: Arte - Adultos | AK19: - | AM19: Arte - Adultos | AO19: - | AQ19: -
B20: EC | C20: Magia e Ilusionismo | G20: =VLOOKUP(C20,System!$B$17:$H$40,3,FALSE) -> Exequiel Florentin | L20: 0.4 | N20: {=LET( mesTxt,LOWER(TRIM(INDEX($U20:$V20,1,1))), meses,{"enero";"febrero";"marzo";"abril";"mayo";"junio";"julio";"agosto";"septiembre";"octubre";"noviembre";"diciembre"}, mesNum,IFERROR(MATCH(mesTxt,meses,0),0), anio,YEAR(DASHBOARD!$AY$2), inicio,DATE(anio,mesNum,1), fin,EOMONTH(inicio,0), disciplina,LOWER(TRIM(INDEX($C20:$D20,1,1))), instructor,LOWER(TRIM(INDEX($G20:$I20,1,1))), porcentaje,N(INDEX($L20:$M20,1,1)), fechas,$C$34:$C$820, tipos,UPPER(TRIM($E$34:$E$820)), categorias,UPPER(TRIM($G$34:$G$820)), conceptos,LOWER(TRIM($I$34:$I$820)), montos,$P$34:$P$820, estados,UPPER(TRIM($Y$34:$Y$820)), ingresos,IF( mesNum=0, 0, SUMPRODUCT( --(fechas>=inicio), --(fechas<=fin), --(tipos="INGRESOS"), --(estados="COMPLETADO"), --ISNUMBER(MATCH(categorias,{"CUOTA";"INSCRIPCIÓN";"INSCRIPCION";"CLASES"},0)), --IFERROR(ISNUMBER(SEARCH(disciplina,conceptos)),FALSE), --IFERROR(ISNUMBER(SEARCH(instructor,conceptos)),FALSE), montos ) ), IF(mesNum=0,"",ingresos*porcentaje) )} -> 0 | P20: =COUNTIFS($AV$34:$AV$825,"<>Abandonado",$AP$34:$AP$825,C20) -> 0 | Q20: 20000 | S20: {=LET( mesTxt,LOWER(TRIM(INDEX($U20:$V20,1,1))), meses,{"enero";"febrero";"marzo";"abril";"mayo";"junio";"julio";"agosto";"septiembre";"octubre";"noviembre";"diciembre"}, mesNum,IFERROR(MATCH(mesTxt,meses,0),0), anio,YEAR(DASHBOARD!$AY$2), inicio,DATE(anio,mesNum,1), fin,EOMONTH(inicio,0), disciplina,LOWER(TRIM(INDEX($C20:$D20,1,1))), instructor,LOWER(TRIM(INDEX($G20:$I20,1,1))), paga,N(INDEX($N20:$O20,1,1)), fechas,$C$34:$C$820, tipos,UPPER(TRIM($E$34:$E$820)), categorias,UPPER(TRIM($G$34:$G$820)), conceptos,LOWER(TRIM($I$34:$I$820)), montos,$P$34:$P$820, estados,UPPER(TRIM($Y$34:$Y$820)), relacionado, IFERROR(ISNUMBER(SEARCH(disciplina,conceptos)),FALSE) * IFERROR(ISNUMBER(SEARCH(instructor,conceptos)),FALSE), ingresosCuotas,IF( mesNum=0, 0, SUMPRODUCT( --(fechas>=inicio), --(fechas<=fin), --(tipos="INGRESOS"), --(estados="COMPLETADO"), --ISNUMBER(MATCH(categorias,{"CUOTA";"INSCRIPCIÓN";"INSCRIPCION"},0)), --(relacionado>0), montos ) ), ingresosComision,IF( mesNum=0, 0, SUMPRODUCT( --(fechas>=inicio), --(fechas<=fin), --(tipos="INGRESOS"), --(estados="COMPLETADO"), --ISNUMBER(MATCH(categorias,{"COMISIÓN";"COMISION"},0)), --(relacionado>0), montos ) ), egresosComision,IF( mesNum=0, 0, SUMPRODUCT( --(fechas>=inicio), --(fechas<=fin), --(tipos="EGRESOS"), --(estados="COMPLETADO"), --ISNUMBER(MATCH(categorias,{"COMISIÓN";"COMISION"},0)), --(relacionado>0), montos ) ), IF(mesNum=0,"",ingresosCuotas+ingresosComision-egresosComision-paga) )} -> 0 | U20: Julio | AF20: 0.89583333
B21: P | C21: Clases de Canto | G21: =VLOOKUP(C21,System!$B$17:$H$40,3,FALSE) -> Leonardo Baigorria | L21: 0.3 | N21: {=LET( mesTxt,LOWER(TRIM(INDEX($U21:$V21,1,1))), meses,{"enero";"febrero";"marzo";"abril";"mayo";"junio";"julio";"agosto";"septiembre";"octubre";"noviembre";"diciembre"}, mesNum,IFERROR(MATCH(mesTxt,meses,0),0), anio,YEAR(DASHBOARD!$AY$2), inicio,DATE(anio,mesNum,1), fin,EOMONTH(inicio,0), disciplina,LOWER(TRIM(INDEX($C21:$D21,1,1))), instructor,LOWER(TRIM(INDEX($G21:$I21,1,1))), porcentaje,N(INDEX($L21:$M21,1,1)), fechas,$C$34:$C$820, tipos,UPPER(TRIM($E$34:$E$820)), categorias,UPPER(TRIM($G$34:$G$820)), conceptos,LOWER(TRIM($I$34:$I$820)), montos,$P$34:$P$820, estados,UPPER(TRIM($Y$34:$Y$820)), ingresos,IF( mesNum=0, 0, SUMPRODUCT( --(fechas>=inicio), --(fechas<=fin), --(tipos="INGRESOS"), --(estados="COMPLETADO"), --ISNUMBER(MATCH(categorias,{"CUOTA";"INSCRIPCIÓN";"INSCRIPCION";"CLASES"},0)), --IFERROR(ISNUMBER(SEARCH(disciplina,conceptos)),FALSE), --IFERROR(ISNUMBER(SEARCH(instructor,conceptos)),FALSE), montos ) ), IF(mesNum=0,"",ingresos*porcentaje) )} -> 0 | P21: =COUNTIFS($AV$34:$AV$825,"<>Abandonado",$AP$34:$AP$825,C21) -> 0 | Q21: 15000 | S21: {=LET( mesTxt,LOWER(TRIM(INDEX($U21:$V21,1,1))), meses,{"enero";"febrero";"marzo";"abril";"mayo";"junio";"julio";"agosto";"septiembre";"octubre";"noviembre";"diciembre"}, mesNum,IFERROR(MATCH(mesTxt,meses,0),0), anio,YEAR(DASHBOARD!$AY$2), inicio,DATE(anio,mesNum,1), fin,EOMONTH(inicio,0), disciplina,LOWER(TRIM(INDEX($C21:$D21,1,1))), instructor,LOWER(TRIM(INDEX($G21:$I21,1,1))), paga,N(INDEX($N21:$O21,1,1)), fechas,$C$34:$C$820, tipos,UPPER(TRIM($E$34:$E$820)), categorias,UPPER(TRIM($G$34:$G$820)), conceptos,LOWER(TRIM($I$34:$I$820)), montos,$P$34:$P$820, estados,UPPER(TRIM($Y$34:$Y$820)), relacionado, IFERROR(ISNUMBER(SEARCH(disciplina,conceptos)),FALSE) * IFERROR(ISNUMBER(SEARCH(instructor,conceptos)),FALSE), ingresosCuotas,IF( mesNum=0, 0, SUMPRODUCT( --(fechas>=inicio), --(fechas<=fin), --(tipos="INGRESOS"), --(estados="COMPLETADO"), --ISNUMBER(MATCH(categorias,{"CUOTA";"INSCRIPCIÓN";"INSCRIPCION"},0)), --(relacionado>0), montos ) ), ingresosComision,IF( mesNum=0, 0, SUMPRODUCT( --(fechas>=inicio), --(fechas<=fin), --(tipos="INGRESOS"), --(estados="COMPLETADO"), --ISNUMBER(MATCH(categorias,{"COMISIÓN";"COMISION"},0)), --(relacionado>0), montos ) ), egresosComision,IF( mesNum=0, 0, SUMPRODUCT( --(fechas>=inicio), --(fechas<=fin), --(tipos="EGRESOS"), --(estados="COMPLETADO"), --ISNUMBER(MATCH(categorias,{"COMISIÓN";"COMISION"},0)), --(relacionado>0), montos ) ), IF(mesNum=0,"",ingresosCuotas+ingresosComision-egresosComision-paga) )} -> 0 | U21: Julio
B22: EC | C22: Arte - Adultos | G22: =VLOOKUP(C22,System!$B$17:$H$40,3,FALSE) -> Vanesa Rodriguez | J22: 35.872.158 | L22: 0.4 | N22: {=LET( mesTxt,LOWER(TRIM(INDEX($U22:$V22,1,1))), meses,{"enero";"febrero";"marzo";"abril";"mayo";"junio";"julio";"agosto";"septiembre";"octubre";"noviembre";"diciembre"}, mesNum,IFERROR(MATCH(mesTxt,meses,0),0), anio,YEAR(DASHBOARD!$AY$2), inicio,DATE(anio,mesNum,1), fin,EOMONTH(inicio,0), disciplina,LOWER(TRIM(INDEX($C22:$D22,1,1))), instructor,LOWER(TRIM(INDEX($G22:$I22,1,1))), porcentaje,N(INDEX($L22:$M22,1,1)), fechas,$C$34:$C$820, tipos,UPPER(TRIM($E$34:$E$820)), categorias,UPPER(TRIM($G$34:$G$820)), conceptos,LOWER(TRIM($I$34:$I$820)), montos,$P$34:$P$820, estados,UPPER(TRIM($Y$34:$Y$820)), ingresos,IF( mesNum=0, 0, SUMPRODUCT( --(fechas>=inicio), --(fechas<=fin), --(tipos="INGRESOS"), --(estados="COMPLETADO"), --ISNUMBER(MATCH(categorias,{"CUOTA";"INSCRIPCIÓN";"INSCRIPCION";"CLASES"},0)), --IFERROR(ISNUMBER(SEARCH(disciplina,conceptos)),FALSE), --IFERROR(ISNUMBER(SEARCH(instructor,conceptos)),FALSE), montos ) ), IF(mesNum=0,"",ingresos*porcentaje) )} -> 14000 | P22: =COUNTIFS($AV$34:$AV$825,"<>Abandonado",$AP$34:$AP$825,C22) -> 1 | Q22: 35000 | S22: {=LET( mesTxt,LOWER(TRIM(INDEX($U22:$V22,1,1))), meses,{"enero";"febrero";"marzo";"abril";"mayo";"junio";"julio";"agosto";"septiembre";"octubre";"noviembre";"diciembre"}, mesNum,IFERROR(MATCH(mesTxt,meses,0),0), anio,YEAR(DASHBOARD!$AY$2), inicio,DATE(anio,mesNum,1), fin,EOMONTH(inicio,0), disciplina,LOWER(TRIM(INDEX($C22:$D22,1,1))), instructor,LOWER(TRIM(INDEX($G22:$I22,1,1))), paga,N(INDEX($N22:$O22,1,1)), fechas,$C$34:$C$820, tipos,UPPER(TRIM($E$34:$E$820)), categorias,UPPER(TRIM($G$34:$G$820)), conceptos,LOWER(TRIM($I$34:$I$820)), montos,$P$34:$P$820, estados,UPPER(TRIM($Y$34:$Y$820)), relacionado, IFERROR(ISNUMBER(SEARCH(disciplina,conceptos)),FALSE) * IFERROR(ISNUMBER(SEARCH(instructor,conceptos)),FALSE), ingresosCuotas,IF( mesNum=0, 0, SUMPRODUCT( --(fechas>=inicio), --(fechas<=fin), --(tipos="INGRESOS"), --(estados="COMPLETADO"), --ISNUMBER(MATCH(categorias,{"CUOTA";"INSCRIPCIÓN";"INSCRIPCION"},0)), --(relacionado>0), montos ) ), ingresosComision,IF( mesNum=0, 0, SUMPRODUCT( --(fechas>=inicio), --(fechas<=fin), --(tipos="INGRESOS"), --(estados="COMPLETADO"), --ISNUMBER(MATCH(categorias,{"COMISIÓN";"COMISION"},0)), --(relacionado>0), montos ) ), egresosComision,IF( mesNum=0, 0, SUMPRODUCT( --(fechas>=inicio), --(fechas<=fin), --(tipos="EGRESOS"), --(estados="COMPLETADO"), --ISNUMBER(MATCH(categorias,{"COMISIÓN";"COMISION"},0)), --(relacionado>0), montos ) ), IF(mesNum=0,"",ingresosCuotas+ingresosComision-egresosComision-paga) )} -> 21000 | U22: Julio
C23: - | G23: =VLOOKUP(C23,System!$B$17:$H$40,3,FALSE) | P23: =COUNTIFS($AV$34:$AV$825,"<>Abandonado",$AP$34:$AP$825,C23) -> 0 | S23: {=LET( mesTxt,LOWER(TRIM(INDEX($U23:$V23,1,1))), meses,{"enero";"febrero";"marzo";"abril";"mayo";"junio";"julio";"agosto";"septiembre";"octubre";"noviembre";"diciembre"}, mesNum,IFERROR(MATCH(mesTxt,meses,0),0), anio,YEAR(DASHBOARD!$AY$2), inicio,DATE(anio,mesNum,1), fin,EOMONTH(inicio,0), disciplina,LOWER(TRIM(INDEX($C23:$D23,1,1))), instructor,LOWER(TRIM(INDEX($G23:$I23,1,1))), paga,N(INDEX($N23:$O23,1,1)), fechas,$C$34:$C$820, tipos,UPPER(TRIM($E$34:$E$820)), categorias,UPPER(TRIM($G$34:$G$820)), conceptos,LOWER(TRIM($I$34:$I$820)), montos,$P$34:$P$820, estados,UPPER(TRIM($Y$34:$Y$820)), relacionado, IFERROR(ISNUMBER(SEARCH(disciplina,conceptos)),FALSE) * IFERROR(ISNUMBER(SEARCH(instructor,conceptos)),FALSE), ingresosCuotas,IF( mesNum=0, 0, SUMPRODUCT( --(fechas>=inicio), --(fechas<=fin), --(tipos="INGRESOS"), --(estados="COMPLETADO"), --ISNUMBER(MATCH(categorias,{"CUOTA";"INSCRIPCIÓN";"INSCRIPCION"},0)), --(relacionado>0), montos ) ), ingresosComision,IF( mesNum=0, 0, SUMPRODUCT( --(fechas>=inicio), --(fechas<=fin), --(tipos="INGRESOS"), --(estados="COMPLETADO"), --ISNUMBER(MATCH(categorias,{"COMISIÓN";"COMISION"},0)), --(relacionado>0), montos ) ), egresosComision,IF( mesNum=0, 0, SUMPRODUCT( --(fechas>=inicio), --(fechas<=fin), --(tipos="EGRESOS"), --(estados="COMPLETADO"), --ISNUMBER(MATCH(categorias,{"COMISIÓN";"COMISION"},0)), --(relacionado>0), montos ) ), IF(mesNum=0,"",ingresosCuotas+ingresosComision-egresosComision-paga) )} | X23: INGRESOS | AF23: GASTOS | AN23: UTILIDAD | AW23: Adeudado | AY23: =SUMIF(AV34:AV837,"Adeudando",AT34:AT837) -> 175000
C24: - | G24: =VLOOKUP(C24,System!$B$17:$H$40,3,FALSE) | P24: =COUNTIFS($AV$34:$AV$825,"<>Abandonado",$AP$34:$AP$825,C24) -> 0 | S24: {=LET( mesTxt,LOWER(TRIM(INDEX($U24:$V24,1,1))), meses,{"enero";"febrero";"marzo";"abril";"mayo";"junio";"julio";"agosto";"septiembre";"octubre";"noviembre";"diciembre"}, mesNum,IFERROR(MATCH(mesTxt,meses,0),0), anio,YEAR(DASHBOARD!$AY$2), inicio,DATE(anio,mesNum,1), fin,EOMONTH(inicio,0), disciplina,LOWER(TRIM(INDEX($C24:$D24,1,1))), instructor,LOWER(TRIM(INDEX($G24:$I24,1,1))), paga,N(INDEX($N24:$O24,1,1)), fechas,$C$34:$C$820, tipos,UPPER(TRIM($E$34:$E$820)), categorias,UPPER(TRIM($G$34:$G$820)), conceptos,LOWER(TRIM($I$34:$I$820)), montos,$P$34:$P$820, estados,UPPER(TRIM($Y$34:$Y$820)), relacionado, IFERROR(ISNUMBER(SEARCH(disciplina,conceptos)),FALSE) * IFERROR(ISNUMBER(SEARCH(instructor,conceptos)),FALSE), ingresosCuotas,IF( mesNum=0, 0, SUMPRODUCT( --(fechas>=inicio), --(fechas<=fin), --(tipos="INGRESOS"), --(estados="COMPLETADO"), --ISNUMBER(MATCH(categorias,{"CUOTA";"INSCRIPCIÓN";"INSCRIPCION"},0)), --(relacionado>0), montos ) ), ingresosComision,IF( mesNum=0, 0, SUMPRODUCT( --(fechas>=inicio), --(fechas<=fin), --(tipos="INGRESOS"), --(estados="COMPLETADO"), --ISNUMBER(MATCH(categorias,{"COMISIÓN";"COMISION"},0)), --(relacionado>0), montos ) ), egresosComision,IF( mesNum=0, 0, SUMPRODUCT( --(fechas>=inicio), --(fechas<=fin), --(tipos="EGRESOS"), --(estados="COMPLETADO"), --ISNUMBER(MATCH(categorias,{"COMISIÓN";"COMISION"},0)), --(relacionado>0), montos ) ), IF(mesNum=0,"",ingresosCuotas+ingresosComision-egresosComision-paga) )} | X24: Enero | Z24: =SUMIFS($P$34:$P$825,$C$34:$C$825,">="&DATE(2026,1,1),$C$34:$C$825,"<"&DATE(2026,2,1),$E$34:$E$825,"INGRESOS",$Y$34:$Y$825,"COMPLETADO") -> 0 | AB24: Febrero | AD24: =SUMIFS($P$34:$P$825,$C$34:$C$825,">="&DATE(2026,2,1),$C$34:$C$825,"<"&DATE(2026,3,1),$E$34:$E$825,"INGRESOS",$Y$34:$Y$825,"COMPLETADO") -> 0 | AF24: Enero | AH24: =-SUMIFS($P$34:$P$825,$C$34:$C$825,">="&DATE(2026,1,1),$C$34:$C$825,"<"&DATE(2026,2,1),$E$34:$E$825,"EGRESOS",$Y$34:$Y$825,"COMPLETADO") -> 0 | AJ24: Febrero | AL24: =-SUMIFS($P$34:$P$825,$C$34:$C$825,">="&DATE(2026,2,1),$C$34:$C$825,"<"&DATE(2026,3,1),$E$34:$E$825,"EGRESOS",$Y$34:$Y$825,"COMPLETADO") -> 0 | AN24: Enero | AP24: =Z24+AH24 -> 0 | AR24: Febrero | AT24: =AD24+AL24 -> 0
C25: - | G25: =VLOOKUP(C25,System!$B$17:$H$40,3,FALSE) | P25: =COUNTIFS($AV$34:$AV$825,"<>Abandonado",$AP$34:$AP$825,C25) -> 0 | S25: {=LET( mesTxt,LOWER(TRIM(INDEX($U25:$V25,1,1))), meses,{"enero";"febrero";"marzo";"abril";"mayo";"junio";"julio";"agosto";"septiembre";"octubre";"noviembre";"diciembre"}, mesNum,IFERROR(MATCH(mesTxt,meses,0),0), anio,YEAR(DASHBOARD!$AY$2), inicio,DATE(anio,mesNum,1), fin,EOMONTH(inicio,0), disciplina,LOWER(TRIM(INDEX($C25:$D25,1,1))), instructor,LOWER(TRIM(INDEX($G25:$I25,1,1))), paga,N(INDEX($N25:$O25,1,1)), fechas,$C$34:$C$820, tipos,UPPER(TRIM($E$34:$E$820)), categorias,UPPER(TRIM($G$34:$G$820)), conceptos,LOWER(TRIM($I$34:$I$820)), montos,$P$34:$P$820, estados,UPPER(TRIM($Y$34:$Y$820)), relacionado, IFERROR(ISNUMBER(SEARCH(disciplina,conceptos)),FALSE) * IFERROR(ISNUMBER(SEARCH(instructor,conceptos)),FALSE), ingresosCuotas,IF( mesNum=0, 0, SUMPRODUCT( --(fechas>=inicio), --(fechas<=fin), --(tipos="INGRESOS"), --(estados="COMPLETADO"), --ISNUMBER(MATCH(categorias,{"CUOTA";"INSCRIPCIÓN";"INSCRIPCION"},0)), --(relacionado>0), montos ) ), ingresosComision,IF( mesNum=0, 0, SUMPRODUCT( --(fechas>=inicio), --(fechas<=fin), --(tipos="INGRESOS"), --(estados="COMPLETADO"), --ISNUMBER(MATCH(categorias,{"COMISIÓN";"COMISION"},0)), --(relacionado>0), montos ) ), egresosComision,IF( mesNum=0, 0, SUMPRODUCT( --(fechas>=inicio), --(fechas<=fin), --(tipos="EGRESOS"), --(estados="COMPLETADO"), --ISNUMBER(MATCH(categorias,{"COMISIÓN";"COMISION"},0)), --(relacionado>0), montos ) ), IF(mesNum=0,"",ingresosCuotas+ingresosComision-egresosComision-paga) )} | X25: Marzo | Z25: =SUMIFS($P$34:$P$825,$C$34:$C$825,">="&DATE(2026,3,1),$C$34:$C$825,"<"&DATE(2026,4,1),$E$34:$E$825,"INGRESOS",$Y$34:$Y$825,"COMPLETADO") -> 0 | AB25: Abril | AD25: =SUMIFS($P$34:$P$825,$C$34:$C$825,">="&DATE(2026,4,1),$C$34:$C$825,"<"&DATE(2026,5,1),$E$34:$E$825,"INGRESOS",$Y$34:$Y$825,"COMPLETADO") -> 0 | AF25: Marzo | AH25: =-SUMIFS($P$34:$P$825,$C$34:$C$825,">="&DATE(2026,3,1),$C$34:$C$825,"<"&DATE(2026,4,1),$E$34:$E$825,"EGRESOS",$Y$34:$Y$825,"COMPLETADO") -> 0 | AJ25: Abril | AL25: =-SUMIFS($P$34:$P$825,$C$34:$C$825,">="&DATE(2026,4,1),$C$34:$C$825,"<"&DATE(2026,5,1),$E$34:$E$825,"EGRESOS",$Y$34:$Y$825,"COMPLETADO") -> -100000 | AN25: Marzo | AP25: =Z25+AH25 -> 0 | AR25: Abril | AT25: =AD25+AL25 -> -100000 | AW25: INGRESO TOTAL | AZ25: EGRESO TOTAL
C26: - | G26: =VLOOKUP(C26,System!$B$17:$H$40,3,FALSE) | P26: =COUNTIFS($AV$34:$AV$825,"<>Abandonado",$AP$34:$AP$825,C26) -> 0 | S26: {=LET( mesTxt,LOWER(TRIM(INDEX($U26:$V26,1,1))), meses,{"enero";"febrero";"marzo";"abril";"mayo";"junio";"julio";"agosto";"septiembre";"octubre";"noviembre";"diciembre"}, mesNum,IFERROR(MATCH(mesTxt,meses,0),0), anio,YEAR(DASHBOARD!$AY$2), inicio,DATE(anio,mesNum,1), fin,EOMONTH(inicio,0), disciplina,LOWER(TRIM(INDEX($C26:$D26,1,1))), instructor,LOWER(TRIM(INDEX($G26:$I26,1,1))), paga,N(INDEX($N26:$O26,1,1)), fechas,$C$34:$C$820, tipos,UPPER(TRIM($E$34:$E$820)), categorias,UPPER(TRIM($G$34:$G$820)), conceptos,LOWER(TRIM($I$34:$I$820)), montos,$P$34:$P$820, estados,UPPER(TRIM($Y$34:$Y$820)), relacionado, IFERROR(ISNUMBER(SEARCH(disciplina,conceptos)),FALSE) * IFERROR(ISNUMBER(SEARCH(instructor,conceptos)),FALSE), ingresosCuotas,IF( mesNum=0, 0, SUMPRODUCT( --(fechas>=inicio), --(fechas<=fin), --(tipos="INGRESOS"), --(estados="COMPLETADO"), --ISNUMBER(MATCH(categorias,{"CUOTA";"INSCRIPCIÓN";"INSCRIPCION"},0)), --(relacionado>0), montos ) ), ingresosComision,IF( mesNum=0, 0, SUMPRODUCT( --(fechas>=inicio), --(fechas<=fin), --(tipos="INGRESOS"), --(estados="COMPLETADO"), --ISNUMBER(MATCH(categorias,{"COMISIÓN";"COMISION"},0)), --(relacionado>0), montos ) ), egresosComision,IF( mesNum=0, 0, SUMPRODUCT( --(fechas>=inicio), --(fechas<=fin), --(tipos="EGRESOS"), --(estados="COMPLETADO"), --ISNUMBER(MATCH(categorias,{"COMISIÓN";"COMISION"},0)), --(relacionado>0), montos ) ), IF(mesNum=0,"",ingresosCuotas+ingresosComision-egresosComision-paga) )} | X26: Mayo | Z26: =SUMIFS($P$34:$P$825,$C$34:$C$825,">="&DATE(2026,5,1),$C$34:$C$825,"<"&DATE(2026,6,1),$E$34:$E$825,"INGRESOS",$Y$34:$Y$825,"COMPLETADO") -> 265000 | AB26: Junio | AD26: =SUMIFS($P$34:$P$825,$C$34:$C$825,">="&DATE(2026,6,1),$C$34:$C$825,"<"&DATE(2026,7,1),$E$34:$E$825,"INGRESOS",$Y$34:$Y$825,"COMPLETADO") -> 310000 | AF26: Mayo | AH26: =-SUMIFS($P$34:$P$825,$C$34:$C$825,">="&DATE(2026,5,1),$C$34:$C$825,"<"&DATE(2026,6,1),$E$34:$E$825,"EGRESOS",$Y$34:$Y$825,"COMPLETADO") -> -171000 | AJ26: Junio | AL26: =-SUMIFS($P$34:$P$825,$C$34:$C$825,">="&DATE(2026,6,1),$C$34:$C$825,"<"&DATE(2026,7,1),$E$34:$E$825,"EGRESOS",$Y$34:$Y$825,"COMPLETADO") -> -186000 | AN26: Mayo | AP26: =Z26+AH26 -> 94000 | AR26: Junio | AT26: =AD26+AL26 -> 124000 | AW26: =SUMIFS($P$34:$P$825,$E$34:$E$825,"INGRESOS",$G$34:$G825,"CUOTA",$V$34:$V$825,"*ADO")+(SUMIFS($P$34:$P$825,$E$34:$E$825,"INGRESOS",$G$34:$G825,"COMISIÓN",$V$34:$V$825,"*ADO")) -> 835000 | AZ26: =SUMIFS($P$34:$P$825,$E$34:$E$825,"EGRESOS",$G$34:$G825,"COMISIÓN",$V$34:$V$825,"*ADO")+SUMIFS($P$34:$P$825,$E$34:$E$825,"EGRESOS",$G$34:$G$825,"CMV",$V$34:$V$825,"*ADO") -> 397000
C27: - | G27: =VLOOKUP(C27,System!$B$17:$H$40,3,FALSE) | P27: =COUNTIFS($AV$34:$AV$825,"<>Abandonado",$AP$34:$AP$825,C27) -> 0 | S27: {=LET( mesTxt,LOWER(TRIM(INDEX($U27:$V27,1,1))), meses,{"enero";"febrero";"marzo";"abril";"mayo";"junio";"julio";"agosto";"septiembre";"octubre";"noviembre";"diciembre"}, mesNum,IFERROR(MATCH(mesTxt,meses,0),0), anio,YEAR(DASHBOARD!$AY$2), inicio,DATE(anio,mesNum,1), fin,EOMONTH(inicio,0), disciplina,LOWER(TRIM(INDEX($C27:$D27,1,1))), instructor,LOWER(TRIM(INDEX($G27:$I27,1,1))), paga,N(INDEX($N27:$O27,1,1)), fechas,$C$34:$C$820, tipos,UPPER(TRIM($E$34:$E$820)), categorias,UPPER(TRIM($G$34:$G$820)), conceptos,LOWER(TRIM($I$34:$I$820)), montos,$P$34:$P$820, estados,UPPER(TRIM($Y$34:$Y$820)), relacionado, IFERROR(ISNUMBER(SEARCH(disciplina,conceptos)),FALSE) * IFERROR(ISNUMBER(SEARCH(instructor,conceptos)),FALSE), ingresosCuotas,IF( mesNum=0, 0, SUMPRODUCT( --(fechas>=inicio), --(fechas<=fin), --(tipos="INGRESOS"), --(estados="COMPLETADO"), --ISNUMBER(MATCH(categorias,{"CUOTA";"INSCRIPCIÓN";"INSCRIPCION"},0)), --(relacionado>0), montos ) ), ingresosComision,IF( mesNum=0, 0, SUMPRODUCT( --(fechas>=inicio), --(fechas<=fin), --(tipos="INGRESOS"), --(estados="COMPLETADO"), --ISNUMBER(MATCH(categorias,{"COMISIÓN";"COMISION"},0)), --(relacionado>0), montos ) ), egresosComision,IF( mesNum=0, 0, SUMPRODUCT( --(fechas>=inicio), --(fechas<=fin), --(tipos="EGRESOS"), --(estados="COMPLETADO"), --ISNUMBER(MATCH(categorias,{"COMISIÓN";"COMISION"},0)), --(relacionado>0), montos ) ), IF(mesNum=0,"",ingresosCuotas+ingresosComision-egresosComision-paga) )} | X27: Julio | Z27: =SUMIFS($P$34:$P$825,$C$34:$C$825,">="&DATE(2026,7,1),$C$34:$C$825,"<"&DATE(2026,8,1),$E$34:$E$825,"INGRESOS",$Y$34:$Y$825,"COMPLETADO") -> 260000 | AB27: Agosto | AD27: =SUMIFS($P$34:$P$825,$C$34:$C$825,">="&DATE(2026,8,1),$C$34:$C$825,"<"&DATE(2026,9,1),$E$34:$E$825,"INGRESOS",$Y$34:$Y$825,"COMPLETADO") -> 0 | AF27: Julio | AH27: =-SUMIFS($P$34:$P$825,$C$34:$C$825,">="&DATE(2026,7,1),$C$34:$C$825,"<"&DATE(2026,8,1),$E$34:$E$825,"EGRESOS",$Y$34:$Y$825,"COMPLETADO") -> -40000 | AJ27: Agosto | AL27: =-SUMIFS($P$34:$P$825,$C$34:$C$825,">="&DATE(2026,8,1),$C$34:$C$825,"<"&DATE(2026,9,1),$E$34:$E$825,"EGRESOS",$Y$34:$Y$825,"COMPLETADO") -> 0 | AN27: Julio | AP27: =Z27+AH27 -> 220000 | AR27: Agosto | AT27: =AD27+AL27 -> 0
C28: - | G28: =VLOOKUP(C28,System!$B$17:$H$40,3,FALSE) | P28: =COUNTIFS($AV$34:$AV$825,"<>Abandonado",$AP$34:$AP$825,C28) -> 0 | S28: {=LET( mesTxt,LOWER(TRIM(INDEX($U28:$V28,1,1))), meses,{"enero";"febrero";"marzo";"abril";"mayo";"junio";"julio";"agosto";"septiembre";"octubre";"noviembre";"diciembre"}, mesNum,IFERROR(MATCH(mesTxt,meses,0),0), anio,YEAR(DASHBOARD!$AY$2), inicio,DATE(anio,mesNum,1), fin,EOMONTH(inicio,0), disciplina,LOWER(TRIM(INDEX($C28:$D28,1,1))), instructor,LOWER(TRIM(INDEX($G28:$I28,1,1))), paga,N(INDEX($N28:$O28,1,1)), fechas,$C$34:$C$820, tipos,UPPER(TRIM($E$34:$E$820)), categorias,UPPER(TRIM($G$34:$G$820)), conceptos,LOWER(TRIM($I$34:$I$820)), montos,$P$34:$P$820, estados,UPPER(TRIM($Y$34:$Y$820)), relacionado, IFERROR(ISNUMBER(SEARCH(disciplina,conceptos)),FALSE) * IFERROR(ISNUMBER(SEARCH(instructor,conceptos)),FALSE), ingresosCuotas,IF( mesNum=0, 0, SUMPRODUCT( --(fechas>=inicio), --(fechas<=fin), --(tipos="INGRESOS"), --(estados="COMPLETADO"), --ISNUMBER(MATCH(categorias,{"CUOTA";"INSCRIPCIÓN";"INSCRIPCION"},0)), --(relacionado>0), montos ) ), ingresosComision,IF( mesNum=0, 0, SUMPRODUCT( --(fechas>=inicio), --(fechas<=fin), --(tipos="INGRESOS"), --(estados="COMPLETADO"), --ISNUMBER(MATCH(categorias,{"COMISIÓN";"COMISION"},0)), --(relacionado>0), montos ) ), egresosComision,IF( mesNum=0, 0, SUMPRODUCT( --(fechas>=inicio), --(fechas<=fin), --(tipos="EGRESOS"), --(estados="COMPLETADO"), --ISNUMBER(MATCH(categorias,{"COMISIÓN";"COMISION"},0)), --(relacionado>0), montos ) ), IF(mesNum=0,"",ingresosCuotas+ingresosComision-egresosComision-paga) )} | X28: Septiembre | Z28: =SUMIFS($P$34:$P$825,$C$34:$C$825,">="&DATE(2026,9,1),$C$34:$C$825,"<"&DATE(2026,10,1),$E$34:$E$825,"INGRESOS",$Y$34:$Y$825,"COMPLETADO") -> 0 | AB28: Octubre | AD28: =SUMIFS($P$34:$P$825,$C$34:$C$825,">="&DATE(2026,10,1),$C$34:$C$825,"<"&DATE(2026,11,1),$E$34:$E$825,"INGRESOS",$Y$34:$Y$825,"COMPLETADO") -> 0 | AF28: Septiembre | AH28: =SUMIFS($P$34:$P$825,$C$34:$C$825,">="&DATE(2026,9,1),$C$34:$C$825,"<"&DATE(2026,10,1),$E$34:$E$825,"EGRESOS",$Y$34:$Y$825,"COMPLETADO") -> 0 | AJ28: Octubre | AL28: =-SUMIFS($P$34:$P$825,$C$34:$C$825,">="&DATE(2026,10,1),$C$34:$C$825,"<"&DATE(2026,11,1),$E$34:$E$825,"EGRESOS",$Y$34:$Y$825,"COMPLETADO") -> 0 | AN28: Septiembre | AP28: =Z28+AH28 -> 0 | AR28: Octubre | AT28: =AD28+AL28 -> 0 | AW28: BALANCE
C29: - | G29: =VLOOKUP(C29,System!$B$17:$H$40,3,FALSE) | P29: =COUNTIFS($AV$34:$AV$825,"<>Abandonado",$AP$34:$AP$825,C29) -> 0 | S29: {=LET( mesTxt,LOWER(TRIM(INDEX($U29:$V29,1,1))), meses,{"enero";"febrero";"marzo";"abril";"mayo";"junio";"julio";"agosto";"septiembre";"octubre";"noviembre";"diciembre"}, mesNum,IFERROR(MATCH(mesTxt,meses,0),0), anio,YEAR(DASHBOARD!$AY$2), inicio,DATE(anio,mesNum,1), fin,EOMONTH(inicio,0), disciplina,LOWER(TRIM(INDEX($C29:$D29,1,1))), instructor,LOWER(TRIM(INDEX($G29:$I29,1,1))), paga,N(INDEX($N29:$O29,1,1)), fechas,$C$34:$C$820, tipos,UPPER(TRIM($E$34:$E$820)), categorias,UPPER(TRIM($G$34:$G$820)), conceptos,LOWER(TRIM($I$34:$I$820)), montos,$P$34:$P$820, estados,UPPER(TRIM($Y$34:$Y$820)), relacionado, IFERROR(ISNUMBER(SEARCH(disciplina,conceptos)),FALSE) * IFERROR(ISNUMBER(SEARCH(instructor,conceptos)),FALSE), ingresosCuotas,IF( mesNum=0, 0, SUMPRODUCT( --(fechas>=inicio), --(fechas<=fin), --(tipos="INGRESOS"), --(estados="COMPLETADO"), --ISNUMBER(MATCH(categorias,{"CUOTA";"INSCRIPCIÓN";"INSCRIPCION"},0)), --(relacionado>0), montos ) ), ingresosComision,IF( mesNum=0, 0, SUMPRODUCT( --(fechas>=inicio), --(fechas<=fin), --(tipos="INGRESOS"), --(estados="COMPLETADO"), --ISNUMBER(MATCH(categorias,{"COMISIÓN";"COMISION"},0)), --(relacionado>0), montos ) ), egresosComision,IF( mesNum=0, 0, SUMPRODUCT( --(fechas>=inicio), --(fechas<=fin), --(tipos="EGRESOS"), --(estados="COMPLETADO"), --ISNUMBER(MATCH(categorias,{"COMISIÓN";"COMISION"},0)), --(relacionado>0), montos ) ), IF(mesNum=0,"",ingresosCuotas+ingresosComision-egresosComision-paga) )} | X29: Noviembre | Z29: =SUMIFS($P$34:$P$825,$C$34:$C$825,">="&DATE(2026,11,1),$C$34:$C$825,"<"&DATE(2026,12,1),$E$34:$E$825,"INGRESOS",$Y$34:$Y$825,"COMPLETADO") -> 0 | AB29: Diciembre | AD29: =SUMIFS($P$34:$P$825,$C$34:$C$825,">="&DATE(2026,12,1),$C$34:$C$825,"<"&DATE(2027,1,1),$E$34:$E$825,"INGRESOS",$Y$34:$Y$825,"COMPLETADO") -> 0 | AF29: Noviembre | AH29: =-SUMIFS($P$34:$P$825,$C$34:$C$825,">="&DATE(2026,11,1),$C$34:$C$825,"<"&DATE(2026,12,1),$E$34:$E$825,"EGRESOS",$Y$34:$Y$825,"COMPLETADO") -> 0 | AJ29: Diciembre | AL29: =-SUMIFS($P$34:$P$825,$C$34:$C$825,">="&DATE(2026,12,1),$C$34:$C$825,"<"&DATE(2027,1,1),$E$34:$E$825,"EGRESOS",$Y$34:$Y$825,"COMPLETADO") -> 0 | AN29: Noviembre | AP29: =Z29+AH29 -> 0 | AR29: Diciembre | AT29: =AD29+AL29 -> 0 | AW29: =AW26-AZ26-X3 -> 322000
C30: - | G30: =VLOOKUP(C30,System!$B$17:$H$40,3,FALSE) | P30: =COUNTIFS($AV$34:$AV$825,"<>Abandonado",$AP$34:$AP$825,C30) -> 0 | S30: {=LET( mesTxt,LOWER(TRIM(INDEX($U30:$V30,1,1))), meses,{"enero";"febrero";"marzo";"abril";"mayo";"junio";"julio";"agosto";"septiembre";"octubre";"noviembre";"diciembre"}, mesNum,IFERROR(MATCH(mesTxt,meses,0),0), anio,YEAR(DASHBOARD!$AY$2), inicio,DATE(anio,mesNum,1), fin,EOMONTH(inicio,0), disciplina,LOWER(TRIM(INDEX($C30:$D30,1,1))), instructor,LOWER(TRIM(INDEX($G30:$I30,1,1))), paga,N(INDEX($N30:$O30,1,1)), fechas,$C$34:$C$820, tipos,UPPER(TRIM($E$34:$E$820)), categorias,UPPER(TRIM($G$34:$G$820)), conceptos,LOWER(TRIM($I$34:$I$820)), montos,$P$34:$P$820, estados,UPPER(TRIM($Y$34:$Y$820)), relacionado, IFERROR(ISNUMBER(SEARCH(disciplina,conceptos)),FALSE) * IFERROR(ISNUMBER(SEARCH(instructor,conceptos)),FALSE), ingresosCuotas,IF( mesNum=0, 0, SUMPRODUCT( --(fechas>=inicio), --(fechas<=fin), --(tipos="INGRESOS"), --(estados="COMPLETADO"), --ISNUMBER(MATCH(categorias,{"CUOTA";"INSCRIPCIÓN";"INSCRIPCION"},0)), --(relacionado>0), montos ) ), ingresosComision,IF( mesNum=0, 0, SUMPRODUCT( --(fechas>=inicio), --(fechas<=fin), --(tipos="INGRESOS"), --(estados="COMPLETADO"), --ISNUMBER(MATCH(categorias,{"COMISIÓN";"COMISION"},0)), --(relacionado>0), montos ) ), egresosComision,IF( mesNum=0, 0, SUMPRODUCT( --(fechas>=inicio), --(fechas<=fin), --(tipos="EGRESOS"), --(estados="COMPLETADO"), --ISNUMBER(MATCH(categorias,{"COMISIÓN";"COMISION"},0)), --(relacionado>0), montos ) ), IF(mesNum=0,"",ingresosCuotas+ingresosComision-egresosComision-paga) )} | X30: TOTAL | AB30: =SUM(Z24:AA29,AD24:AE29) -> 835000 | AF30: TOTAL | AJ30: =SUM(AH24:AI29,AL24:AM29) -> -497000 | AN30: TOTAL | AR30: =SUM(AP24:AQ29,AT24:AU29) -> 338000
P31: =SUM(P18:P30) -> 20
B32: MOVIMIENTOS | AB32: INSCRIPTOS
B33: Id. | C33: Fecha | E33: Tipo | G33: Categoría | I33: Concepto | N33: Contra-parte | P33: Monto | R33: Impuestos | T33: M.P. | V33: Estado Finan. | Y33: Estado | AB33: Id. | AD33: Fecha | AF33: Nombre | AI33: Apellido | AL33: D.N.I. | AN33: Tel. | AP33: Actividad | AR33: Modalidad | AT33: Cuota | AV33: Estado | AY33: Instructor | BB33: Vence
B34: I-1001 | C34: 46221.005 | E34: INGRESOS | G34: CUOTA | I34: Pago de cuota [A-0007] de Emily Nielsen por clases de Arte - niños al profesor Vanesa Rodriguez | N34: 55.400.083 | P34: 5000 | R34: 0 | T34: Transferencia | V34: PAGADO | Y34: COMPLETADO | AB34: A-0025 | AD34: 46219.658 | AF34: Joaquin | AI34: Rodriguez | AL34: 05.555.555 | AN34: 3764239892 | AP34: Arte - niños | AR34: Completo | AT34: 25000 | AV34: Nuevo inscripto | AY34: Vanesa Rodriguez | BB34: 46250
B35: I-0999 | C35: 46221.003 | E35: INGRESOS | G35: CUOTA | I35: Pago de cuota [A-0008] de Enzo Nielsen por clases de Arte - niños al profesor Vanesa Rodriguez | N35: 57.962.209 | P35: 5000 | R35: 0 | T35: Transferencia | V35: PAGADO | Y35: COMPLETADO | AB35: A-0024 | AD35: 46219.657 | AF35: Olivia | AI35: Acosta | AL35: 54.944.974 | AN35: 3764239892 | AP35: Arte - niños | AR35: Completo | AT35: 25000 | AV35: Nuevo inscripto | AY35: Vanesa Rodriguez | BB35: 46250
B36: I-0997 | C36: 46221.001 | E36: INGRESOS | G36: CUOTA | I36: Pago de cuota [A-0007] de Emily Nielsen por clases de Arte - niños al profesor Vanesa Rodriguez | N36: 55.400.083 | P36: 20000 | R36: 0 | T36: Efectivo | V36: PAGADO | Y36: COMPLETADO | AB36: A-0023 | AD36: 46210.712 | AF36: Samuel | AI36: Tomaselli | AL36: 56.595.205 | AN36: 3764848014 | AP36: Arte - niños | AR36: Completo | AT36: 25000 | AV36: Adeudando | AY36: Vanesa Rodriguez | BB36: SIN PAGOS
B37: I-0995 | C37: 46220.999 | E37: INGRESOS | G37: CUOTA | I37: Pago de cuota [A-0008] de Enzo Nielsen por clases de Arte - niños al profesor Vanesa Rodriguez | N37: 57.962.209 | P37: 20000 | R37: 0 | T37: Efectivo | V37: PAGADO | Y37: COMPLETADO | AB37: A-0022 | AD37: 46205.764 | AF37: Sergio Adriel | AI37: Duran | AL37: 55.910.712 | AN37: 3764559297 | AP37: Arte - niños | AR37: Completo | AT37: 25000 | AV37: Al día | AY37: Vanesa Rodriguez | BB37: 46236
B38: I-0989 | C38: 46219.661 | E38: INGRESOS | G38: CUOTA | I38: Pago de cuota [A-0025] de Joaquin Rodriguez por clases de Arte - niños al profesor Vanesa Rodriguez | N38: 05.555.555 | P38: 25000 | R38: 0 | T38: Efectivo | V38: PAGADO | Y38: COMPLETADO | AB38: A-0021 | AD38: 46202 | AF38: Gianna | AI38: Ziliolo | AL38: 59.014.487 | AN38: 3764899469 | AP38: Arte - niños | AR38: Completo | AT38: 25000 | AV38: Al día | AY38: Vanesa Rodriguez | BB38: 46233
B39: I-0988 | C39: 46219.66 | E39: INGRESOS | G39: CUOTA | I39: Pago de cuota [A-0024] de Olivia Acosta por clases de Arte - niños al profesor Vanesa Rodriguez | N39: 54.944.974 | P39: 25000 | R39: 0 | T39: Efectivo | V39: PAGADO | Y39: COMPLETADO | AB39: A-0020 | AD39: 46198.778 | AF39: Noah | AI39: Duarte | AL39: 56.240.322 | AN39: 376520582 | AP39: Arte - niños | AR39: Completo | AT39: 25000 | AV39: Adeudando | AY39: Vanesa Rodriguez | BB39: SIN PAGOS
